Workbook

Sheet README
A1: EnergiaPY.live — Base Maestra V5
A2: V5 consolidates the V4 historical/economic base with latest verified operational, customer, hydrology, climate, macro, household and grid-quality baselines. No synthetic data.
A4: Version | B4: v3 / 11-09-2026
A5: Principio | B5: Nunca completar silenciosamente datos faltantes. Dato oficial, contractual, periodistico y derivado se etiquetan por separado.
A6: Measurements | B6: 1,458 observaciones totales; 1,340 canónicas para métricas.
A7: Prices | B7: 368 referencias/tarifas/precios + tarifas residenciales vigentes y reglas de tarifa social.
A8: Economic transactions | B8: 76 pagos/compensaciones/royalties.
A9: Infrastructure | B9: 149 observaciones de red/capacidad.
A10: Earliest physical history | B10: Acaray/interconexion: 1968/1969 marker; Itaipu generation: 1984; Yacyreta generation: 1994; ANDE billed series: 1983.
A11: Economic history | B11: Itaipu royalties: 1989; ANDE tariff averages: 1990; cession detail loaded: 2013 onward; Yacyreta legal framework from treaty/notes reversales.
A12: Queued | B12: ONS Itaipu hourly, ONS international exchanges, CAMMESA API/files, ANDE/INE GIS and post-2012 EBY monthly backfill.
A13: Canonical rule | B13: For a logical duplicate, only canonical_flag=1 enters metrics. Highest revision_priority wins; alternates remain for audit.
A14: Economic rule | B14: Cession compensation != market sale != tariff != royalty. Never combine them without explicit metric definition.
A15: Recommended production tables | B15: measurements, prices, economic_terms, economic_transactions, infrastructure, source_documents, quality_issues, import_queue, assets, sources.
... A22: Derived averages | B22: Equivalent MW from GWh/time are derived reference averages, not instantaneous measured MW.

Sheet Coverage
A1: dataset | B1: source_start | C1: source_end | D1: loaded_start | E1: loaded_end | F1: status | G1: notes
A2: ANDE billed market | B2: 1983 | C2: 2018 | D2: 1983 | E2: 2018 | F2: loaded/revised | G2: Billed by sector + export; later categories require continuation from newer documents
A3: ANDE SIN gross consumption/demand | B3: 2003 | C3: 2026 | D3: 2003 | E3: 2026-05 + events | F3: loaded | G3: Annual through 2025; monthly Jan-May 2026 currently in seed
A4: ANDE tariff averages | B4: 1990 | C4: 2024 | D4: 1990 | E4: 2024 + current tariff bands | F4: loaded | G4: Tarifa media oficial 1990-2024; Pliego 21 residencial/social vigente cargado. 2025 anual pendiente; proxy provisional en summary.
A5: ANDE transmission/distribution | B5: 2003 | C5: 2023 | D5: 2003 | E5: 2023 | F5: loaded | G5: GIS geometry of individual lines/substations pending
A6: Acaray interconnection/export history | B6: 1969 | C6: current | D6: 1969 contract marker | E6: 2025 export totals | F6: partial | G6: Detailed hourly plant output not public in seed
A7: Itaipu generation | B7: 1984 | C7: current | D7: 1984 | E7: 2002 + 2018-20 supply + 2024-25 generation | F7: partial | G7: ONS hourly backfill will fill major gap
A8: Itaipu royalties | B8: 1989 | C8: current | D8: 1989 | E8: 2026-08 partial | F8: loaded | G8: Annual cash series + current YTD
A9: Itaipu cession compensation | B9: 2013 | C9: current | D9: 2013 | E9: 2026-08 partial | F9: partial | G9: 2019 exact cash cession omitted until source-specific verification
A10: Yacyreta generation/destination | B10: 1994 | C10: current | D10: 1994-08 | E10: 2012-06 + 2020 | F10: partial | G10: Need later monthly backfill/API/public reports
A11: Yacyreta economic/legal | B11: 1973 | C11: current | D11: 1973 legal | E11: 2025 contract + 2024 payments | F11: partial | G11: Need systematic annual compensation/royalties series
A12: ONS Itaipu hourly | B12: dataset availability | C12: current | F12: queued | G12: Official bulk dataset identified; load on server
A13: ONS international exchange | B13: dataset availability | C13: current | F13: queued | G13: Official bulk dataset identified; load on server
A14: CAMMESA SADI/flows | B14: historical/current | C14: current | F14: queued | G14: API + monthly Variables Relevantes identified
A15: BCP FX / IPC for tariff normalization | B15: 1950 IPC / FX historical | C15: current | D15: 1990 | E15: 2025 annual + 2026 current snapshots | F15: loaded_provisional | G15: WDI/IMF annual backfill 1990-2025 + BCP 2026 current. Raw BCP historical reconciliation remains required.
A16: Tariff normalization real/USD | B16: 1990 | C16: 2025 | D16: 1990 | E16: 2025 | F16: loaded | G16: All canonical ANDE PYG/kWh tariffs converted to real-2025 PYG/kWh and USD/MWh using annual macro layer.
A17: ANDE customer categories 2025 | B17: 2025 | C17: 2025 | D17: 2025 | E17: 2025 | F17: loaded | G17: Billed kWh + user counts + derived kWh/user and shares.
A18: ANDE losses and continuity | B18: 2015/current | C18: current | D18: 2024/25 | E18: 2025 + targets | F18: loaded/current-baseline | G18: National loss + Metropolitan DEP/FEP; deeper regional series still desirable.
A19: Itaipu current-year operations | B19: 2026 | C19: current | D19: 2026-01 | E19: 2026-08 | F19: loaded | G19: Jan-Aug production/supply and availability plus derived equivalent average power.
A20: Yacyreta current hydrology/power | B20: current | C20: current | D20: 2026-09-10 | E20: 2026-09-11 | F20: loaded/current-baseline | G20: Current operational/hydrological snapshot; exact homepage power timestamp unavailable.
A21: BCP IMAEP contextual features | B21: historical | C21: current | D21: 2026-01 | E21: 2026-06 | F21: loaded-current | G21: Latest verified numeric report June 2026; historical monthly backfill can follow.
A22: INE household income | B22: EPHC historical | C22: 2025 | D22: 2025 | E22: 2025 | F22: loaded-baseline | G22: 2025 aggregate income and quintiles; microdata not yet fully backfilled.
A23: INE household/equipment census | B23: 2002/2012/2022 | C23: 2022 | D23: 2022 | E23: 2022 | F23: loaded-baseline | G23: Electricity access and energy-relevant appliance penetration.
A24: NOAA ENSO/RONI outlook | B24: 1950/current | C24: current | D24: 2026-09 issue | E24: 9 seasons | F24: loaded-current | G24: September 2026 outlook; full historical ONI/RONI backfill remains optional/high value.
A25: DMH automatic stations | B25: current | C25: current | D25: 2026-09-10 | E25: 2026-09-10 snapshot | F25: partial-current | G25: Orientative web data; production collector should store full 10-min series.
A26: Distributed generation | B26: 2026 | C26: current | D26: regulatory | E26: quantitative pending | F26: framework-loaded | G26: Legal framework active; public installed MW/user series not found.

Sheet Sources
A1: code | B1: name | C1: country | D1: authority_class | E1: base_url | F1: scope
A2: ANDE | B2: Administracion Nacional de Electricidad | C2: PY | D2: OFFICIAL_PRIMARY | E2: https://www.ande.gov.py/ | F2: SIN Paraguay, Acaray, balance, demanda, consumo, perdidas, tarifas, red, exportaciones ANDE
A3: ITAIPU | B3: Itaipu Binacional | C3: PY/BR | D3: OFFICIAL_PRIMARY | E3: https://www.itaipu.gov.py/ | F3: Generacion Itaipu, suministro, Anexo C, royalties, cesion, facturacion
A4: EBY | B4: Entidad Binacional Yacyreta | C4: PY/AR | D4: OFFICIAL_PRIMARY | E4: https://www.eby.gov.py/ | F4: Generacion Yacyreta, entregas SINP/SADI, acuerdos operativos, cesion
A5: ONS | B5: Operador Nacional do Sistema Eletrico | C5: BR | D5: OFFICIAL_PRIMARY | E5: https://dados.ons.org.br/ | F5: Itaipu horario, intercambio internacional, carga Brasil
A6: CAMMESA | B6: Compania Administradora del Mercado Mayorista Electrico | C6: AR | D6: OFFICIAL_PRIMARY | E6: https://cammesaweb.cammesa.com/ | F6: SADI, flujos, variables relevantes, API REST/JSON
A7: BACN | B7: Biblioteca y Archivo Central del Congreso Nacional | C7: PY | D7: OFFICIAL_LEGAL | E7: https://www.bacn.gov.py/ | F7: Tratados y leyes de Itaipu/Yacyreta, terminos economicos
A8: MEF | B8: Ministerio de Economia y Finanzas | C8: PY | D8: OFFICIAL_PRIMARY | E8: https://www.mef.gov.py/ | F8: Transferencias binacionales, royalties, compensaciones
A9: ABC | B9: ABC Color | C9: PY | D9: PRESS_SECONDARY | E9: https://www.abc.com.py/ | F9: Referencias de mercado, precios derivados, contexto comercial
A10: BCP | B10: Banco Central del Paraguay | C10: PY | D10: OFFICIAL_PRIMARY | E10: https://www.bcp.gov.py/ | F10: Tipo de cambio, IPC e indicadores macroeconomicos para normalizacion economica.
A11: WDI_IMF | B11: World Development Indicators / IMF IFS | C11: INTL | D11: OFFICIAL_INTL_SECONDARY | E11: https://data.worldbank.org/ | F11: Backfill y control cruzado de IPC y tipo de cambio anual; BCP sigue siendo la fuente primaria nacional.
A12: NOAA_CPC | B12: NOAA Climate Prediction Center | C12: climate/ENSO | D12: HTML data tables | E12: active | F12: Official ENSO RONI probabilities and strengths
... A14: INE | B14: Instituto Nacional de Estadistica Paraguay | C14: household/demographic | D14: PDF/microdata | E14: active | F14: Census and EPHC

Sheet Source_Documents
A1: document_code | B1: source_code | C1: title | D1: document_type | E1: period_start | F1: period_end | G1: url | H1: authority_class | I1: load_status | J1: notes
A2: ANDE-83-06 | B2: ANDE | C2: Compilacion/Balance de Energia 1983-2006 | D2: historical_statistics | E2: 1983 | F2: 2006 | G2: https://www.ande.gov.py/estadisticas/BalanceEnergia1983-2006/CompilacionEstadistica83-06.pdf | H2: OFFICIAL_PRIMARY | I2: PARTIAL_LOADED | J2: Serie historica antigua; algunos solapes fueron revisados por compilaciones posteriores.
A3: ANDE-90-10 | B3: ANDE | C3: Compilacion Estadistica 1990-2010 | D3: historical_statistics | E3: 1990 | F3: 2010 | G3: https://www.ande.gov.py/documentos_contables/157/compilacion_estadistica_1990-2010.pdf | H3: OFFICIAL_PRIMARY | I3: LOADED | J3: Tarifas y estadisticas historicas.
A4: ANDE-95-15 | B4: ANDE | C4: Compilacion Estadistica 1995-2015 | D4: historical_statistics | E4: 1995 | F4: 2015 | G4: https://www.ande.gov.py/documentos_contables/481/compilacion_estadistica_1995-2015.pdf | H4: OFFICIAL_PRIMARY | I4: REFERENCED | J4: Balance electrico completo 1995-2015.
A5: ANDE-98-18 | B5: ANDE | C5: Compilacion Estadistica 1998-2018 | D5: historical_statistics | E5: 1998 | F5: 2018 | G5: https://www.ande.gov.py/documentos_contables/650/compilacion_estadistica_1998-2018.pdf | H5: OFFICIAL_PRIMARY | I5: LOADED | J5: Energia facturada y exportacion revisadas.
A6: ANDE-03-23 | B6: ANDE | C6: Compilacion Estadistica 2003-2023 | D6: historical_statistics | E6: 2003 | F6: 2023 | G6: https://www.ande.gov.py/finanzas/2.%20COMPILACION%20ESTADISTICA%202003-2023/ANDE%20-%20Compilacion%20Estadistica%202003-2023.pdf | H6: OFFICIAL_PRIMARY | I6: LOADED | J6: Serie principal SIN, balance, infraestructura, tarifas.
A7: ANDE-20-24 | B7: ANDE | C7: Resumen Estadistico 2020-2024 | D7: historical_statistics | E7: 2020 | F7: 2024 | G7: https://www.ande.gov.py/finanzas/ANDE%20-%20Resumen%20Estad%C3%ADstico%202020%20-%202024.pdf | H7: OFFICIAL_PRIMARY | I7: LOADED | J7: Regiones, perdidas, exportacion 2024.
A8: ANDE-BAGP-2025 | B8: ANDE | C8: Balance Anual de Gestion Publica 2025 | D8: annual_report | E8: 2025 | F8: 2025 | G8: https://www.ande.gov.py/finanzas/BAGP%202025%20ANDE.pdf | H8: OFFICIAL_PRIMARY | I8: LOADED | J8: Consumo, demanda maxima y exportacion ENARSA.
A9: ANDE-TARIFF-CURRENT | B9: ANDE | C9: Tarifas vigentes | D9: tariff | E9: current | F9: current | G9: https://www.ande.gov.py/tarifas_vigentes.php | H9: OFFICIAL_PRIMARY | I9: LOADED | J9: Pliego Tarifario 21 vigente: tarifas residenciales normales y reglas de tarifa social incorporadas en v3.
A10: ANDE-ACL-2024 | B10: ANDE | C10: Concurso de venta de energia al ACL Brasil 2738/2024 | D10: market_tender | E10: 2024 | F10: 2024 | G10: https://www.ande.gov.py/interna_contrataciones.php?id=2844 | H10: OFFICIAL_PRIMARY | I10: REFERENCED | J10: Oferta de bloque 100 MW medios Acaray.
A11: ITAIPU-MEM-2002 | B11: ITAIPU | C11: Memoria Anual 2002 | D11: annual_report | E11: 1984 | F11: 2002 | G11: https://www.itaipu.gov.py/sites/default/files/af_df/Memoria%20Anual%202002.pdf | H11: OFFICIAL_PRIMARY | I11: LOADED | J11: Produccion anual 1984-2002.
A12: ITAIPU-MEM-2023 | B12: ITAIPU | C12: Memoria Anual 2023 | D12: annual_report | E12: 2022 | F12: 2023 | G12: https://www.itaipu.gov.py/sites/default/files/u62/Memoria%20Anual%20Itaipu%202023_Espa%C3%B1ol_internet.pdf | H12: OFFICIAL_PRIMARY | I12: LOADED | J12: Suministro mensual 2023 y comparativo 2022.
... A39: WDI-INFL-PRY | B39: WDI_IMF | C39: Inflation consumer prices - Paraguay | D39: macro_backfill | E39: 1990 | F39: 2025 | G39: https://data.worldbank.org/indicator/FP.CPI.TOTL.ZG?locations=PY | H39: OFFICIAL_INTL_SECONDARY | I39: LOADED | J39: Inflacion anual usada para continuidad y control cruzado del CPI.

Sheet Assets
A1: code | B1: name | C1: type | D1: country | E1: lat | F1: lon | G1: notes
A2: PY_SIN | B2: Sistema Interconectado Nacional Paraguay | C2: system | D2: PY | G2: Sistema nacional paraguayo
A3: ITAIPU | B3: Itaipu Binacional | C3: hydro_plant | D3: PY/BR | E3: -25.407 | F3: -54.588 | G3: Coordenada de referencia; validar con capa GIS oficial antes de produccion
A4: YACYRETA | B4: Central Hidroelectrica Yacyreta | C4: hydro_plant | D4: PY/AR | E4: -27.482 | F4: -56.738 | G4: Coordenada de referencia; validar con capa GIS oficial
A5: ACARAY | B5: Central Hidroelectrica Acaray | C5: hydro_plant | D5: PY | E5: -25.455 | F5: -54.632 | G5: Coordenada de referencia; validar con capa GIS oficial
A6: SADI | B6: Sistema Argentino de Interconexion | C6: system | D6: AR | G6: Sistema argentino
A7: BR_SIN | B7: Sistema Interligado Nacional Brasil | C7: system | D7: BR | G7: Sistema brasileño
A8: ENARSA | B8: Energia Argentina S.A. (ENARSA) | C8: counterparty | D8: AR | G8: Comprador/exportacion ANDE
A9: COPEL | B9: COPEL | C9: counterparty | D9: BR | G9: Interconexion historica Acaray-Foz desde 1969
A10: SMD_ITAIPU | B10: Subestacion Margen Derecha Itaipu | C10: substation | D10: PY | G10: Nodo previsto para ventas al ACL Brasil
A11: ACARAY_CONVERTER | B11: Conversora/Interconexion Acaray | C11: interconnection | D11: PY/BR | G11: Intercambio internacional Paraguay-Brasil
A12: SOLAR_PTO_ESPERANZA | B12: Planta Fotovoltaica Puerto Esperanza | C12: solar_plant | D12: PY | G12: GIS oficial pendiente
A13: PY_GRID | B13: Paraguay electricity grid | C13: grid | D13: PY | G13: National grid/quality aggregate asset
A14: PY_GRID_METRO | B14: Metropolitan electricity system | C14: grid_region | D14: PY | G14: Metropolitan quality scope
A15: PY_ECONOMY | B15: Paraguay economy | C15: macro | D15: PY | G15: Macro feature namespace
A16: PY_HOUSEHOLDS | B16: Paraguay households | C16: population | D16: PY | G16: Household/citizenship feature namespace
A17: PY_CLIMATE | B17: Paraguay climate | C17: climate | D17: PY | G17: Climate feature namespace
... A19: ITUZAINGO | B19: Ituzaingo river gauge/port | C19: hydrology_gauge | D19: AR | G19: Reference gauge in EBY operational reports

Sheet Measurements
A1: record_id | B1: period_start | C1: period_end | D1: grain | E1: variable_code | F1: asset_code | G1: origin_code | H1: destination_code | I1: value_source | J1: unit_source | K1: value_normalized | L1: unit_normalized | M1: source_code | N1: authority_class | O1: quality_class | P1: canonical_flag | Q1: revision_priority | R1: source_url | S1: source_file_code | T1: source_published_at | U1: collected_at | V1: notes
A2: R0000001 | B2: 2003-01-01 | C2: 2003-12-31 | D2: year | E2: PY_CONSUMPTION_ENERGY | F2: PY_SIN | G2: PY | H2: PY | I2: 6183000 | J2: MWh | K2: 6183000 | L2: MWh | M2: ANDE | N2: OFFICIAL_PRIMARY | O2: OFFICIAL_AGGREGATE | P2: 1 | Q2: 50 | R2: https://www.ande.gov.py/finanzas/2.%20COMPILACION%20ESTADISTICA%202003-2023/ANDE%20-%20Compilacion%20Estadistica%202003-2023.pdf | S2: ANDE-STAT-2003-2023 | U2: 2026-09-10 23:00:00
A3: R0000002 | B3: 2003-01-01 | C3: 2003-12-31 | D3: year | E3: PY_MAX_DEMAND | F3: PY_SIN | G3: PY | H3: PY | I3: 1191 | J3: MW | K3: 1191 | L3: MW | M3: ANDE | N3: OFFICIAL_PRIMARY | O3: OFFICIAL_AGGREGATE | P3: 1 | Q3: 50 | R3: https://www.ande.gov.py/finanzas/2.%20COMPILACION%20ESTADISTICA%202003-2023/ANDE%20-%20Compilacion%20Estadistica%202003-2023.pdf | S3: ANDE-STAT-2003-2023 | U3: 2026-09-10 23:00:00
A4: R0000003 | B4: 2004-01-01 | C4: 2004-12-31 | D4: year | E4: PY_CONSUMPTION_ENERGY | F4: PY_SIN | G4: PY | H4: PY | I4: 6580000 | J4: MWh | K4: 6580000 | L4: MWh | M4: ANDE | N4: OFFICIAL_PRIMARY | O4: OFFICIAL_AGGREGATE | P4: 1 | Q4: 50 | R4: https://www.ande.gov.py/finanzas/2.%20COMPILACION%20ESTADISTICA%202003-2023/ANDE%20-%20Compilacion%20Estadistica%202003-2023.pdf | S4: ANDE-STAT-2003-2023 | U4: 2026-09-10 23:00:00
A5: R0000004 | B5: 2004-01-01 | C5: 2004-12-31 | D5: year | E5: PY_MAX_DEMAND | F5: PY_SIN | G5: PY | H5: PY | I5: 1241 | J5: MW | K5: 1241 | L5: MW | M5: ANDE | N5: OFFICIAL_PRIMARY | O5: OFFICIAL_AGGREGATE | P5: 1 | Q5: 50 | R5: https://www.ande.gov.py/finanzas/2.%20COMPILACION%20ESTADISTICA%202003-2023/ANDE%20-%20Compilacion%20Estadistica%202003-2023.pdf | S5: ANDE-STAT-2003-2023 | U5: 2026-09-10 23:00:00
A6: R0000005 | B6: 2005-01-01 | C6: 2005-12-31 | D6: year | E6: PY_CONSUMPTION_ENERGY | F6: PY_SIN | G6: PY | H6: PY | I6: 6944000 | J6: MWh | K6: 6944000 | L6: MWh | M6: ANDE | N6: OFFICIAL_PRIMARY | O6: OFFICIAL_AGGREGATE | P6: 1 | Q6: 50 | R6: https://www.ande.gov.py/finanzas/2.%20COMPILACION%20ESTADISTICA%202003-2023/ANDE%20-%20Compilacion%20Estadistica%202003-2023.pdf | S6: ANDE-STAT-2003-2023 | U6: 2026-09-10 23:00:00
A7: R0000006 | B7: 2005-01-01 | C7: 2005-12-31 | D7: year | E7: PY_MAX_DEMAND | F7: PY_SIN | G7: PY | H7: PY | I7: 1354 | J7: MW | K7: 1354 | L7: MW | M7: ANDE | N7: OFFICIAL_PRIMARY | O7: OFFICIAL_AGGREGATE | P7: 1 | Q7: 50 | R7: https://www.ande.gov.py/finanzas/2.%20COMPILACION%20ESTADISTICA%202003-2023/ANDE%20-%20Compilacion%20Estadistica%202003-2023.pdf | S7: ANDE-STAT-2003-2023 | U7: 2026-09-10 23:00:00
A8: R0000007 | B8: 2006-01-01 | C8: 2006-12-31 | D8: year | E8: PY_CONSUMPTION_ENERGY | F8: PY_SIN | G8: PY | H8: PY | I8: 7701000 | J8: MWh | K8: 7701000 | L8: MWh | M8: ANDE | N8: OFFICIAL_PRIMARY | O8: OFFICIAL_AGGREGATE | P8: 1 | Q8: 50 | R8: https://www.ande.gov.py/finanzas/2.%20COMPILACION%20ESTADISTICA%202003-2023/ANDE%20-%20Compilacion%20Estadistica%202003-2023.pdf | S8: ANDE-STAT-2003-2023 | U8: 2026-09-10 23:00:00
A9: R0000008 | B9: 2006-01-01 | C9: 2006-12-31 | D9: year | E9: PY_MAX_DEMAND | F9: PY_SIN | G9: PY | H9: PY | I9: 1450 | J9: MW | K9: 1450 | L9: MW | M9: ANDE | N9: OFFICIAL_PRIMARY | O9: OFFICIAL_AGGREGATE | P9: 1 | Q9: 50 | R9: https://www.ande.gov.py/finanzas/2.%20COMPILACION%20ESTADISTICA%202003-2023/ANDE%20-%20Compilacion%20Estadistica%202003-2023.pdf | S9: ANDE-STAT-2003-2023 | U9: 2026-09-10 23:00:00
A10: R0000009 | B10: 2007-01-01 | C10: 2007-12-31 | D10: year | E10: PY_CONSUMPTION_ENERGY | F10: PY_SIN | G10: PY | H10: PY | I10: 8299000 | J10: MWh | K10: 8299000 | L10: MWh | M10: ANDE | N10: OFFICIAL_PRIMARY | O10: OFFICIAL_AGGREGATE | P10: 1 | Q10: 50 | R10: https://www.ande.gov.py/finanzas/2.%20COMPILACION%20ESTADISTICA%202003-2023/ANDE%20-%20Compilacion%20Estadistica%202003-2023.pdf | S10: ANDE-STAT-2003-2023 | U10: 2026-09-10 23:00:00
A11: R0000010 | B11: 2007-01-01 | C11: 2007-12-31 | D11: year | E11: PY_MAX_DEMAND | F11: PY_SIN | G11: PY | H11: PY | I11: 1521 | J11: MW | K11: 1521 | L11: MW | M11: ANDE | N11: OFFICIAL_PRIMARY | O11: OFFICIAL_AGGREGATE | P11: 1 | Q11: 50 | R11: https://www.ande.gov.py/finanzas/2.%20COMPILACION%20ESTADISTICA%202003-2023/ANDE%20-%20Compilacion%20Estadistica%202003-2023.pdf | S11: ANDE-STAT-2003-2023 | U11: 2026-09-10 23:00:00
A12: R0000011 | B12: 2008-01-01 | C12: 2008-12-31 | D12: year | E12: PY_CONSUMPTION_ENERGY | F12: PY_SIN | G12: PY | H12: PY | I12: 8888000 | J12: MWh | K12: 8888000 | L12: MWh | M12: ANDE | N12: OFFICIAL_PRIMARY | O12: OFFICIAL_AGGREGATE | P12: 1 | Q12: 50 | R12: https://www.ande.gov.py/finanzas/2.%20COMPILACION%20ESTADISTICA%202003-2023/ANDE%20-%20Compilacion%20Estadistica%202003-2023.pdf | S12: ANDE-STAT-2003-2023 | U12: 2026-09-10 23:00:00
A13: R0000012 | B13: 2008-01-01 | C13: 2008-12-31 | D13: year | E13: PY_MAX_DEMAND | F13: PY_SIN | G13: PY | H13: PY | I13: 1648 | J13: MW | K13: 1648 | L13: MW | M13: ANDE | N13: OFFICIAL_PRIMARY | O13: OFFICIAL_AGGREGATE | P13: 1 | Q13: 50 | R13: https://www.ande.gov.py/finanzas/2.%20COMPILACION%20ESTADISTICA%202003-2023/ANDE%20-%20Compilacion%20Estadistica%202003-2023.pdf | S13: ANDE-STAT-2003-2023 | U13: 2026-09-10 23:00:00
... A37: R0000036 | B37: 2020-01-01 | C37: 2020-12-31 | D37: year | E37: PY_MAX_DEMAND | F37: PY_SIN | G37: PY | H37: PY | I37: 3563 | J37: MW | K37: 3563 | L37: MW | M37: ANDE | N37: OFFICIAL_PRIMARY | O37: OFFICIAL_AGGREGATE | P37: 1 | Q37: 50 | R37: https://www.ande.gov.py/finanzas/2.%20COMPILACION%20ESTADISTICA%202003-2023/ANDE%20-%20Compilacion%20Estadistica%202003-2023.pdf | S37: ANDE-STAT-2003-2023 | U37: 2026-09-10 23:00:00
A38: R0000037 | B38: 2020-01-01 | C38: 2020-12-31 | D38: year | E38: PY_LOAD_FACTOR | F38: PY_SIN | G38: PY | H38: PY | I38: 57.5 | J38: percent | K38: 57.5 | L38: percent | M38: ANDE | N38: OFFICIAL_PRIMARY | O38: OFFICIAL_AGGREGATE | P38: 1 | Q38: 50 | R38: https://www.ande.gov.py/finanzas/2.%20COMPILACION%20ESTADISTICA%202003-2023/ANDE%20-%20Compilacion%20Estadistica%202003-2023.pdf | S38: ANDE-STAT-2003-2023 | U38: 2026-09-10 23:00:00 | V38: Factor de carga publicado.
A39: R0000038 | B39: 2021-01-01 | C39: 2021-12-31 | D39: year | E39: PY_CONSUMPTION_ENERGY | F39: PY_SIN | G39: PY | H39: PY | I39: 18583322 | J39: MWh | K39: 18583322 | L39: MWh | M39: ANDE | N39: OFFICIAL_PRIMARY | O39: OFFICIAL_AGGREGATE | P39: 0 | Q39: 50 | R39: https://www.ande.gov.py/finanzas/2.%20COMPILACION%20ESTADISTICA%202003-2023/ANDE%20-%20Compilacion%20Estadistica%202003-2023.pdf | S39: ANDE-STAT-2003-2023 | U39: 2026-09-10 23:00:00
A40: R0000039 | B40: 2021-01-01 | C40: 2021-12-31 | D40: year | E40: PY_MAX_DEMAND | F40: PY_SIN | G40: PY | H40: PY | I40: 3777 | J40: MW | K40: 3777 | L40: MW | M40: ANDE | N40: OFFICIAL_PRIMARY | O40: OFFICIAL_AGGREGATE | P40: 1 | Q40: 50 | R40: https://www.ande.gov.py/finanzas/2.%20COMPILACION%20ESTADISTICA%202003-2023/ANDE%20-%20Compilacion%20Estadistica%202003-2023.pdf | S40: ANDE-STAT-2003-2023 | U40: 2026-09-10 23:00:00
A41: R0000040 | B41: 2021-01-01 | C41: 2021-12-31 | D41: year | E41: PY_LOAD_FACTOR | F41: PY_SIN | G41: PY | H41: PY | I41: 56.2 | J41: percent | K41: 56.2 | L41: percent | M41: ANDE | N41: OFFICIAL_PRIMARY | O41: OFFICIAL_AGGREGATE | P41: 1 | Q41: 50 | R41: https://www.ande.gov.py/finanzas/2.%20COMPILACION%20ESTADISTICA%202003-2023/ANDE%20-%20Compilacion%20Estadistica%202003-2023.pdf | S41: ANDE-STAT-2003-2023 | U41: 2026-09-10 23:00:00 | V41: Factor de carga publicado.
A42: R0000041 | B42: 2022-01-01 | C42: 2022-12-31 | D42: year | E42: PY_CONSUMPTION_ENERGY | F42: PY_SIN | G42: PY | H42: PY | I42: 19634614 | J42: MWh | K42: 19634614 | L42: MWh | M42: ANDE | N42: OFFICIAL_PRIMARY | O42: OFFICIAL_AGGREGATE | P42: 0 | Q42: 50 | R42: https://www.ande.gov.py/finanzas/2.%20COMPILACION%20ESTADISTICA%202003-2023/ANDE%20-%20Compilacion%20Estadistica%202003-2023.pdf | S42: ANDE-STAT-2003-2023 | U42: 2026-09-10 23:00:00
A43: R0000042 | B43: 2022-01-01 | C43: 2022-12-31 | D43: year | E43: PY_MAX_DEMAND | F43: PY_SIN | G43: PY | H43: PY | I43: 4270 | J43: MW | K43: 4270 | L43: MW | M43: ANDE | N43: OFFICIAL_PRIMARY | O43: OFFICIAL_AGGREGATE | P43: 1 | Q43: 50 | R43: https://www.ande.gov.py/finanzas/2.%20COMPILACION%20ESTADISTICA%202003-2023/ANDE%20-%20Compilacion%20Estadistica%202003-2023.pdf | S43: ANDE-STAT-2003-2023 | U43: 2026-09-10 23:00:00
A44: R0000043 | B44: 2022-01-01 | C44: 2022-12-31 | D44: year | E44: PY_LOAD_FACTOR | F44: PY_SIN | G44: PY | H44: PY | I44: 52.5 | J44: percent | K44: 52.5 | L44: percent | M44: ANDE | N44: OFFICIAL_PRIMARY | O44: OFFICIAL_AGGREGATE | P44: 1 | Q44: 50 | R44: https://www.ande.gov.py/finanzas/2.%20COMPILACION%20ESTADISTICA%202003-2023/ANDE%20-%20Compilacion%20Estadistica%202003-2023.pdf | S44: ANDE-STAT-2003-2023 | U44: 2026-09-10 23:00:00 | V44: Factor de carga publicado.
A45: R0000044 | B45: 2023-01-01 | C45: 2023-12-31 | D45: year | E45: PY_CONSUMPTION_ENERGY | F45: PY_SIN | G45: PY | H45: PY | I45: 22078726 | J45: MWh | K45: 22078726 | L45: MWh | M45: ANDE | N45: OFFICIAL_PRIMARY | O45: OFFICIAL_AGGREGATE | P45: 0 | Q45: 50 | R45: https://www.ande.gov.py/finanzas/2.%20COMPILACION%20ESTADISTICA%202003-2023/ANDE%20-%20Compilacion%20Estadistica%202003-2023.pdf | S45: ANDE-STAT-2003-2023 | U45: 2026-09-10 23:00:00
A46: R0000045 | B46: 2023-01-01 | C46: 2023-12-31 | D46: year | E46: PY_MAX_DEMAND | F46: PY_SIN | G46: PY | H46: PY | I46: 4744 | J46: MW | K46: 4744 | L46: MW | M46: ANDE | N46: OFFICIAL_PRIMARY | O46: OFFICIAL_AGGREGATE | P46: 1 | Q46: 50 | R46: https://www.ande.gov.py/finanzas/2.%20COMPILACION%20ESTADISTICA%202003-2023/ANDE%20-%20Compilacion%20Estadistica%202003-2023.pdf | S46: ANDE-STAT-2003-2023 | U46: 2026-09-10 23:00:00
A47: R0000046 | B47: 2023-01-01 | C47: 2023-12-31 | D47: year | E47: PY_LOAD_FACTOR | F47: PY_SIN | G47: PY | H47: PY | I47: 53.1 | J47: percent | K47: 53.1 | L47: percent | M47: ANDE | N47: OFFICIAL_PRIMARY | O47: OFFICIAL_AGGREGATE | P47: 1 | Q47: 50 | R47: https://www.ande.gov.py/finanzas/2.%20COMPILACION%20ESTADISTICA%202003-2023/ANDE%20-%20Compilacion%20Estadistica%202003-2023.pdf | S47: ANDE-STAT-2003-2023 | U47: 2026-09-10 23:00:00 | V47: Factor de carga publicado.
A48: R0000047 | B48: 2024-01-01 | C48: 2024-12-31 | D48: year | E48: PY_CONSUMPTION_ENERGY | F48: PY_SIN | G48: PY | H48: PY | I48: 26154488 | J48: MWh | K48: 26154488 | L48: MWh | M48: ANDE | N48: OFFICIAL_PRIMARY | O48: OFFICIAL_AGGREGATE | P48: 1 | Q48: 50 | R48: https://www.ande.gov.py/finanzas/ANDE%20-%20Resumen%20Estad%C3%ADstico%202020%20-%202024.pdf | S48: ANDE-STAT-2020-2024 | U48: 2026-09-10 23:00:00
A49: R0000048 | B49: 2024-01-01 | C49: 2024-12-31 | D49: year | E49: PY_MAX_DEMAND | F49: PY_SIN | G49: PY | H49: PY | I49: 5027 | J49: MW | K49: 5027 | L49: MW | M49: ANDE | N49: OFFICIAL_PRIMARY | O49: OFFICIAL_AGGREGATE | P49: 1 | Q49: 50 | R49: https://www.ande.gov.py/finanzas/ANDE%20-%20Resumen%20Estad%C3%ADstico%202020%20-%202024.pdf | S49: ANDE-STAT-2020-2024 | U49: 2026-09-10 23:00:00
A50: R0000049 | B50: 2024-01-01 | C50: 2024-12-31 | D50: year | E50: PY_LOAD_FACTOR | F50: PY_SIN | G50: PY | H50: PY | I50: 59.39 | J50: percent | K50: 59.39 | L50: percent | M50: ANDE | N50: OFFICIAL_PRIMARY | O50: OFFICIAL_AGGREGATE | P50: 1 | Q50: 50 | R50: https://www.ande.gov.py/finanzas/ANDE%20-%20Resumen%20Estad%C3%ADstico%202020%20-%202024.pdf | S50: ANDE-STAT-2020-2024 | U50: 2026-09-10 23:00:00 | V50: Factor de carga publicado.
A51: R0000050 | B51: 2025-01-01 | C51: 2025-12-31 | D51: year | E51: PY_CONSUMPTION_ENERGY | F51: PY_SIN | G51: PY | H51: PY | I51: 29418538 | J51: MWh | K51: 29418538 | L51: MWh | M51: ANDE | N51: OFFICIAL_PRIMARY | O51: OFFICIAL_AGGREGATE | P51: 1 | Q51: 50 | R51: https://www.ande.gov.py/finanzas/BAGP%202025%20ANDE.pdf | S51: ANDE-BAGP-2025 | U51: 2026-09-10 23:00:00 | V51: 2025: total exacto de BAGP; nota de prensa redondea a 29.419 GWh.
A52: R0000051 | B52: 2025-01-01 | C52: 2025-12-31 | D52: year | E52: PY_MAX_DEMAND | F52: PY_SIN | G52: PY | H52: PY | I52: 5280 | J52: MW | K52: 5280 | L52: MW | M52: ANDE | N52: OFFICIAL_PRIMARY | O52: OFFICIAL_AGGREGATE | P52: 1 | Q52: 50 | R52: https://www.ande.gov.py/finanzas/BAGP%202025%20ANDE.pdf | S52: ANDE-BAGP-2025 | U52: 2026-09-10 23:00:00 | V52: 2025: total exacto de BAGP; nota de prensa redondea a 29.419 GWh.
A53: R0000052 | B53: 2025-01-01 | C53: 2025-12-31 | D53: year | E53: PY_LOAD_FACTOR | F53: PY_SIN | G53: PY | H53: PY | I53: 63.6 | J53: percent | K53: 63.6 | L53: percent | M53: ANDE | N53: OFFICIAL_PRIMARY | O53: OFFICIAL_AGGREGATE | P53: 1 | Q53: 50 | R53: https://www.ande.gov.py/finanzas/BAGP%202025%20ANDE.pdf | S53: ANDE-BAGP-2025 | U53: 2026-09-10 23:00:00 | V53: Factor de carga publicado.
A54: R0000053 | B54: 2020-01-01 | C54: 2020-12-31 | D54: year | E54: PY_REGION_ENERGY | F54: PY_REGION_METROPOLITANO | G54: PY | H54: PY | I54: 9312851 | J54: MWh | K54: 9312851 | L54: MWh | M54: ANDE | N54: OFFICIAL_PRIMARY | O54: OFFICIAL_AGGREGATE | P54: 1 | Q54: 50 | R54: https://www.ande.gov.py/finanzas/ANDE%20-%20Resumen%20Estad%C3%ADstico%202020%20-%202024.pdf | S54: ANDE-STAT-2020-2024 | U54: 2026-09-10 23:00:00 | V54: Sistema/region: Metropolitano.
A55: R0000054 | B55: 2021-01-01 | C55: 2021-12-31 | D55: year | E55: PY_REGION_ENERGY | F55: PY_REGION_METROPOLITANO | G55: PY | H55: PY | I55: 9543744 | J55: MWh | K55: 9543744 | L55: MWh | M55: ANDE | N55: OFFICIAL_PRIMARY | O55: OFFICIAL_AGGREGATE | P55: 1 | Q55: 50 | R55: https://www.ande.gov.py/finanzas/ANDE%20-%20Resumen%20Estad%C3%ADstico%202020%20-%202024.pdf | S55: ANDE-STAT-2020-2024 | U55: 2026-09-10 23:00:00 | V55: Sistema/region: Metropolitano.
A56: R0000055 | B56: 2022-01-01 | C56: 2022-12-31 | D56: year | E56: PY_REGION_ENERGY | F56: PY_REGION_METROPOLITANO | G56: PY | H56: PY | I56: 9964357 | J56: MWh | K56: 9964357 | L56: MWh | M56: ANDE | N56: OFFICIAL_PRIMARY | O56: OFFICIAL_AGGREGATE | P56: 1 | Q56: 50 | R56: https://www.ande.gov.py/finanzas/ANDE%20-%20Resumen%20Estad%C3%ADstico%202020%20-%202024.pdf | S56: ANDE-STAT-2020-2024 | U56: 2026-09-10 23:00:00 | V56: Sistema/region: Metropolitano.
A57: R0000056 | B57: 2023-01-01 | C57: 2023-12-31 | D57: year | E57: PY_REGION_ENERGY | F57: PY_REGION_METROPOLITANO | G57: PY | H57: PY | I57: 11174060 | J57: MWh | K57: 11174060 | L57: MWh | M57: ANDE | N57: OFFICIAL_PRIMARY | O57: OFFICIAL_AGGREGATE | P57: 1 | Q57: 50 | R57: https://www.ande.gov.py/finanzas/ANDE%20-%20Resumen%20Estad%C3%ADstico%202020%20-%202024.pdf | S57: ANDE-STAT-2020-2024 | U57: 2026-09-10 23:00:00 | V57: Sistema/region: Metropolitano.
A58: R0000057 | B58: 2024-01-01 | C58: 2024-12-31 | D58: year | E58: PY_REGION_ENERGY | F58: PY_REGION_METROPOLITANO | G58: PY | H58: PY | I58: 12291090 | J58: MWh | K58: 12291090 | L58: MWh | M58: ANDE | N58: OFFICIAL_PRIMARY | O58: OFFICIAL_AGGREGATE | P58: 1 | Q58: 50 | R58: https://www.ande.gov.py/finanzas/ANDE%20-%20Resumen%20Estad%C3%ADstico%202020%20-%202024.pdf | S58: ANDE-STAT-2020-2024 | U58: 2026-09-10 23:00:00 | V58: Sistema/region: Metropolitano.
A59: R0000058 | B59: 2020-01-01 | C59: 2020-12-31 | D59: year | E59: PY_REGION_ENERGY | F59: PY_REGION_CENTRAL | G59: PY | H59: PY | I59: 1833781 | J59: MWh | K59: 1833781 | L59: MWh | M59: ANDE | N59: OFFICIAL_PRIMARY | O59: OFFICIAL_AGGREGATE | P59: 1 | Q59: 50 | R59: https://www.ande.gov.py/finanzas/ANDE%20-%20Resumen%20Estad%C3%ADstico%202020%20-%202024.pdf | S59: ANDE-STAT-2020-2024 | U59: 2026-09-10 23:00:00 | V59: Sistema/region: Central.
A60: R0000059 | B60: 2021-01-01 | C60: 2021-12-31 | D60: year | E60: PY_REGION_ENERGY | F60: PY_REGION_CENTRAL | G60: PY | H60: PY | I60: 1985053 | J60: MWh | K60: 1985053 | L60: MWh | M60: ANDE | N60: OFFICIAL_PRIMARY | O60: OFFICIAL_AGGREGATE | P60: 1 | Q60: 50 | R60: https://www.ande.gov.py/finanzas/ANDE%20-%20Resumen%20Estad%C3%ADstico%202020%20-%202024.pdf | S60: ANDE-STAT-2020-2024 | U60: 2026-09-10 23:00:00 | V60: Sistema/region: Central.
A61: R0000060 | B61: 2022-01-01 | C61: 2022-12-31 | D61: year | E61: PY_REGION_ENERGY | F61: PY_REGION_CENTRAL | G61: PY | H61: PY | I61: 2373625 | J61: MWh | K61: 2373625 | L61: MWh | M61: ANDE | N61: OFFICIAL_PRIMARY | O61: OFFICIAL_AGGREGATE | P61: 1 | Q61: 50 | R61: https://www.ande.gov.py/finanzas/ANDE%20-%20Resumen%20Estad%C3%ADstico%202020%20-%202024.pdf | S61: ANDE-STAT-2020-2024 | U61: 2026-09-10 23:00:00 | V61: Sistema/region: Central.
... A142: R0000141 | B142: 2026-01-01 | C142: 2026-05-31 | D142: period | E142: PY_CONSUMPTION_ENERGY_YTD | F142: PY_SIN | G142: PY | H142: PY | I142: 14587100 | J142: MWh | K142: 14587100 | L142: MWh | M142: ANDE | N142: OFFICIAL_PRIMARY | O142: OFFICIAL_AGGREGATE | P142: 1 | Q142: 50 | R142: https://www.ande.gov.py/interna.php?id=15361 | S142: ANDE-MAY-2026 | U142: 2026-09-10 23:00:00 | V142: Acumulado enero-mayo publicado por ANDE.
A143: R0000142 | B143: 2025-08-14 06:23:00 | C143: 2025-08-14 06:23:00 | D143: event | E143: PY_DEMAND | F143: PY_SIN | G143: PY | H143: PY | I143: 3070 | J143: MW | K143: 3070 | L143: MW | M143: ANDE | N143: OFFICIAL_PRIMARY | O143: OFFICIAL_MEASURED | P143: 1 | Q143: 50 | R143: https://www.ande.gov.py/interna.php?id=14173 | U143: 2026-09-10 23:00:00 | V143: Evento: Avería en interruptor 220 kV de Acaray; demanda reportada al momento del inconveniente. ANDE indica abastecimiento principalmente por Itaipú; no desglosa MW por central.
A144: R0000143 | B144: 2025-12-15 14:12:00 | C144: 2025-12-15 14:12:00 | D144: event | E144: PY_DEMAND | F144: PY_SIN | G144: PY | H144: PY | I144: 5280 | J144: MW | K144: 5280 | L144: MW | M144: ANDE | N144: OFFICIAL_PRIMARY | O144: OFFICIAL_MEASURED | P144: 1 | Q144: 50 | R144: https://www.ande.gov.py/interna.php?id=14816 | U144: 2026-09-10 23:00:00 | V144: Récord: Nuevo récord histórico de demanda instantánea 2025. La suma de aportes + exportación puede diferir conceptualmente de demanda según convención de signo/medición.
A145: R0000144 | B145: 2025-12-15 14:12:00 | C145: 2025-12-15 14:12:00 | D145: event | E145: POWER_TO_PY | F145: ITAIPU | G145: ITAIPU | H145: PY | I145: 3745 | J145: MW | K145: 3745 | L145: MW | M145: ANDE | N145: OFFICIAL_PRIMARY | O145: OFFICIAL_MEASURED | P145: 1 | Q145: 50 | R145: https://www.ande.gov.py/interna.php?id=14816 | U145: 2026-09-10 23:00:00 | V145: Récord: Nuevo récord histórico de demanda instantánea 2025. La suma de aportes + exportación puede diferir conceptualmente de demanda según convención de signo/medición.
A146: R0000145 | B146: 2025-12-15 14:12:00 | C146: 2025-12-15 14:12:00 | D146: event | E146: POWER_TO_PY | F146: YACYRETA | G146: YACYRETA | H146: PY | I146: 1419 | J146: MW | K146: 1419 | L146: MW | M146: ANDE | N146: OFFICIAL_PRIMARY | O146: OFFICIAL_MEASURED | P146: 1 | Q146: 50 | R146: https://www.ande.gov.py/interna.php?id=14816 | U146: 2026-09-10 23:00:00 | V146: Récord: Nuevo récord histórico de demanda instantánea 2025. La suma de aportes + exportación puede diferir conceptualmente de demanda según convención de signo/medición.
A147: R0000146 | B147: 2025-12-15 14:12:00 | C147: 2025-12-15 14:12:00 | D147: event | E147: POWER_TO_PY | F147: ACARAY | G147: ACARAY | H147: PY | I147: 132 | J147: MW | K147: 132 | L147: MW | M147: ANDE | N147: OFFICIAL_PRIMARY | O147: OFFICIAL_MEASURED | P147: 1 | Q147: 50 | R147: https://www.ande.gov.py/interna.php?id=14816 | U147: 2026-09-10 23:00:00 | V147: Récord: Nuevo récord histórico de demanda instantánea 2025. La suma de aportes + exportación puede diferir conceptualmente de demanda según convención de signo/medición.
A148: R0000147 | B148: 2025-12-15 14:12:00 | C148: 2025-12-15 14:12:00 | D148: event | E148: PY_EXPORT_POWER | F148: PY_SIN | G148: PY | H148: EXTERNAL | I148: 16 | J148: MW | K148: 16 | L148: MW | M148: ANDE | N148: OFFICIAL_PRIMARY | O148: OFFICIAL_MEASURED | P148: 1 | Q148: 50 | R148: https://www.ande.gov.py/interna.php?id=14816 | U148: 2026-09-10 23:00:00 | V148: Récord: Nuevo récord histórico de demanda instantánea 2025. La suma de aportes + exportación puede diferir conceptualmente de demanda según convención de signo/medición.
A149: R0000148 | B149: 2026-01-26 00:00:00 | C149: 2026-01-26 00:00:00 | D149: event | E149: PY_DEMAND | F149: PY_SIN | G149: PY | H149: PY | I149: 5752 | J149: MW | K149: 5752 | L149: MW | M149: ANDE | N149: OFFICIAL_PRIMARY | O149: OFFICIAL_MEASURED | P149: 1 | Q149: 50 | R149: https://www.ande.gov.py/interna.php?id=14950 | U149: 2026-09-10 23:00:00 | V149: Récord: Récord histórico del SIN reportado por ANDE. No se publicó en esa nota el reparto instantáneo por central.
A150: R0000149 | B150: 2026-02-18 14:05:00 | C150: 2026-02-18 14:05:00 | D150: event | E150: PY_DEMAND | F150: PY_SIN | G150: PY | H150: PY | I150: 5690 | J150: MW | K150: 5690 | L150: MW | M150: ANDE | N150: OFFICIAL_PRIMARY | O150: OFFICIAL_MEASURED | P150: 1 | Q150: 50 | R150: https://www.ande.gov.py/interna.php?id=14999 | U150: 2026-09-10 23:00:00 | V150: Pico diario: Máximo de consumo del día antes del incidente. Sistema sin perturbaciones.
A151: R0000150 | B151: 2026-02-18 15:18:00 | C151: 2026-02-18 15:18:00 | D151: event | E151: PY_DEMAND | F151: PY_SIN | G151: PY | H151: PY | I151: 5330 | J151: MW | K151: 5330 | L151: MW | M151: ANDE | N151: OFFICIAL_PRIMARY | O151: OFFICIAL_MEASURED | P151: 1 | Q151: 50 | R151: https://www.ande.gov.py/interna.php?id=14999 | U151: 2026-09-10 23:00:00 | V151: Evento: Carga del sistema al inicio de la perturbación. Suma de las tres centrales = 5.330 MW, consistente con la carga reportada.
A152: R0000151 | B152: 2026-02-18 15:18:00 | C152: 2026-02-18 15:18:00 | D152: event | E152: POWER_TO_PY | F152: ITAIPU | G152: ITAIPU | H152: PY | I152: 3746 | J152: MW | K152: 3746 | L152: MW | M152: ANDE | N152: OFFICIAL_PRIMARY | O152: OFFICIAL_MEASURED | P152: 1 | Q152: 50 | R152: https://www.ande.gov.py/interna.php?id=14999 | U152: 2026-09-10 23:00:00 | V152: Evento: Carga del sistema al inicio de la perturbación. Suma de las tres centrales = 5.330 MW, consistente con la carga reportada.
A153: R0000152 | B153: 2026-02-18 15:18:00 | C153: 2026-02-18 15:18:00 | D153: event | E153: POWER_TO_PY | F153: YACYRETA | G153: YACYRETA | H153: PY | I153: 1454 | J153: MW | K153: 1454 | L153: MW | M153: ANDE | N153: OFFICIAL_PRIMARY | O153: OFFICIAL_MEASURED | P153: 1 | Q153: 50 | R153: https://www.ande.gov.py/interna.php?id=14999 | U153: 2026-09-10 23:00:00 | V153: Evento: Carga del sistema al inicio de la perturbación. Suma de las tres centrales = 5.330 MW, consistente con la carga reportada.
A154: R0000153 | B154: 2026-02-18 15:18:00 | C154: 2026-02-18 15:18:00 | D154: event | E154: POWER_TO_PY | F154: ACARAY | G154: ACARAY | H154: PY | I154: 130 | J154: MW | K154: 130 | L154: MW | M154: ANDE | N154: OFFICIAL_PRIMARY | O154: OFFICIAL_MEASURED | P154: 1 | Q154: 50 | R154: https://www.ande.gov.py/interna.php?id=14999 | U154: 2026-09-10 23:00:00 | V154: Evento: Carga del sistema al inicio de la perturbación. Suma de las tres centrales = 5.330 MW, consistente con la carga reportada.
... A158: R0000157 | B158: 2022-01-01 | C158: 2022-07-31 | D158: period | E158: PY_CONSUMPTION_ENERGY | F158: PY_SIN | G158: PY | H158: PY | I158: 11583364 | J158: MWh | K158: 11583364 | L158: MWh | M158: ANDE | N158: OFFICIAL_PRIMARY | O158: OFFICIAL_AGGREGATE | P158: 1 | Q158: 50 | R158: https://www.ande.gov.py/interna.php?id=10223 | U158: 2026-09-10 23:00:00 | V158: Acumulado enero-julio 2022 publicado por ANDE.
A159: R0000158 | B159: 1994-08-01 | C159: 1994-08-31 | D159: month | E159: YACYRETA_NET_ENERGY | F159: YACYRETA | G159: YACYRETA | H159: TOTAL | I159: 826 | J159: MWh | K159: 826 | L159: MWh | M159: EBY | N159: OFFICIAL_PRIMARY | O159: OFFICIAL_AGGREGATE | P159: 1 | Q159: 50 | R159: https://www.eby.gov.py/wp-content/uploads/2019/12/YacyretaEnergiasMensualesDesdePuestaenMarcha.pdf | S159: EBY-MONTHLY-1994-2012 | U159: 2026-09-10 23:00:00 | V159: Energia mensual Yacyreta desde puesta en marcha.
A160: R0000159 | B160: 1994-08-01 | C160: 1994-08-31 | D160: month | E160: ENERGY_TO_ARGENTINA | F160: YACYRETA | G160: YACYRETA | H160: SADI | I160: 826 | J160: MWh | K160: 826 | L160: MWh | M160: EBY | N160: OFFICIAL_PRIMARY | O160: OFFICIAL_AGGREGATE | P160: 1 | Q160: 50 | R160: https://www.eby.gov.py/wp-content/uploads/2019/12/YacyretaEnergiasMensualesDesdePuestaenMarcha.pdf | S160: EBY-MONTHLY-1994-2012 | U160: 2026-09-10 23:00:00 | V160: Energia mensual entregada al SADI.
A161: R0000160 | B161: 1994-08-01 | C161: 1994-08-31 | D161: month | E161: ENERGY_TO_PY | F161: YACYRETA | G161: YACYRETA | H161: SINP | I161: 0 | J161: MWh | K161: 0 | L161: MWh | M161: EBY | N161: OFFICIAL_PRIMARY | O161: OFFICIAL_AGGREGATE | P161: 1 | Q161: 50 | R161: https://www.eby.gov.py/wp-content/uploads/2019/12/YacyretaEnergiasMensualesDesdePuestaenMarcha.pdf | S161: EBY-MONTHLY-1994-2012 | U161: 2026-09-10 23:00:00 | V161: Energia mensual entregada al SINP.
A162: R0000161 | B162: 1994-09-01 | C162: 1994-09-30 | D162: month | E162: YACYRETA_NET_ENERGY | F162: YACYRETA | G162: YACYRETA | H162: TOTAL | I162: 55808 | J162: MWh | K162: 55808 | L162: MWh | M162: EBY | N162: OFFICIAL_PRIMARY | O162: OFFICIAL_AGGREGATE | P162: 1 | Q162: 50 | R162: https://www.eby.gov.py/wp-content/uploads/2019/12/YacyretaEnergiasMensualesDesdePuestaenMarcha.pdf | S162: EBY-MONTHLY-1994-2012 | U162: 2026-09-10 23:00:00 | V162: Energia mensual Yacyreta desde puesta en marcha.
A163: R0000162 | B163: 1994-09-01 | C163: 1994-09-30 | D163: month | E163: ENERGY_TO_ARGENTINA | F163: YACYRETA | G163: YACYRETA | H163: SADI | I163: 55808 | J163: MWh | K163: 55808 | L163: MWh | M163: EBY | N163: OFFICIAL_PRIMARY | O163: OFFICIAL_AGGREGATE | P163: 1 | Q163: 50 | R163: https://www.eby.gov.py/wp-content/uploads/2019/12/YacyretaEnergiasMensualesDesdePuestaenMarcha.pdf | S163: EBY-MONTHLY-1994-2012 | U163: 2026-09-10 23:00:00 | V163: Energia mensual entregada al SADI.
A164: R0000163 | B164: 1994-09-01 | C164: 1994-09-30 | D164: month | E164: ENERGY_TO_PY | F164: YACYRETA | G164: YACYRETA | H164: SINP | I164: 0 | J164: MWh | K164: 0 | L164: MWh | M164: EBY | N164: OFFICIAL_PRIMARY | O164: OFFICIAL_AGGREGATE | P164: 1 | Q164: 50 | R164: https://www.eby.gov.py/wp-content/uploads/2019/12/YacyretaEnergiasMensualesDesdePuestaenMarcha.pdf | S164: EBY-MONTHLY-1994-2012 | U164: 2026-09-10 23:00:00 | V164: Energia mensual entregada al SINP.
A165: R0000164 | B165: 1994-10-01 | C165: 1994-10-31 | D165: month | E165: YACYRETA_NET_ENERGY | F165: YACYRETA | G165: YACYRETA | H165: TOTAL | I165: 62043 | J165: MWh | K165: 62043 | L165: MWh | M165: EBY | N165: OFFICIAL_PRIMARY | O165: OFFICIAL_AGGREGATE | P165: 1 | Q165: 50 | R165: https://www.eby.gov.py/wp-content/uploads/2019/12/YacyretaEnergiasMensualesDesdePuestaenMarcha.pdf | S165: EBY-MONTHLY-1994-2012 | U165: 2026-09-10 23:00:00 | V165: Energia mensual Yacyreta desde puesta en marcha.
A166: R0000165 | B166: 1994-10-01 | C166: 1994-10-31 | D166: month | E166: ENERGY_TO_ARGENTINA | F166: YACYRETA | G166: YACYRETA | H166: SADI | I166: 62043 | J166: MWh | K166: 62043 | L166: MWh | M166: EBY | N166: OFFICIAL_PRIMARY | O166: OFFICIAL_AGGREGATE | P166: 1 | Q166: 50 | R166: https://www.eby.gov.py/wp-content/uploads/2019/12/YacyretaEnergiasMensualesDesdePuestaenMarcha.pdf | S166: EBY-MONTHLY-1994-2012 | U166: 2026-09-10 23:00:00 | V166: Energia mensual entregada al SADI.
A167: R0000166 | B167: 1994-10-01 | C167: 1994-10-31 | D167: month | E167: ENERGY_TO_PY | F167: YACYRETA | G167: YACYRETA | H167: SINP | I167: 0 | J167: MWh | K167: 0 | L167: MWh | M167: EBY | N167: OFFICIAL_PRIMARY | O167: OFFICIAL_AGGREGATE | P167: 1 | Q167: 50 | R167: https://www.eby.gov.py/wp-content/uploads/2019/12/YacyretaEnergiasMensualesDesdePuestaenMarcha.pdf | S167: EBY-MONTHLY-1994-2012 | U167: 2026-09-10 23:00:00 | V167: Energia mensual entregada al SINP.
A168: R0000167 | B168: 1994-11-01 | C168: 1994-11-30 | D168: month | E168: YACYRETA_NET_ENERGY | F168: YACYRETA | G168: YACYRETA | H168: TOTAL | I168: 105254 | J168: MWh | K168: 105254 | L168: MWh | M168: EBY | N168: OFFICIAL_PRIMARY | O168: OFFICIAL_AGGREGATE | P168: 1 | Q168: 50 | R168: https://www.eby.gov.py/wp-content/uploads/2019/12/YacyretaEnergiasMensualesDesdePuestaenMarcha.pdf | S168: EBY-MONTHLY-1994-2012 | U168: 2026-09-10 23:00:00 | V168: Energia mensual Yacyreta desde puesta en marcha.
A169: R0000168 | B169: 1994-11-01 | C169: 1994-11-30 | D169: month | E169: ENERGY_TO_ARGENTINA | F169: YACYRETA | G169: YACYRETA | H169: SADI | I169: 105254 | J169: MWh | K169: 105254 | L169: MWh | M169: EBY | N169: OFFICIAL_PRIMARY | O169: OFFICIAL_AGGREGATE | P169: 1 | Q169: 50 | R169: https://www.eby.gov.py/wp-content/uploads/2019/12/YacyretaEnergiasMensualesDesdePuestaenMarcha.pdf | S169: EBY-MONTHLY-1994-2012 | U169: 2026-09-10 23:00:00 | V169: Energia mensual entregada al SADI.
A170: R0000169 | B170: 1994-11-01 | C170: 1994-11-30 | D170: month | E170: ENERGY_TO_PY | F170: YACYRETA | G170: YACYRETA | H170: SINP | I170: 0 | J170: MWh | K170: 0 | L170: MWh | M170: EBY | N170: OFFICIAL_PRIMARY | O170: OFFICIAL_AGGREGATE | P170: 1 | Q170: 50 | R170: https://www.eby.gov.py/wp-content/uploads/2019/12/YacyretaEnergiasMensualesDesdePuestaenMarcha.pdf | S170: EBY-MONTHLY-1994-2012 | U170: 2026-09-10 23:00:00 | V170: Energia mensual entregada al SINP.
... A1459: R0001458 | B1459: 2025-01-01 | C1459: 2025-12-31 | D1459: year | E1459: ITAIPU_CESSION_VOLUME_DERIVED | F1459: ITAIPU | G1459: PY | H1459: BR | I1459: 10671500 | J1459: MWh | K1459: 10671500 | L1459: MWh | M1459: ABC | N1459: PRESS_SECONDARY | O1459: PRESS_DERIVED | P1459: 0 | Q1459: 20 | R1459: https://www.abc.com.py/economia/2026/01/20/en-2025-pagaron-al-paraguay-us-15-por-cada-1000-kwh-que-cedio-al-brasil/ | S1459: ABC-ITA-2025 | U1459: 2026-09-11 00:05:00 | V1459: Derived from 50% entitlement less Paraguayan use; contextual, not primary physical measurement.
A1460: V5_0001 | B1460: 2026-01-01 | C1460: 2026-08-31 | D1460: YTD | E1460: ITAIPU_SUPPLY_TO_PY | F1460: ITAIPU | I1460: 19276 | J1460: GWh | K1460: 19276 | L1460: GWh | M1460: ITAIPU | N1460: OFFICIAL_PRIMARY | O1460: OFFICIAL_AGGREGATE | P1460: 1 | Q1460: 95 | R1460: https://www.itaipu.gov.py/noticias/energia/itaipu-suministro-19-276-gwh-de-energia-electrica-a-la-ande-de-enero-a-agosto-de-2026 | S1460: V5_CURRENT_BASELINES | U1460: 2026-09-11T01:00:00-03:00 | V1460: Supplied to Paraguay through ANDE Jan-Aug 2026.
A1461: V5_0002 | B1461: 2026-01-01 | C1461: 2026-08-31 | D1461: YTD | E1461: ITAIPU_TOTAL_GENERATION | F1461: ITAIPU | I1461: 51144 | J1461: GWh | K1461: 51144 | L1461: GWh | M1461: ITAIPU | N1461: OFFICIAL_PRIMARY | O1461: OFFICIAL_AGGREGATE | P1461: 1 | Q1461: 95 | R1461: https://www.itaipu.gov.py/noticias/energia/itaipu-suministro-19-276-gwh-de-energia-electrica-a-la-ande-de-enero-a-agosto-de-2026 | S1461: V5_CURRENT_BASELINES | U1461: 2026-09-11T01:00:00-03:00 | V1461: Total generation Jan-Aug 2026.
A1462: V5_0003 | B1462: 2026-01-01 | C1462: 2026-08-31 | D1462: YTD | E1462: ITAIPU_UNIT_AVAILABILITY | F1462: ITAIPU | I1462: 96.35 | J1462: percent | K1462: 96.35 | L1462: percent | M1462: ITAIPU | N1462: OFFICIAL_PRIMARY | O1462: OFFICIAL_AGGREGATE | P1462: 1 | Q1462: 95 | R1462: https://www.itaipu.gov.py/noticias/energia/itaipu-suministro-19-276-gwh-de-energia-electrica-a-la-ande-de-enero-a-agosto-de-2026 | S1462: V5_CURRENT_BASELINES | U1462: 2026-09-11T01:00:00-03:00 | V1462: Availability through August 2026.
A1463: V5_0004 | B1463: 2026-08-01 | C1463: 2026-08-31 | D1463: month | E1463: ITAIPU_AUG_TOTAL_GENERATION | F1463: ITAIPU | I1463: 6796 | J1463: GWh | K1463: 6796 | L1463: GWh | M1463: ITAIPU | N1463: OFFICIAL_PRIMARY | O1463: OFFICIAL_AGGREGATE | P1463: 1 | Q1463: 95 | R1463: https://www.itaipu.gov.py/noticias/energia/itaipu-suministro-19-276-gwh-de-energia-electrica-a-la-ande-de-enero-a-agosto-de-2026 | S1463: V5_CURRENT_BASELINES | U1463: 2026-09-11T01:00:00-03:00
A1464: V5_0005 | B1464: 2026-08-01 | C1464: 2026-08-31 | D1464: month | E1464: ITAIPU_AUG_50HZ_GENERATION | F1464: ITAIPU | I1464: 3428 | J1464: GWh | K1464: 3428 | L1464: GWh | M1464: ITAIPU | N1464: OFFICIAL_PRIMARY | O1464: OFFICIAL_AGGREGATE | P1464: 1 | Q1464: 95 | R1464: https://www.itaipu.gov.py/noticias/energia/itaipu-suministro-19-276-gwh-de-energia-electrica-a-la-ande-de-enero-a-agosto-de-2026 | S1464: V5_CURRENT_BASELINES | U1464: 2026-09-11T01:00:00-03:00
A1465: V5_0006 | B1465: 2026-08-01 | C1465: 2026-08-31 | D1465: month | E1465: ITAIPU_AUG_SUPPLY_TO_ANDE | F1465: ITAIPU | I1465: 2401 | J1465: GWh | K1465: 2401 | L1465: GWh | M1465: ITAIPU | N1465: OFFICIAL_PRIMARY | O1465: OFFICIAL_AGGREGATE | P1465: 1 | Q1465: 95 | R1465: https://www.itaipu.gov.py/noticias/energia/itaipu-suministro-19-276-gwh-de-energia-electrica-a-la-ande-de-enero-a-agosto-de-2026 | S1465: V5_CURRENT_BASELINES | U1465: 2026-09-11T01:00:00-03:00
A1466: V5_0007 | B1466: 2026-01-01 | C1466: 2026-08-31 | D1466: YTD_avg | E1466: ITAIPU_AVG_POWER_TO_PY_EQUIV | F1466: ITAIPU | I1466: 3305.213 | J1466: MW | K1466: 3305.213 | L1466: MW | M1466: ENERGIAPY | N1466: DERIVED | O1466: DERIVED_FROM_OFFICIAL | P1466: 1 | Q1466: 80 | R1466: https://www.itaipu.gov.py/noticias/energia/itaipu-suministro-19-276-gwh-de-energia-electrica-a-la-ande-de-enero-a-agosto-de-2026 | S1466: V5_CURRENT_BASELINES | U1466: 2026-09-11T01:00:00-03:00 | V1466: Energy/time equivalent average; not an instantaneous measurement.
A1467: V5_0008 | B1467: 2026-01-01 | C1467: 2026-08-31 | D1467: YTD_avg | E1467: ITAIPU_AVG_TOTAL_POWER_EQUIV | F1467: ITAIPU | I1467: 8769.547 | J1467: MW | K1467: 8769.547 | L1467: MW | M1467: ENERGIAPY | N1467: DERIVED | O1467: DERIVED_FROM_OFFICIAL | P1467: 1 | Q1467: 80 | R1467: https://www.itaipu.gov.py/noticias/energia/itaipu-suministro-19-276-gwh-de-energia-electrica-a-la-ande-de-enero-a-agosto-de-2026 | S1467: V5_CURRENT_BASELINES | U1467: 2026-09-11T01:00:00-03:00 | V1467: Energy/time equivalent average; not an instantaneous measurement.
A1468: V5_0009 | B1468: 2026-08-01 | C1468: 2026-08-31 | D1468: month_avg | E1468: ITAIPU_AUG_AVG_POWER_EQUIV | F1468: ITAIPU | I1468: 9134.409 | J1468: MW | K1468: 9134.409 | L1468: MW | M1468: ENERGIAPY | N1468: DERIVED | O1468: DERIVED_FROM_OFFICIAL | P1468: 1 | Q1468: 80 | R1468: https://www.itaipu.gov.py/noticias/energia/itaipu-suministro-19-276-gwh-de-energia-electrica-a-la-ande-de-enero-a-agosto-de-2026 | S1468: V5_CURRENT_BASELINES | U1468: 2026-09-11T01:00:00-03:00
A1469: V5_0010 | B1469: 2026-08-01 | C1469: 2026-08-31 | D1469: month_avg | E1469: ITAIPU_AUG_AVG_TO_ANDE_EQUIV | F1469: ITAIPU | I1469: 3227.151 | J1469: MW | K1469: 3227.151 | L1469: MW | M1469: ENERGIAPY | N1469: DERIVED | O1469: DERIVED_FROM_OFFICIAL | P1469: 1 | Q1469: 80 | R1469: https://www.itaipu.gov.py/noticias/energia/itaipu-suministro-19-276-gwh-de-energia-electrica-a-la-ande-de-enero-a-agosto-de-2026 | S1469: V5_CURRENT_BASELINES | U1469: 2026-09-11T01:00:00-03:00
A1470: V5_0011 | B1470: 2026-09-11 | C1470: 2026-09-11 | D1470: latest_hour_label | E1470: YACYRETA_POWER_LAST_HOUR | F1470: YACYRETA | I1470: 2034 | J1470: MW | K1470: 2034 | L1470: MW | M1470: EBY | N1470: OFFICIAL_PRIMARY | O1470: OFFICIAL_WEB_CURRENT | P1470: 1 | Q1470: 95 | R1470: https://eby.gov.py/ | S1470: V5_CURRENT_BASELINES | U1470: 2026-09-11T01:00:00-03:00 | V1470: EBY homepage says power generated in the last hour; exact measurement timestamp is not exposed.
A1471: V5_0012 | B1471: 2026-09-10 | C1471: 2026-09-10 | D1471: 06:00 | E1471: YACYRETA_RESERVOIR_LEVEL | F1471: YACYRETA | I1471: 82.82 | J1471: mSNM | K1471: 82.82 | L1471: mSNM | M1471: EBY | N1471: OFFICIAL_PRIMARY | O1471: OFFICIAL_MEASURED | P1471: 1 | Q1471: 95 | R1471: https://eby.gov.py/cota-82-82-msnm-resumen-ejecutivo-n-6077-10-09-2026/ | S1471: V5_CURRENT_BASELINES | U1471: 2026-09-11T01:00:00-03:00
A1472: V5_0013 | B1472: 2026-09-10 | C1472: 2026-09-10 | D1472: day | E1472: YACYRETA_INFLOW_FORECAST | F1472: YACYRETA | I1472: 13400 | J1472: m3/s | K1472: 13400 | L1472: m3/s | M1472: EBY | N1472: OFFICIAL_PRIMARY | O1472: OFFICIAL_FORECAST | P1472: 1 | Q1472: 95 | R1472: https://eby.gov.py/cota-82-82-msnm-resumen-ejecutivo-n-6077-10-09-2026/ | S1472: V5_CURRENT_BASELINES | U1472: 2026-09-11T01:00:00-03:00
A1473: V5_0014 | B1473: 2026-09-11 | C1473: 2026-09-11 | D1473: day | E1473: YACYRETA_INFLOW_FORECAST_NEXT_DAY | F1473: YACYRETA | I1473: 14500 | J1473: m3/s | K1473: 14500 | L1473: m3/s | M1473: EBY | N1473: OFFICIAL_PRIMARY | O1473: OFFICIAL_FORECAST | P1473: 1 | Q1473: 95 | R1473: https://eby.gov.py/cota-82-82-msnm-resumen-ejecutivo-n-6077-10-09-2026/ | S1473: V5_CURRENT_BASELINES | U1473: 2026-09-11T01:00:00-03:00
A1474: V5_0015 | B1474: 2026-09-10 | C1474: 2026-09-10 | D1474: day | E1474: YACYRETA_ANACUA_FLOW | F1474: YACYRETA | I1474: 1000 | J1474: m3/s | K1474: 1000 | L1474: m3/s | M1474: EBY | N1474: OFFICIAL_PRIMARY | O1474: OFFICIAL_OPERATIONAL | P1474: 1 | Q1474: 95 | R1474: https://eby.gov.py/cota-82-82-msnm-resumen-ejecutivo-n-6077-10-09-2026/ | S1474: V5_CURRENT_BASELINES | U1474: 2026-09-11T01:00:00-03:00 | V1474: Brazo Ana Cua spillway.
A1475: V5_0016 | B1475: 2026-09-10 | C1475: 2026-09-10 | D1475: day | E1475: AYOLAS_RIVER_LEVEL | F1475: AYOLAS | I1475: 1.8 | J1475: m | K1475: 1.8 | L1475: m | M1475: EBY | N1475: OFFICIAL_PRIMARY | O1475: OFFICIAL_MEASURED | P1475: 1 | Q1475: 95 | R1475: https://eby.gov.py/cota-82-82-msnm-resumen-ejecutivo-n-6077-10-09-2026/ | S1475: V5_CURRENT_BASELINES | U1475: 2026-09-11T01:00:00-03:00
A1476: V5_0017 | B1476: 2026-09-10 | C1476: 2026-09-10 | D1476: 02:00 | E1476: ITUZAINGO_RIVER_LEVEL | F1476: ITUZAINGO | I1476: 1.6 | J1476: m | K1476: 1.6 | L1476: m | M1476: EBY | N1476: OFFICIAL_PRIMARY | O1476: OFFICIAL_MEASURED | P1476: 1 | Q1476: 95 | R1476: https://eby.gov.py/cota-82-82-msnm-resumen-ejecutivo-n-6077-10-09-2026/ | S1476: V5_CURRENT_BASELINES | U1476: 2026-09-11T01:00:00-03:00
A1477: V5_0018 | B1477: 2025-01-01 | C1477: 2025-12-31 | D1477: year | E1477: PY_SIN_ENERGY_CONSUMPTION | F1477: PY_SIN | I1477: 29418538 | J1477: MWh | K1477: 29418538 | L1477: MWh | M1477: ANDE | N1477: OFFICIAL_PRIMARY | O1477: OFFICIAL_AGGREGATE | P1477: 1 | Q1477: 95 | R1477: https://www.ande.gov.py/finanzas/BAGP%202025%20ANDE.pdf | S1477: V5_CURRENT_BASELINES | U1477: 2026-09-11T01:00:00-03:00
A1478: V5_0019 | B1478: 2025-01-01 | C1478: 2025-12-31 | D1478: year | E1478: PY_SIN_MAX_DEMAND | F1478: PY_SIN | I1478: 5280 | J1478: MW | K1478: 5280 | L1478: MW | M1478: ANDE | N1478: OFFICIAL_PRIMARY | O1478: OFFICIAL_AGGREGATE | P1478: 1 | Q1478: 95 | R1478: https://www.ande.gov.py/finanzas/BAGP%202025%20ANDE.pdf | S1478: V5_CURRENT_BASELINES | U1478: 2026-09-11T01:00:00-03:00
A1479: V5_0020 | B1479: 2025-01-01 | C1479: 2025-12-31 | D1479: year | E1479: PY_SIN_LOAD_FACTOR | F1479: PY_SIN | I1479: 63.6 | J1479: percent | K1479: 63.6 | L1479: percent | M1479: ANDE | N1479: OFFICIAL_PRIMARY | O1479: OFFICIAL_AGGREGATE | P1479: 1 | Q1479: 95 | R1479: https://www.ande.gov.py/finanzas/BAGP%202025%20ANDE.pdf | S1479: V5_CURRENT_BASELINES | U1479: 2026-09-11T01:00:00-03:00
A1480: V5_0021 | B1480: 2025-01-01 | C1480: 2025-12-31 | D1480: year | E1480: ANDE_TOTAL_LOSS_RATE | F1480: PY_GRID | I1480: 24.4 | J1480: percent | K1480: 24.4 | L1480: percent | M1480: ANDE | N1480: OFFICIAL_PRIMARY | O1480: OFFICIAL_AGGREGATE | P1480: 1 | Q1480: 95 | R1480: https://www.ande.gov.py/finanzas/BAGP%202025%20ANDE.pdf | S1480: V5_CURRENT_BASELINES | U1480: 2026-09-11T01:00:00-03:00 | V1480: BAGP annual canonical figure. ANDE news rounds this to 24.5%.
A1481: V5_0022 | B1481: 2025-01-01 | C1481: 2025-12-31 | D1481: year | E1481: ANDE_DISTRIBUTION_LOSS_RATE | F1481: PY_GRID | I1481: 20.03 | J1481: percent | K1481: 20.03 | L1481: percent | M1481: ANDE | N1481: OFFICIAL_PRIMARY | O1481: OFFICIAL_RELEASE | P1481: 1 | Q1481: 95 | R1481: https://www.ande.gov.py/interna.php?id=15116 | S1481: V5_CURRENT_BASELINES | U1481: 2026-09-11T01:00:00-03:00
A1482: V5_0023 | B1482: 2024-12-01 | C1482: 2025-03-31 | D1482: season | E1482: DEP_METROPOLITAN_SUMMER | F1482: PY_GRID_METRO | I1482: 2.44 | J1482: hours | K1482: 2.44 | L1482: hours | M1482: ANDE | N1482: OFFICIAL_PRIMARY | O1482: OFFICIAL_RELEASE | P1482: 1 | Q1482: 95 | R1482: https://www.ande.gov.py/interna.php?id=13680 | S1482: V5_CURRENT_BASELINES | U1482: 2026-09-11T01:00:00-03:00
A1483: V5_0024 | B1483: 2024-12-01 | C1483: 2025-03-31 | D1483: season | E1483: FEP_METROPOLITAN_SUMMER | F1483: PY_GRID_METRO | I1483: 3.79 | J1483: interruptions_equivalent | K1483: 3.79 | L1483: interruptions_equivalent | M1483: ANDE | N1483: OFFICIAL_PRIMARY | O1483: OFFICIAL_RELEASE | P1483: 1 | Q1483: 95 | R1483: https://www.ande.gov.py/interna.php?id=13680 | S1483: V5_CURRENT_BASELINES | U1483: 2026-09-11T01:00:00-03:00
A1484: V5_0025 | B1484: 2025-01-01 | C1484: 2025-12-31 | D1484: year | E1484: TARIFA_SOCIAL_SUBSIDY_TOTAL | F1484: PY_HOUSEHOLDS | I1484: 50185 | J1484: million_PYG | K1484: 50185 | L1484: million_PYG | M1484: ANDE | N1484: OFFICIAL_PRIMARY | O1484: OFFICIAL_AGGREGATE | P1484: 1 | Q1484: 95 | R1484: https://www.ande.gov.py/finanzas/BAGP%202025%20ANDE.pdf | S1484: V5_CURRENT_BASELINES | U1484: 2026-09-11T01:00:00-03:00
A1485: V5_0026 | B1485: 2025-01-01 | C1485: 2025-12-31 | D1485: year_avg | E1485: TARIFA_SOCIAL_SUBSIDY_MONTHLY_AVG | F1485: PY_HOUSEHOLDS | I1485: 4182 | J1485: million_PYG/month | K1485: 4182 | L1485: million_PYG/month | M1485: ANDE | N1485: OFFICIAL_PRIMARY | O1485: OFFICIAL_AGGREGATE | P1485: 1 | Q1485: 95 | R1485: https://www.ande.gov.py/finanzas/BAGP%202025%20ANDE.pdf | S1485: V5_CURRENT_BASELINES | U1485: 2026-09-11T01:00:00-03:00 | V1485: Published average in BAGP.
A1486: V5_0027 | B1486: 2024-01-01 | C1486: 2025-12-31 | D1486: 2y | E1486: ILLEGAL_CRYPTO_POWER_INTERVENED | F1486: PY_GRID | I1486: 91.8 | J1486: MW | K1486: 91.8 | L1486: MW | M1486: ANDE | N1486: OFFICIAL_PRIMARY | O1486: OFFICIAL_RELEASE | P1486: 1 | Q1486: 95 | R1486: https://www.ande.gov.py/interna.php?id=15116 | S1486: V5_CURRENT_BASELINES | U1486: 2026-09-11T01:00:00-03:00 | V1486: 37 illegal crypto farms intervened in 2024-2025.
A1487: V5_0028 | B1487: 2024-01-01 | C1487: 2025-12-31 | D1487: 2y_context | E1487: ILLEGAL_CRYPTO_AVOIDED_LOSS_MONTHLY | F1487: PY_GRID | I1487: 18600 | J1487: million_PYG/month | K1487: 18600 | L1487: million_PYG/month | M1487: ANDE | N1487: OFFICIAL_PRIMARY | O1487: OFFICIAL_RELEASE | P1487: 1 | Q1487: 95 | R1487: https://www.ande.gov.py/interna.php?id=15116 | S1487: V5_CURRENT_BASELINES | U1487: 2026-09-11T01:00:00-03:00 | V1487: ANDE says monthly economic harm avoided exceeds this amount.
A1488: V5_0029 | B1488: 2026-06-01 | C1488: 2026-06-30 | D1488: month_or_YTD | E1488: IMAEP_YOY | F1488: PY_ECONOMY | I1488: 5.6 | J1488: percent | K1488: 5.6 | L1488: percent | M1488: BCP | N1488: OFFICIAL_PRIMARY | O1488: OFFICIAL_PRELIMINARY | P1488: 1 | Q1488: 95 | R1488: https://www.bcp.gov.py/documents/20117/2588253/Informe%2BIMAEP-Sectores-Junio_2026.pdf/1b25c6bf-e43c-1c91-9a58-037d4cee0653 | S1488: V5_CURRENT_BASELINES | U1488: 2026-09-11T01:00:00-03:00 | V1488: IMAEP total interannual growth
A1489: V5_0030 | B1489: 2026-01-01 | C1489: 2026-06-30 | D1489: month_or_YTD | E1489: IMAEP_YTD | F1489: PY_ECONOMY | I1489: 5.6 | J1489: percent | K1489: 5.6 | L1489: percent | M1489: BCP | N1489: OFFICIAL_PRIMARY | O1489: OFFICIAL_PRELIMINARY | P1489: 1 | Q1489: 95 | R1489: https://www.bcp.gov.py/documents/20117/2588253/Informe%2BIMAEP-Sectores-Junio_2026.pdf/1b25c6bf-e43c-1c91-9a58-037d4cee0653 | S1489: V5_CURRENT_BASELINES | U1489: 2026-09-11T01:00:00-03:00 | V1489: IMAEP accumulated Jan-Jun 2026
A1490: V5_0031 | B1490: 2026-06-01 | C1490: 2026-06-30 | D1490: month_or_YTD | E1490: IMAEP_PRIMARY_YOY | F1490: PY_ECONOMY | I1490: 9.4 | J1490: percent | K1490: 9.4 | L1490: percent | M1490: BCP | N1490: OFFICIAL_PRIMARY | O1490: OFFICIAL_PRELIMINARY | P1490: 1 | Q1490: 95 | R1490: https://www.bcp.gov.py/documents/20117/2588253/Informe%2BIMAEP-Sectores-Junio_2026.pdf/1b25c6bf-e43c-1c91-9a58-037d4cee0653 | S1490: V5_CURRENT_BASELINES | U1490: 2026-09-11T01:00:00-03:00 | V1490: Primary sector interannual
A1491: V5_0032 | B1491: 2026-01-01 | C1491: 2026-06-30 | D1491: month_or_YTD | E1491: IMAEP_PRIMARY_YTD | F1491: PY_ECONOMY | I1491: 9.8 | J1491: percent | K1491: 9.8 | L1491: percent | M1491: BCP | N1491: OFFICIAL_PRIMARY | O1491: OFFICIAL_PRELIMINARY | P1491: 1 | Q1491: 95 | R1491: https://www.bcp.gov.py/documents/20117/2588253/Informe%2BIMAEP-Sectores-Junio_2026.pdf/1b25c6bf-e43c-1c91-9a58-037d4cee0653 | S1491: V5_CURRENT_BASELINES | U1491: 2026-09-11T01:00:00-03:00 | V1491: Primary sector accumulated
A1492: V5_0033 | B1492: 2026-06-01 | C1492: 2026-06-30 | D1492: month_or_YTD | E1492: IMAEP_SECONDARY_YOY | F1492: PY_ECONOMY | I1492: 5.6 | J1492: percent | K1492: 5.6 | L1492: percent | M1492: BCP | N1492: OFFICIAL_PRIMARY | O1492: OFFICIAL_PRELIMINARY | P1492: 1 | Q1492: 95 | R1492: https://www.bcp.gov.py/documents/20117/2588253/Informe%2BIMAEP-Sectores-Junio_2026.pdf/1b25c6bf-e43c-1c91-9a58-037d4cee0653 | S1492: V5_CURRENT_BASELINES | U1492: 2026-09-11T01:00:00-03:00 | V1492: Secondary sector interannual
A1493: V5_0034 | B1493: 2026-01-01 | C1493: 2026-06-30 | D1493: month_or_YTD | E1493: IMAEP_SECONDARY_YTD | F1493: PY_ECONOMY | I1493: 4.7 | J1493: percent | K1493: 4.7 | L1493: percent | M1493: BCP | N1493: OFFICIAL_PRIMARY | O1493: OFFICIAL_PRELIMINARY | P1493: 1 | Q1493: 95 | R1493: https://www.bcp.gov.py/documents/20117/2588253/Informe%2BIMAEP-Sectores-Junio_2026.pdf/1b25c6bf-e43c-1c91-9a58-037d4cee0653 | S1493: V5_CURRENT_BASELINES | U1493: 2026-09-11T01:00:00-03:00 | V1493: Secondary sector accumulated
A1494: V5_0035 | B1494: 2026-06-01 | C1494: 2026-06-30 | D1494: month_or_YTD | E1494: IMAEP_MANUFACTURING_YOY | F1494: PY_ECONOMY | I1494: 2.8 | J1494: percent | K1494: 2.8 | L1494: percent | M1494: BCP | N1494: OFFICIAL_PRIMARY | O1494: OFFICIAL_PRELIMINARY | P1494: 1 | Q1494: 95 | R1494: https://www.bcp.gov.py/documents/20117/2588253/Informe%2BIMAEP-Sectores-Junio_2026.pdf/1b25c6bf-e43c-1c91-9a58-037d4cee0653 | S1494: V5_CURRENT_BASELINES | U1494: 2026-09-11T01:00:00-03:00 | V1494: Manufacturing interannual
...

Sheet Canonical
A1: record_id | B1: period_start | C1: period_end | D1: grain | E1: variable_code | F1: asset_code | G1: origin_code | H1: destination_code | I1: value_source | J1: unit_source | K1: value_normalized | L1: unit_normalized | M1: source_code | N1: authority_class | O1: quality_class | P1: canonical_flag | Q1: revision_priority | R1: source_url | S1: source_file_code | T1: source_published_at | U1: collected_at | V1: notes
A2: R0000001 | B2: 2003-01-01 | C2: 2003-12-31 | D2: year | E2: PY_CONSUMPTION_ENERGY | F2: PY_SIN | G2: PY | H2: PY | I2: 6183000 | J2: MWh | K2: 6183000 | L2: MWh | M2: ANDE | N2: OFFICIAL_PRIMARY | O2: OFFICIAL_AGGREGATE | P2: 1 | Q2: 50 | R2: https://www.ande.gov.py/finanzas/2.%20COMPILACION%20ESTADISTICA%202003-2023/ANDE%20-%20Compilacion%20Estadistica%202003-2023.pdf | S2: ANDE-STAT-2003-2023 | U2: 2026-09-10 23:00:00
A3: R0000002 | B3: 2003-01-01 | C3: 2003-12-31 | D3: year | E3: PY_MAX_DEMAND | F3: PY_SIN | G3: PY | H3: PY | I3: 1191 | J3: MW | K3: 1191 | L3: MW | M3: ANDE | N3: OFFICIAL_PRIMARY | O3: OFFICIAL_AGGREGATE | P3: 1 | Q3: 50 | R3: https://www.ande.gov.py/finanzas/2.%20COMPILACION%20ESTADISTICA%202003-2023/ANDE%20-%20Compilacion%20Estadistica%202003-2023.pdf | S3: ANDE-STAT-2003-2023 | U3: 2026-09-10 23:00:00
A4: R0000003 | B4: 2004-01-01 | C4: 2004-12-31 | D4: year | E4: PY_CONSUMPTION_ENERGY | F4: PY_SIN | G4: PY | H4: PY | I4: 6580000 | J4: MWh | K4: 6580000 | L4: MWh | M4: ANDE | N4: OFFICIAL_PRIMARY | O4: OFFICIAL_AGGREGATE | P4: 1 | Q4: 50 | R4: https://www.ande.gov.py/finanzas/2.%20COMPILACION%20ESTADISTICA%202003-2023/ANDE%20-%20Compilacion%20Estadistica%202003-2023.pdf | S4: ANDE-STAT-2003-2023 | U4: 2026-09-10 23:00:00
A5: R0000004 | B5: 2004-01-01 | C5: 2004-12-31 | D5: year | E5: PY_MAX_DEMAND | F5: PY_SIN | G5: PY | H5: PY | I5: 1241 | J5: MW | K5: 1241 | L5: MW | M5: ANDE | N5: OFFICIAL_PRIMARY | O5: OFFICIAL_AGGREGATE | P5: 1 | Q5: 50 | R5: https://www.ande.gov.py/finanzas/2.%20COMPILACION%20ESTADISTICA%202003-2023/ANDE%20-%20Compilacion%20Estadistica%202003-2023.pdf | S5: ANDE-STAT-2003-2023 | U5: 2026-09-10 23:00:00
A6: R0000005 | B6: 2005-01-01 | C6: 2005-12-31 | D6: year | E6: PY_CONSUMPTION_ENERGY | F6: PY_SIN | G6: PY | H6: PY | I6: 6944000 | J6: MWh | K6: 6944000 | L6: MWh | M6: ANDE | N6: OFFICIAL_PRIMARY | O6: OFFICIAL_AGGREGATE | P6: 1 | Q6: 50 | R6: https://www.ande.gov.py/finanzas/2.%20COMPILACION%20ESTADISTICA%202003-2023/ANDE%20-%20Compilacion%20Estadistica%202003-2023.pdf | S6: ANDE-STAT-2003-2023 | U6: 2026-09-10 23:00:00
A7: R0000006 | B7: 2005-01-01 | C7: 2005-12-31 | D7: year | E7: PY_MAX_DEMAND | F7: PY_SIN | G7: PY | H7: PY | I7: 1354 | J7: MW | K7: 1354 | L7: MW | M7: ANDE | N7: OFFICIAL_PRIMARY | O7: OFFICIAL_AGGREGATE | P7: 1 | Q7: 50 | R7: https://www.ande.gov.py/finanzas/2.%20COMPILACION%20ESTADISTICA%202003-2023/ANDE%20-%20Compilacion%20Estadistica%202003-2023.pdf | S7: ANDE-STAT-2003-2023 | U7: 2026-09-10 23:00:00
A8: R0000007 | B8: 2006-01-01 | C8: 2006-12-31 | D8: year | E8: PY_CONSUMPTION_ENERGY | F8: PY_SIN | G8: PY | H8: PY | I8: 7701000 | J8: MWh | K8: 7701000 | L8: MWh | M8: ANDE | N8: OFFICIAL_PRIMARY | O8: OFFICIAL_AGGREGATE | P8: 1 | Q8: 50 | R8: https://www.ande.gov.py/finanzas/2.%20COMPILACION%20ESTADISTICA%202003-2023/ANDE%20-%20Compilacion%20Estadistica%202003-2023.pdf | S8: ANDE-STAT-2003-2023 | U8: 2026-09-10 23:00:00
A9: R0000008 | B9: 2006-01-01 | C9: 2006-12-31 | D9: year | E9: PY_MAX_DEMAND | F9: PY_SIN | G9: PY | H9: PY | I9: 1450 | J9: MW | K9: 1450 | L9: MW | M9: ANDE | N9: OFFICIAL_PRIMARY | O9: OFFICIAL_AGGREGATE | P9: 1 | Q9: 50 | R9: https://www.ande.gov.py/finanzas/2.%20COMPILACION%20ESTADISTICA%202003-2023/ANDE%20-%20Compilacion%20Estadistica%202003-2023.pdf | S9: ANDE-STAT-2003-2023 | U9: 2026-09-10 23:00:00
A10: R0000009 | B10: 2007-01-01 | C10: 2007-12-31 | D10: year | E10: PY_CONSUMPTION_ENERGY | F10: PY_SIN | G10: PY | H10: PY | I10: 8299000 | J10: MWh | K10: 8299000 | L10: MWh | M10: ANDE | N10: OFFICIAL_PRIMARY | O10: OFFICIAL_AGGREGATE | P10: 1 | Q10: 50 | R10: https://www.ande.gov.py/finanzas/2.%20COMPILACION%20ESTADISTICA%202003-2023/ANDE%20-%20Compilacion%20Estadistica%202003-2023.pdf | S10: ANDE-STAT-2003-2023 | U10: 2026-09-10 23:00:00
A11: R0000010 | B11: 2007-01-01 | C11: 2007-12-31 | D11: year | E11: PY_MAX_DEMAND | F11: PY_SIN | G11: PY | H11: PY | I11: 1521 | J11: MW | K11: 1521 | L11: MW | M11: ANDE | N11: OFFICIAL_PRIMARY | O11: OFFICIAL_AGGREGATE | P11: 1 | Q11: 50 | R11: https://www.ande.gov.py/finanzas/2.%20COMPILACION%20ESTADISTICA%202003-2023/ANDE%20-%20Compilacion%20Estadistica%202003-2023.pdf | S11: ANDE-STAT-2003-2023 | U11: 2026-09-10 23:00:00
A12: R0000011 | B12: 2008-01-01 | C12: 2008-12-31 | D12: year | E12: PY_CONSUMPTION_ENERGY | F12: PY_SIN | G12: PY | H12: PY | I12: 8888000 | J12: MWh | K12: 8888000 | L12: MWh | M12: ANDE | N12: OFFICIAL_PRIMARY | O12: OFFICIAL_AGGREGATE | P12: 1 | Q12: 50 | R12: https://www.ande.gov.py/finanzas/2.%20COMPILACION%20ESTADISTICA%202003-2023/ANDE%20-%20Compilacion%20Estadistica%202003-2023.pdf | S12: ANDE-STAT-2003-2023 | U12: 2026-09-10 23:00:00
A13: R0000012 | B13: 2008-01-01 | C13: 2008-12-31 | D13: year | E13: PY_MAX_DEMAND | F13: PY_SIN | G13: PY | H13: PY | I13: 1648 | J13: MW | K13: 1648 | L13: MW | M13: ANDE | N13: OFFICIAL_PRIMARY | O13: OFFICIAL_AGGREGATE | P13: 1 | Q13: 50 | R13: https://www.ande.gov.py/finanzas/2.%20COMPILACION%20ESTADISTICA%202003-2023/ANDE%20-%20Compilacion%20Estadistica%202003-2023.pdf | S13: ANDE-STAT-2003-2023 | U13: 2026-09-10 23:00:00
... A36: R0000036 | B36: 2020-01-01 | C36: 2020-12-31 | D36: year | E36: PY_MAX_DEMAND | F36: PY_SIN | G36: PY | H36: PY | I36: 3563 | J36: MW | K36: 3563 | L36: MW | M36: ANDE | N36: OFFICIAL_PRIMARY | O36: OFFICIAL_AGGREGATE | P36: 1 | Q36: 50 | R36: https://www.ande.gov.py/finanzas/2.%20COMPILACION%20ESTADISTICA%202003-2023/ANDE%20-%20Compilacion%20Estadistica%202003-2023.pdf | S36: ANDE-STAT-2003-2023 | U36: 2026-09-10 23:00:00
A37: R0000037 | B37: 2020-01-01 | C37: 2020-12-31 | D37: year | E37: PY_LOAD_FACTOR | F37: PY_SIN | G37: PY | H37: PY | I37: 57.5 | J37: percent | K37: 57.5 | L37: percent | M37: ANDE | N37: OFFICIAL_PRIMARY | O37: OFFICIAL_AGGREGATE | P37: 1 | Q37: 50 | R37: https://www.ande.gov.py/finanzas/2.%20COMPILACION%20ESTADISTICA%202003-2023/ANDE%20-%20Compilacion%20Estadistica%202003-2023.pdf | S37: ANDE-STAT-2003-2023 | U37: 2026-09-10 23:00:00 | V37: Factor de carga publicado.
A38: R0000039 | B38: 2021-01-01 | C38: 2021-12-31 | D38: year | E38: PY_MAX_DEMAND | F38: PY_SIN | G38: PY | H38: PY | I38: 3777 | J38: MW | K38: 3777 | L38: MW | M38: ANDE | N38: OFFICIAL_PRIMARY | O38: OFFICIAL_AGGREGATE | P38: 1 | Q38: 50 | R38: https://www.ande.gov.py/finanzas/2.%20COMPILACION%20ESTADISTICA%202003-2023/ANDE%20-%20Compilacion%20Estadistica%202003-2023.pdf | S38: ANDE-STAT-2003-2023 | U38: 2026-09-10 23:00:00
A39: R0000040 | B39: 2021-01-01 | C39: 2021-12-31 | D39: year | E39: PY_LOAD_FACTOR | F39: PY_SIN | G39: PY | H39: PY | I39: 56.2 | J39: percent | K39: 56.2 | L39: percent | M39: ANDE | N39: OFFICIAL_PRIMARY | O39: OFFICIAL_AGGREGATE | P39: 1 | Q39: 50 | R39: https://www.ande.gov.py/finanzas/2.%20COMPILACION%20ESTADISTICA%202003-2023/ANDE%20-%20Compilacion%20Estadistica%202003-2023.pdf | S39: ANDE-STAT-2003-2023 | U39: 2026-09-10 23:00:00 | V39: Factor de carga publicado.
A40: R0000042 | B40: 2022-01-01 | C40: 2022-12-31 | D40: year | E40: PY_MAX_DEMAND | F40: PY_SIN | G40: PY | H40: PY | I40: 4270 | J40: MW | K40: 4270 | L40: MW | M40: ANDE | N40: OFFICIAL_PRIMARY | O40: OFFICIAL_AGGREGATE | P40: 1 | Q40: 50 | R40: https://www.ande.gov.py/finanzas/2.%20COMPILACION%20ESTADISTICA%202003-2023/ANDE%20-%20Compilacion%20Estadistica%202003-2023.pdf | S40: ANDE-STAT-2003-2023 | U40: 2026-09-10 23:00:00
A41: R0000043 | B41: 2022-01-01 | C41: 2022-12-31 | D41: year | E41: PY_LOAD_FACTOR | F41: PY_SIN | G41: PY | H41: PY | I41: 52.5 | J41: percent | K41: 52.5 | L41: percent | M41: ANDE | N41: OFFICIAL_PRIMARY | O41: OFFICIAL_AGGREGATE | P41: 1 | Q41: 50 | R41: https://www.ande.gov.py/finanzas/2.%20COMPILACION%20ESTADISTICA%202003-2023/ANDE%20-%20Compilacion%20Estadistica%202003-2023.pdf | S41: ANDE-STAT-2003-2023 | U41: 2026-09-10 23:00:00 | V41: Factor de carga publicado.
A42: R0000045 | B42: 2023-01-01 | C42: 2023-12-31 | D42: year | E42: PY_MAX_DEMAND | F42: PY_SIN | G42: PY | H42: PY | I42: 4744 | J42: MW | K42: 4744 | L42: MW | M42: ANDE | N42: OFFICIAL_PRIMARY | O42: OFFICIAL_AGGREGATE | P42: 1 | Q42: 50 | R42: https://www.ande.gov.py/finanzas/2.%20COMPILACION%20ESTADISTICA%202003-2023/ANDE%20-%20Compilacion%20Estadistica%202003-2023.pdf | S42: ANDE-STAT-2003-2023 | U42: 2026-09-10 23:00:00
A43: R0000046 | B43: 2023-01-01 | C43: 2023-12-31 | D43: year | E43: PY_LOAD_FACTOR | F43: PY_SIN | G43: PY | H43: PY | I43: 53.1 | J43: percent | K43: 53.1 | L43: percent | M43: ANDE | N43: OFFICIAL_PRIMARY | O43: OFFICIAL_AGGREGATE | P43: 1 | Q43: 50 | R43: https://www.ande.gov.py/finanzas/2.%20COMPILACION%20ESTADISTICA%202003-2023/ANDE%20-%20Compilacion%20Estadistica%202003-2023.pdf | S43: ANDE-STAT-2003-2023 | U43: 2026-09-10 23:00:00 | V43: Factor de carga publicado.
A44: R0000047 | B44: 2024-01-01 | C44: 2024-12-31 | D44: year | E44: PY_CONSUMPTION_ENERGY | F44: PY_SIN | G44: PY | H44: PY | I44: 26154488 | J44: MWh | K44: 26154488 | L44: MWh | M44: ANDE | N44: OFFICIAL_PRIMARY | O44: OFFICIAL_AGGREGATE | P44: 1 | Q44: 50 | R44: https://www.ande.gov.py/finanzas/ANDE%20-%20Resumen%20Estad%C3%ADstico%202020%20-%202024.pdf | S44: ANDE-STAT-2020-2024 | U44: 2026-09-10 23:00:00
A45: R0000048 | B45: 2024-01-01 | C45: 2024-12-31 | D45: year | E45: PY_MAX_DEMAND | F45: PY_SIN | G45: PY | H45: PY | I45: 5027 | J45: MW | K45: 5027 | L45: MW | M45: ANDE | N45: OFFICIAL_PRIMARY | O45: OFFICIAL_AGGREGATE | P45: 1 | Q45: 50 | R45: https://www.ande.gov.py/finanzas/ANDE%20-%20Resumen%20Estad%C3%ADstico%202020%20-%202024.pdf | S45: ANDE-STAT-2020-2024 | U45: 2026-09-10 23:00:00
A46: R0000049 | B46: 2024-01-01 | C46: 2024-12-31 | D46: year | E46: PY_LOAD_FACTOR | F46: PY_SIN | G46: PY | H46: PY | I46: 59.39 | J46: percent | K46: 59.39 | L46: percent | M46: ANDE | N46: OFFICIAL_PRIMARY | O46: OFFICIAL_AGGREGATE | P46: 1 | Q46: 50 | R46: https://www.ande.gov.py/finanzas/ANDE%20-%20Resumen%20Estad%C3%ADstico%202020%20-%202024.pdf | S46: ANDE-STAT-2020-2024 | U46: 2026-09-10 23:00:00 | V46: Factor de carga publicado.
A47: R0000050 | B47: 2025-01-01 | C47: 2025-12-31 | D47: year | E47: PY_CONSUMPTION_ENERGY | F47: PY_SIN | G47: PY | H47: PY | I47: 29418538 | J47: MWh | K47: 29418538 | L47: MWh | M47: ANDE | N47: OFFICIAL_PRIMARY | O47: OFFICIAL_AGGREGATE | P47: 1 | Q47: 50 | R47: https://www.ande.gov.py/finanzas/BAGP%202025%20ANDE.pdf | S47: ANDE-BAGP-2025 | U47: 2026-09-10 23:00:00 | V47: 2025: total exacto de BAGP; nota de prensa redondea a 29.419 GWh.
A48: R0000051 | B48: 2025-01-01 | C48: 2025-12-31 | D48: year | E48: PY_MAX_DEMAND | F48: PY_SIN | G48: PY | H48: PY | I48: 5280 | J48: MW | K48: 5280 | L48: MW | M48: ANDE | N48: OFFICIAL_PRIMARY | O48: OFFICIAL_AGGREGATE | P48: 1 | Q48: 50 | R48: https://www.ande.gov.py/finanzas/BAGP%202025%20ANDE.pdf | S48: ANDE-BAGP-2025 | U48: 2026-09-10 23:00:00 | V48: 2025: total exacto de BAGP; nota de prensa redondea a 29.419 GWh.
A49: R0000052 | B49: 2025-01-01 | C49: 2025-12-31 | D49: year | E49: PY_LOAD_FACTOR | F49: PY_SIN | G49: PY | H49: PY | I49: 63.6 | J49: percent | K49: 63.6 | L49: percent | M49: ANDE | N49: OFFICIAL_PRIMARY | O49: OFFICIAL_AGGREGATE | P49: 1 | Q49: 50 | R49: https://www.ande.gov.py/finanzas/BAGP%202025%20ANDE.pdf | S49: ANDE-BAGP-2025 | U49: 2026-09-10 23:00:00 | V49: Factor de carga publicado.
A50: R0000053 | B50: 2020-01-01 | C50: 2020-12-31 | D50: year | E50: PY_REGION_ENERGY | F50: PY_REGION_METROPOLITANO | G50: PY | H50: PY | I50: 9312851 | J50: MWh | K50: 9312851 | L50: MWh | M50: ANDE | N50: OFFICIAL_PRIMARY | O50: OFFICIAL_AGGREGATE | P50: 1 | Q50: 50 | R50: https://www.ande.gov.py/finanzas/ANDE%20-%20Resumen%20Estad%C3%ADstico%202020%20-%202024.pdf | S50: ANDE-STAT-2020-2024 | U50: 2026-09-10 23:00:00 | V50: Sistema/region: Metropolitano.
A51: R0000054 | B51: 2021-01-01 | C51: 2021-12-31 | D51: year | E51: PY_REGION_ENERGY | F51: PY_REGION_METROPOLITANO | G51: PY | H51: PY | I51: 9543744 | J51: MWh | K51: 9543744 | L51: MWh | M51: ANDE | N51: OFFICIAL_PRIMARY | O51: OFFICIAL_AGGREGATE | P51: 1 | Q51: 50 | R51: https://www.ande.gov.py/finanzas/ANDE%20-%20Resumen%20Estad%C3%ADstico%202020%20-%202024.pdf | S51: ANDE-STAT-2020-2024 | U51: 2026-09-10 23:00:00 | V51: Sistema/region: Metropolitano.
A52: R0000055 | B52: 2022-01-01 | C52: 2022-12-31 | D52: year | E52: PY_REGION_ENERGY | F52: PY_REGION_METROPOLITANO | G52: PY | H52: PY | I52: 9964357 | J52: MWh | K52: 9964357 | L52: MWh | M52: ANDE | N52: OFFICIAL_PRIMARY | O52: OFFICIAL_AGGREGATE | P52: 1 | Q52: 50 | R52: https://www.ande.gov.py/finanzas/ANDE%20-%20Resumen%20Estad%C3%ADstico%202020%20-%202024.pdf | S52: ANDE-STAT-2020-2024 | U52: 2026-09-10 23:00:00 | V52: Sistema/region: Metropolitano.
A53: R0000056 | B53: 2023-01-01 | C53: 2023-12-31 | D53: year | E53: PY_REGION_ENERGY | F53: PY_REGION_METROPOLITANO | G53: PY | H53: PY | I53: 11174060 | J53: MWh | K53: 11174060 | L53: MWh | M53: ANDE | N53: OFFICIAL_PRIMARY | O53: OFFICIAL_AGGREGATE | P53: 1 | Q53: 50 | R53: https://www.ande.gov.py/finanzas/ANDE%20-%20Resumen%20Estad%C3%ADstico%202020%20-%202024.pdf | S53: ANDE-STAT-2020-2024 | U53: 2026-09-10 23:00:00 | V53: Sistema/region: Metropolitano.
A54: R0000057 | B54: 2024-01-01 | C54: 2024-12-31 | D54: year | E54: PY_REGION_ENERGY | F54: PY_REGION_METROPOLITANO | G54: PY | H54: PY | I54: 12291090 | J54: MWh | K54: 12291090 | L54: MWh | M54: ANDE | N54: OFFICIAL_PRIMARY | O54: OFFICIAL_AGGREGATE | P54: 1 | Q54: 50 | R54: https://www.ande.gov.py/finanzas/ANDE%20-%20Resumen%20Estad%C3%ADstico%202020%20-%202024.pdf | S54: ANDE-STAT-2020-2024 | U54: 2026-09-10 23:00:00 | V54: Sistema/region: Metropolitano.
A55: R0000058 | B55: 2020-01-01 | C55: 2020-12-31 | D55: year | E55: PY_REGION_ENERGY | F55: PY_REGION_CENTRAL | G55: PY | H55: PY | I55: 1833781 | J55: MWh | K55: 1833781 | L55: MWh | M55: ANDE | N55: OFFICIAL_PRIMARY | O55: OFFICIAL_AGGREGATE | P55: 1 | Q55: 50 | R55: https://www.ande.gov.py/finanzas/ANDE%20-%20Resumen%20Estad%C3%ADstico%202020%20-%202024.pdf | S55: ANDE-STAT-2020-2024 | U55: 2026-09-10 23:00:00 | V55: Sistema/region: Central.
A56: R0000059 | B56: 2021-01-01 | C56: 2021-12-31 | D56: year | E56: PY_REGION_ENERGY | F56: PY_REGION_CENTRAL | G56: PY | H56: PY | I56: 1985053 | J56: MWh | K56: 1985053 | L56: MWh | M56: ANDE | N56: OFFICIAL_PRIMARY | O56: OFFICIAL_AGGREGATE | P56: 1 | Q56: 50 | R56: https://www.ande.gov.py/finanzas/ANDE%20-%20Resumen%20Estad%C3%ADstico%202020%20-%202024.pdf | S56: ANDE-STAT-2020-2024 | U56: 2026-09-10 23:00:00 | V56: Sistema/region: Central.
A57: R0000060 | B57: 2022-01-01 | C57: 2022-12-31 | D57: year | E57: PY_REGION_ENERGY | F57: PY_REGION_CENTRAL | G57: PY | H57: PY | I57: 2373625 | J57: MWh | K57: 2373625 | L57: MWh | M57: ANDE | N57: OFFICIAL_PRIMARY | O57: OFFICIAL_AGGREGATE | P57: 1 | Q57: 50 | R57: https://www.ande.gov.py/finanzas/ANDE%20-%20Resumen%20Estad%C3%ADstico%202020%20-%202024.pdf | S57: ANDE-STAT-2020-2024 | U57: 2026-09-10 23:00:00 | V57: Sistema/region: Central.
... A137: R0000141 | B137: 2026-01-01 | C137: 2026-05-31 | D137: period | E137: PY_CONSUMPTION_ENERGY_YTD | F137: PY_SIN | G137: PY | H137: PY | I137: 14587100 | J137: MWh | K137: 14587100 | L137: MWh | M137: ANDE | N137: OFFICIAL_PRIMARY | O137: OFFICIAL_AGGREGATE | P137: 1 | Q137: 50 | R137: https://www.ande.gov.py/interna.php?id=15361 | S137: ANDE-MAY-2026 | U137: 2026-09-10 23:00:00 | V137: Acumulado enero-mayo publicado por ANDE.
A138: R0000142 | B138: 2025-08-14 06:23:00 | C138: 2025-08-14 06:23:00 | D138: event | E138: PY_DEMAND | F138: PY_SIN | G138: PY | H138: PY | I138: 3070 | J138: MW | K138: 3070 | L138: MW | M138: ANDE | N138: OFFICIAL_PRIMARY | O138: OFFICIAL_MEASURED | P138: 1 | Q138: 50 | R138: https://www.ande.gov.py/interna.php?id=14173 | U138: 2026-09-10 23:00:00 | V138: Evento: Avería en interruptor 220 kV de Acaray; demanda reportada al momento del inconveniente. ANDE indica abastecimiento principalmente por Itaipú; no desglosa MW por central.
A139: R0000143 | B139: 2025-12-15 14:12:00 | C139: 2025-12-15 14:12:00 | D139: event | E139: PY_DEMAND | F139: PY_SIN | G139: PY | H139: PY | I139: 5280 | J139: MW | K139: 5280 | L139: MW | M139: ANDE | N139: OFFICIAL_PRIMARY | O139: OFFICIAL_MEASURED | P139: 1 | Q139: 50 | R139: https://www.ande.gov.py/interna.php?id=14816 | U139: 2026-09-10 23:00:00 | V139: Récord: Nuevo récord histórico de demanda instantánea 2025. La suma de aportes + exportación puede diferir conceptualmente de demanda según convención de signo/medición.
A140: R0000144 | B140: 2025-12-15 14:12:00 | C140: 2025-12-15 14:12:00 | D140: event | E140: POWER_TO_PY | F140: ITAIPU | G140: ITAIPU | H140: PY | I140: 3745 | J140: MW | K140: 3745 | L140: MW | M140: ANDE | N140: OFFICIAL_PRIMARY | O140: OFFICIAL_MEASURED | P140: 1 | Q140: 50 | R140: https://www.ande.gov.py/interna.php?id=14816 | U140: 2026-09-10 23:00:00 | V140: Récord: Nuevo récord histórico de demanda instantánea 2025. La suma de aportes + exportación puede diferir conceptualmente de demanda según convención de signo/medición.
A141: R0000145 | B141: 2025-12-15 14:12:00 | C141: 2025-12-15 14:12:00 | D141: event | E141: POWER_TO_PY | F141: YACYRETA | G141: YACYRETA | H141: PY | I141: 1419 | J141: MW | K141: 1419 | L141: MW | M141: ANDE | N141: OFFICIAL_PRIMARY | O141: OFFICIAL_MEASURED | P141: 1 | Q141: 50 | R141: https://www.ande.gov.py/interna.php?id=14816 | U141: 2026-09-10 23:00:00 | V141: Récord: Nuevo récord histórico de demanda instantánea 2025. La suma de aportes + exportación puede diferir conceptualmente de demanda según convención de signo/medición.
A142: R0000146 | B142: 2025-12-15 14:12:00 | C142: 2025-12-15 14:12:00 | D142: event | E142: POWER_TO_PY | F142: ACARAY | G142: ACARAY | H142: PY | I142: 132 | J142: MW | K142: 132 | L142: MW | M142: ANDE | N142: OFFICIAL_PRIMARY | O142: OFFICIAL_MEASURED | P142: 1 | Q142: 50 | R142: https://www.ande.gov.py/interna.php?id=14816 | U142: 2026-09-10 23:00:00 | V142: Récord: Nuevo récord histórico de demanda instantánea 2025. La suma de aportes + exportación puede diferir conceptualmente de demanda según convención de signo/medición.
A143: R0000147 | B143: 2025-12-15 14:12:00 | C143: 2025-12-15 14:12:00 | D143: event | E143: PY_EXPORT_POWER | F143: PY_SIN | G143: PY | H143: EXTERNAL | I143: 16 | J143: MW | K143: 16 | L143: MW | M143: ANDE | N143: OFFICIAL_PRIMARY | O143: OFFICIAL_MEASURED | P143: 1 | Q143: 50 | R143: https://www.ande.gov.py/interna.php?id=14816 | U143: 2026-09-10 23:00:00 | V143: Récord: Nuevo récord histórico de demanda instantánea 2025. La suma de aportes + exportación puede diferir conceptualmente de demanda según convención de signo/medición.
A144: R0000148 | B144: 2026-01-26 00:00:00 | C144: 2026-01-26 00:00:00 | D144: event | E144: PY_DEMAND | F144: PY_SIN | G144: PY | H144: PY | I144: 5752 | J144: MW | K144: 5752 | L144: MW | M144: ANDE | N144: OFFICIAL_PRIMARY | O144: OFFICIAL_MEASURED | P144: 1 | Q144: 50 | R144: https://www.ande.gov.py/interna.php?id=14950 | U144: 2026-09-10 23:00:00 | V144: Récord: Récord histórico del SIN reportado por ANDE. No se publicó en esa nota el reparto instantáneo por central.
A145: R0000149 | B145: 2026-02-18 14:05:00 | C145: 2026-02-18 14:05:00 | D145: event | E145: PY_DEMAND | F145: PY_SIN | G145: PY | H145: PY | I145: 5690 | J145: MW | K145: 5690 | L145: MW | M145: ANDE | N145: OFFICIAL_PRIMARY | O145: OFFICIAL_MEASURED | P145: 1 | Q145: 50 | R145: https://www.ande.gov.py/interna.php?id=14999 | U145: 2026-09-10 23:00:00 | V145: Pico diario: Máximo de consumo del día antes del incidente. Sistema sin perturbaciones.
A146: R0000150 | B146: 2026-02-18 15:18:00 | C146: 2026-02-18 15:18:00 | D146: event | E146: PY_DEMAND | F146: PY_SIN | G146: PY | H146: PY | I146: 5330 | J146: MW | K146: 5330 | L146: MW | M146: ANDE | N146: OFFICIAL_PRIMARY | O146: OFFICIAL_MEASURED | P146: 1 | Q146: 50 | R146: https://www.ande.gov.py/interna.php?id=14999 | U146: 2026-09-10 23:00:00 | V146: Evento: Carga del sistema al inicio de la perturbación. Suma de las tres centrales = 5.330 MW, consistente con la carga reportada.
A147: R0000151 | B147: 2026-02-18 15:18:00 | C147: 2026-02-18 15:18:00 | D147: event | E147: POWER_TO_PY | F147: ITAIPU | G147: ITAIPU | H147: PY | I147: 3746 | J147: MW | K147: 3746 | L147: MW | M147: ANDE | N147: OFFICIAL_PRIMARY | O147: OFFICIAL_MEASURED | P147: 1 | Q147: 50 | R147: https://www.ande.gov.py/interna.php?id=14999 | U147: 2026-09-10 23:00:00 | V147: Evento: Carga del sistema al inicio de la perturbación. Suma de las tres centrales = 5.330 MW, consistente con la carga reportada.
A148: R0000152 | B148: 2026-02-18 15:18:00 | C148: 2026-02-18 15:18:00 | D148: event | E148: POWER_TO_PY | F148: YACYRETA | G148: YACYRETA | H148: PY | I148: 1454 | J148: MW | K148: 1454 | L148: MW | M148: ANDE | N148: OFFICIAL_PRIMARY | O148: OFFICIAL_MEASURED | P148: 1 | Q148: 50 | R148: https://www.ande.gov.py/interna.php?id=14999 | U148: 2026-09-10 23:00:00 | V148: Evento: Carga del sistema al inicio de la perturbación. Suma de las tres centrales = 5.330 MW, consistente con la carga reportada.
A149: R0000153 | B149: 2026-02-18 15:18:00 | C149: 2026-02-18 15:18:00 | D149: event | E149: POWER_TO_PY | F149: ACARAY | G149: ACARAY | H149: PY | I149: 130 | J149: MW | K149: 130 | L149: MW | M149: ANDE | N149: OFFICIAL_PRIMARY | O149: OFFICIAL_MEASURED | P149: 1 | Q149: 50 | R149: https://www.ande.gov.py/interna.php?id=14999 | U149: 2026-09-10 23:00:00 | V149: Evento: Carga del sistema al inicio de la perturbación. Suma de las tres centrales = 5.330 MW, consistente con la carga reportada.
... A153: R0000157 | B153: 2022-01-01 | C153: 2022-07-31 | D153: period | E153: PY_CONSUMPTION_ENERGY | F153: PY_SIN | G153: PY | H153: PY | I153: 11583364 | J153: MWh | K153: 11583364 | L153: MWh | M153: ANDE | N153: OFFICIAL_PRIMARY | O153: OFFICIAL_AGGREGATE | P153: 1 | Q153: 50 | R153: https://www.ande.gov.py/interna.php?id=10223 | U153: 2026-09-10 23:00:00 | V153: Acumulado enero-julio 2022 publicado por ANDE.
A154: R0000158 | B154: 1994-08-01 | C154: 1994-08-31 | D154: month | E154: YACYRETA_NET_ENERGY | F154: YACYRETA | G154: YACYRETA | H154: TOTAL | I154: 826 | J154: MWh | K154: 826 | L154: MWh | M154: EBY | N154: OFFICIAL_PRIMARY | O154: OFFICIAL_AGGREGATE | P154: 1 | Q154: 50 | R154: https://www.eby.gov.py/wp-content/uploads/2019/12/YacyretaEnergiasMensualesDesdePuestaenMarcha.pdf | S154: EBY-MONTHLY-1994-2012 | U154: 2026-09-10 23:00:00 | V154: Energia mensual Yacyreta desde puesta en marcha.
A155: R0000159 | B155: 1994-08-01 | C155: 1994-08-31 | D155: month | E155: ENERGY_TO_ARGENTINA | F155: YACYRETA | G155: YACYRETA | H155: SADI | I155: 826 | J155: MWh | K155: 826 | L155: MWh | M155: EBY | N155: OFFICIAL_PRIMARY | O155: OFFICIAL_AGGREGATE | P155: 1 | Q155: 50 | R155: https://www.eby.gov.py/wp-content/uploads/2019/12/YacyretaEnergiasMensualesDesdePuestaenMarcha.pdf | S155: EBY-MONTHLY-1994-2012 | U155: 2026-09-10 23:00:00 | V155: Energia mensual entregada al SADI.
A156: R0000160 | B156: 1994-08-01 | C156: 1994-08-31 | D156: month | E156: ENERGY_TO_PY | F156: YACYRETA | G156: YACYRETA | H156: SINP | I156: 0 | J156: MWh | K156: 0 | L156: MWh | M156: EBY | N156: OFFICIAL_PRIMARY | O156: OFFICIAL_AGGREGATE | P156: 1 | Q156: 50 | R156: https://www.eby.gov.py/wp-content/uploads/2019/12/YacyretaEnergiasMensualesDesdePuestaenMarcha.pdf | S156: EBY-MONTHLY-1994-2012 | U156: 2026-09-10 23:00:00 | V156: Energia mensual entregada al SINP.
A157: R0000161 | B157: 1994-09-01 | C157: 1994-09-30 | D157: month | E157: YACYRETA_NET_ENERGY | F157: YACYRETA | G157: YACYRETA | H157: TOTAL | I157: 55808 | J157: MWh | K157: 55808 | L157: MWh | M157: EBY | N157: OFFICIAL_PRIMARY | O157: OFFICIAL_AGGREGATE | P157: 1 | Q157: 50 | R157: https://www.eby.gov.py/wp-content/uploads/2019/12/YacyretaEnergiasMensualesDesdePuestaenMarcha.pdf | S157: EBY-MONTHLY-1994-2012 | U157: 2026-09-10 23:00:00 | V157: Energia mensual Yacyreta desde puesta en marcha.
A158: R0000162 | B158: 1994-09-01 | C158: 1994-09-30 | D158: month | E158: ENERGY_TO_ARGENTINA | F158: YACYRETA | G158: YACYRETA | H158: SADI | I158: 55808 | J158: MWh | K158: 55808 | L158: MWh | M158: EBY | N158: OFFICIAL_PRIMARY | O158: OFFICIAL_AGGREGATE | P158: 1 | Q158: 50 | R158: https://www.eby.gov.py/wp-content/uploads/2019/12/YacyretaEnergiasMensualesDesdePuestaenMarcha.pdf | S158: EBY-MONTHLY-1994-2012 | U158: 2026-09-10 23:00:00 | V158: Energia mensual entregada al SADI.
A159: R0000163 | B159: 1994-09-01 | C159: 1994-09-30 | D159: month | E159: ENERGY_TO_PY | F159: YACYRETA | G159: YACYRETA | H159: SINP | I159: 0 | J159: MWh | K159: 0 | L159: MWh | M159: EBY | N159: OFFICIAL_PRIMARY | O159: OFFICIAL_AGGREGATE | P159: 1 | Q159: 50 | R159: https://www.eby.gov.py/wp-content/uploads/2019/12/YacyretaEnergiasMensualesDesdePuestaenMarcha.pdf | S159: EBY-MONTHLY-1994-2012 | U159: 2026-09-10 23:00:00 | V159: Energia mensual entregada al SINP.
A160: R0000164 | B160: 1994-10-01 | C160: 1994-10-31 | D160: month | E160: YACYRETA_NET_ENERGY | F160: YACYRETA | G160: YACYRETA | H160: TOTAL | I160: 62043 | J160: MWh | K160: 62043 | L160: MWh | M160: EBY | N160: OFFICIAL_PRIMARY | O160: OFFICIAL_AGGREGATE | P160: 1 | Q160: 50 | R160: https://www.eby.gov.py/wp-content/uploads/2019/12/YacyretaEnergiasMensualesDesdePuestaenMarcha.pdf | S160: EBY-MONTHLY-1994-2012 | U160: 2026-09-10 23:00:00 | V160: Energia mensual Yacyreta desde puesta en marcha.
A161: R0000165 | B161: 1994-10-01 | C161: 1994-10-31 | D161: month | E161: ENERGY_TO_ARGENTINA | F161: YACYRETA | G161: YACYRETA | H161: SADI | I161: 62043 | J161: MWh | K161: 62043 | L161: MWh | M161: EBY | N161: OFFICIAL_PRIMARY | O161: OFFICIAL_AGGREGATE | P161: 1 | Q161: 50 | R161: https://www.eby.gov.py/wp-content/uploads/2019/12/YacyretaEnergiasMensualesDesdePuestaenMarcha.pdf | S161: EBY-MONTHLY-1994-2012 | U161: 2026-09-10 23:00:00 | V161: Energia mensual entregada al SADI.
A162: R0000166 | B162: 1994-10-01 | C162: 1994-10-31 | D162: month | E162: ENERGY_TO_PY | F162: YACYRETA | G162: YACYRETA | H162: SINP | I162: 0 | J162: MWh | K162: 0 | L162: MWh | M162: EBY | N162: OFFICIAL_PRIMARY | O162: OFFICIAL_AGGREGATE | P162: 1 | Q162: 50 | R162: https://www.eby.gov.py/wp-content/uploads/2019/12/YacyretaEnergiasMensualesDesdePuestaenMarcha.pdf | S162: EBY-MONTHLY-1994-2012 | U162: 2026-09-10 23:00:00 | V162: Energia mensual entregada al SINP.
A163: R0000167 | B163: 1994-11-01 | C163: 1994-11-30 | D163: month | E163: YACYRETA_NET_ENERGY | F163: YACYRETA | G163: YACYRETA | H163: TOTAL | I163: 105254 | J163: MWh | K163: 105254 | L163: MWh | M163: EBY | N163: OFFICIAL_PRIMARY | O163: OFFICIAL_AGGREGATE | P163: 1 | Q163: 50 | R163: https://www.eby.gov.py/wp-content/uploads/2019/12/YacyretaEnergiasMensualesDesdePuestaenMarcha.pdf | S163: EBY-MONTHLY-1994-2012 | U163: 2026-09-10 23:00:00 | V163: Energia mensual Yacyreta desde puesta en marcha.
A164: R0000168 | B164: 1994-11-01 | C164: 1994-11-30 | D164: month | E164: ENERGY_TO_ARGENTINA | F164: YACYRETA | G164: YACYRETA | H164: SADI | I164: 105254 | J164: MWh | K164: 105254 | L164: MWh | M164: EBY | N164: OFFICIAL_PRIMARY | O164: OFFICIAL_AGGREGATE | P164: 1 | Q164: 50 | R164: https://www.eby.gov.py/wp-content/uploads/2019/12/YacyretaEnergiasMensualesDesdePuestaenMarcha.pdf | S164: EBY-MONTHLY-1994-2012 | U164: 2026-09-10 23:00:00 | V164: Energia mensual entregada al SADI.
A165: R0000169 | B165: 1994-11-01 | C165: 1994-11-30 | D165: month | E165: ENERGY_TO_PY | F165: YACYRETA | G165: YACYRETA | H165: SINP | I165: 0 | J165: MWh | K165: 0 | L165: MWh | M165: EBY | N165: OFFICIAL_PRIMARY | O165: OFFICIAL_AGGREGATE | P165: 1 | Q165: 50 | R165: https://www.eby.gov.py/wp-content/uploads/2019/12/YacyretaEnergiasMensualesDesdePuestaenMarcha.pdf | S165: EBY-MONTHLY-1994-2012 | U165: 2026-09-10 23:00:00 | V165: Energia mensual entregada al SINP.
... A1341: R0001457 | B1341: 2023-12-01 | C1341: 2023-12-31 | D1341: month | E1341: ITAIPU_SUPPLIED_ENERGY | F1341: ITAIPU | G1341: ITAIPU | H1341: BR | I1341: 6324000 | J1341: MWh | K1341: 6324000 | L1341: MWh | M1341: ITAIPU | N1341: OFFICIAL_PRIMARY | O1341: OFFICIAL_AGGREGATE | P1341: 1 | Q1341: 98 | R1341: https://www.itaipu.gov.py/sites/default/files/u62/Memoria%20Anual%20Itaipu%202023_Espa%C3%B1ol_internet.pdf | S1341: ITAIPU-MEM-2023 | U1341: 2026-09-11 00:05:00 | V1341: Tabla mensual oficial, valores redondeados a GWh.
A1342: V5_0001 | B1342: 2026-01-01 | C1342: 2026-08-31 | D1342: YTD | E1342: ITAIPU_SUPPLY_TO_PY | F1342: ITAIPU | I1342: 19276 | J1342: GWh | K1342: 19276 | L1342: GWh | M1342: ITAIPU | N1342: OFFICIAL_PRIMARY | O1342: OFFICIAL_AGGREGATE | P1342: 1 | Q1342: 95 | R1342: https://www.itaipu.gov.py/noticias/energia/itaipu-suministro-19-276-gwh-de-energia-electrica-a-la-ande-de-enero-a-agosto-de-2026 | S1342: V5_CURRENT_BASELINES | U1342: 2026-09-11T01:00:00-03:00 | V1342: Supplied to Paraguay through ANDE Jan-Aug 2026.
A1343: V5_0002 | B1343: 2026-01-01 | C1343: 2026-08-31 | D1343: YTD | E1343: ITAIPU_TOTAL_GENERATION | F1343: ITAIPU | I1343: 51144 | J1343: GWh | K1343: 51144 | L1343: GWh | M1343: ITAIPU | N1343: OFFICIAL_PRIMARY | O1343: OFFICIAL_AGGREGATE | P1343: 1 | Q1343: 95 | R1343: https://www.itaipu.gov.py/noticias/energia/itaipu-suministro-19-276-gwh-de-energia-electrica-a-la-ande-de-enero-a-agosto-de-2026 | S1343: V5_CURRENT_BASELINES | U1343: 2026-09-11T01:00:00-03:00 | V1343: Total generation Jan-Aug 2026.
A1344: V5_0003 | B1344: 2026-01-01 | C1344: 2026-08-31 | D1344: YTD | E1344: ITAIPU_UNIT_AVAILABILITY | F1344: ITAIPU | I1344: 96.35 | J1344: percent | K1344: 96.35 | L1344: percent | M1344: ITAIPU | N1344: OFFICIAL_PRIMARY | O1344: OFFICIAL_AGGREGATE | P1344: 1 | Q1344: 95 | R1344: https://www.itaipu.gov.py/noticias/energia/itaipu-suministro-19-276-gwh-de-energia-electrica-a-la-ande-de-enero-a-agosto-de-2026 | S1344: V5_CURRENT_BASELINES | U1344: 2026-09-11T01:00:00-03:00 | V1344: Availability through August 2026.
A1345: V5_0004 | B1345: 2026-08-01 | C1345: 2026-08-31 | D1345: month | E1345: ITAIPU_AUG_TOTAL_GENERATION | F1345: ITAIPU | I1345: 6796 | J1345: GWh | K1345: 6796 | L1345: GWh | M1345: ITAIPU | N1345: OFFICIAL_PRIMARY | O1345: OFFICIAL_AGGREGATE | P1345: 1 | Q1345: 95 | R1345: https://www.itaipu.gov.py/noticias/energia/itaipu-suministro-19-276-gwh-de-energia-electrica-a-la-ande-de-enero-a-agosto-de-2026 | S1345: V5_CURRENT_BASELINES | U1345: 2026-09-11T01:00:00-03:00
A1346: V5_0005 | B1346: 2026-08-01 | C1346: 2026-08-31 | D1346: month | E1346: ITAIPU_AUG_50HZ_GENERATION | F1346: ITAIPU | I1346: 3428 | J1346: GWh | K1346: 3428 | L1346: GWh | M1346: ITAIPU | N1346: OFFICIAL_PRIMARY | O1346: OFFICIAL_AGGREGATE | P1346: 1 | Q1346: 95 | R1346: https://www.itaipu.gov.py/noticias/energia/itaipu-suministro-19-276-gwh-de-energia-electrica-a-la-ande-de-enero-a-agosto-de-2026 | S1346: V5_CURRENT_BASELINES | U1346: 2026-09-11T01:00:00-03:00
A1347: V5_0006 | B1347: 2026-08-01 | C1347: 2026-08-31 | D1347: month | E1347: ITAIPU_AUG_SUPPLY_TO_ANDE | F1347: ITAIPU | I1347: 2401 | J1347: GWh | K1347: 2401 | L1347: GWh | M1347: ITAIPU | N1347: OFFICIAL_PRIMARY | O1347: OFFICIAL_AGGREGATE | P1347: 1 | Q1347: 95 | R1347: https://www.itaipu.gov.py/noticias/energia/itaipu-suministro-19-276-gwh-de-energia-electrica-a-la-ande-de-enero-a-agosto-de-2026 | S1347: V5_CURRENT_BASELINES | U1347: 2026-09-11T01:00:00-03:00
A1348: V5_0007 | B1348: 2026-01-01 | C1348: 2026-08-31 | D1348: YTD_avg | E1348: ITAIPU_AVG_POWER_TO_PY_EQUIV | F1348: ITAIPU | I1348: 3305.213 | J1348: MW | K1348: 3305.213 | L1348: MW | M1348: ENERGIAPY | N1348: DERIVED | O1348: DERIVED_FROM_OFFICIAL | P1348: 1 | Q1348: 80 | R1348: https://www.itaipu.gov.py/noticias/energia/itaipu-suministro-19-276-gwh-de-energia-electrica-a-la-ande-de-enero-a-agosto-de-2026 | S1348: V5_CURRENT_BASELINES | U1348: 2026-09-11T01:00:00-03:00 | V1348: Energy/time equivalent average; not an instantaneous measurement.
A1349: V5_0008 | B1349: 2026-01-01 | C1349: 2026-08-31 | D1349: YTD_avg | E1349: ITAIPU_AVG_TOTAL_POWER_EQUIV | F1349: ITAIPU | I1349: 8769.547 | J1349: MW | K1349: 8769.547 | L1349: MW | M1349: ENERGIAPY | N1349: DERIVED | O1349: DERIVED_FROM_OFFICIAL | P1349: 1 | Q1349: 80 | R1349: https://www.itaipu.gov.py/noticias/energia/itaipu-suministro-19-276-gwh-de-energia-electrica-a-la-ande-de-enero-a-agosto-de-2026 | S1349: V5_CURRENT_BASELINES | U1349: 2026-09-11T01:00:00-03:00 | V1349: Energy/time equivalent average; not an instantaneous measurement.
A1350: V5_0009 | B1350: 2026-08-01 | C1350: 2026-08-31 | D1350: month_avg | E1350: ITAIPU_AUG_AVG_POWER_EQUIV | F1350: ITAIPU | I1350: 9134.409 | J1350: MW | K1350: 9134.409 | L1350: MW | M1350: ENERGIAPY | N1350: DERIVED | O1350: DERIVED_FROM_OFFICIAL | P1350: 1 | Q1350: 80 | R1350: https://www.itaipu.gov.py/noticias/energia/itaipu-suministro-19-276-gwh-de-energia-electrica-a-la-ande-de-enero-a-agosto-de-2026 | S1350: V5_CURRENT_BASELINES | U1350: 2026-09-11T01:00:00-03:00
A1351: V5_0010 | B1351: 2026-08-01 | C1351: 2026-08-31 | D1351: month_avg | E1351: ITAIPU_AUG_AVG_TO_ANDE_EQUIV | F1351: ITAIPU | I1351: 3227.151 | J1351: MW | K1351: 3227.151 | L1351: MW | M1351: ENERGIAPY | N1351: DERIVED | O1351: DERIVED_FROM_OFFICIAL | P1351: 1 | Q1351: 80 | R1351: https://www.itaipu.gov.py/noticias/energia/itaipu-suministro-19-276-gwh-de-energia-electrica-a-la-ande-de-enero-a-agosto-de-2026 | S1351: V5_CURRENT_BASELINES | U1351: 2026-09-11T01:00:00-03:00
A1352: V5_0011 | B1352: 2026-09-11 | C1352: 2026-09-11 | D1352: latest_hour_label | E1352: YACYRETA_POWER_LAST_HOUR | F1352: YACYRETA | I1352: 2034 | J1352: MW | K1352: 2034 | L1352: MW | M1352: EBY | N1352: OFFICIAL_PRIMARY | O1352: OFFICIAL_WEB_CURRENT | P1352: 1 | Q1352: 95 | R1352: https://eby.gov.py/ | S1352: V5_CURRENT_BASELINES | U1352: 2026-09-11T01:00:00-03:00 | V1352: EBY homepage says power generated in the last hour; exact measurement timestamp is not exposed.
A1353: V5_0012 | B1353: 2026-09-10 | C1353: 2026-09-10 | D1353: 06:00 | E1353: YACYRETA_RESERVOIR_LEVEL | F1353: YACYRETA | I1353: 82.82 | J1353: mSNM | K1353: 82.82 | L1353: mSNM | M1353: EBY | N1353: OFFICIAL_PRIMARY | O1353: OFFICIAL_MEASURED | P1353: 1 | Q1353: 95 | R1353: https://eby.gov.py/cota-82-82-msnm-resumen-ejecutivo-n-6077-10-09-2026/ | S1353: V5_CURRENT_BASELINES | U1353: 2026-09-11T01:00:00-03:00
A1354: V5_0013 | B1354: 2026-09-10 | C1354: 2026-09-10 | D1354: day | E1354: YACYRETA_INFLOW_FORECAST | F1354: YACYRETA | I1354: 13400 | J1354: m3/s | K1354: 13400 | L1354: m3/s | M1354: EBY | N1354: OFFICIAL_PRIMARY | O1354: OFFICIAL_FORECAST | P1354: 1 | Q1354: 95 | R1354: https://eby.gov.py/cota-82-82-msnm-resumen-ejecutivo-n-6077-10-09-2026/ | S1354: V5_CURRENT_BASELINES | U1354: 2026-09-11T01:00:00-03:00
A1355: V5_0014 | B1355: 2026-09-11 | C1355: 2026-09-11 | D1355: day | E1355: YACYRETA_INFLOW_FORECAST_NEXT_DAY | F1355: YACYRETA | I1355: 14500 | J1355: m3/s | K1355: 14500 | L1355: m3/s | M1355: EBY | N1355: OFFICIAL_PRIMARY | O1355: OFFICIAL_FORECAST | P1355: 1 | Q1355: 95 | R1355: https://eby.gov.py/cota-82-82-msnm-resumen-ejecutivo-n-6077-10-09-2026/ | S1355: V5_CURRENT_BASELINES | U1355: 2026-09-11T01:00:00-03:00
A1356: V5_0015 | B1356: 2026-09-10 | C1356: 2026-09-10 | D1356: day | E1356: YACYRETA_ANACUA_FLOW | F1356: YACYRETA | I1356: 1000 | J1356: m3/s | K1356: 1000 | L1356: m3/s | M1356: EBY | N1356: OFFICIAL_PRIMARY | O1356: OFFICIAL_OPERATIONAL | P1356: 1 | Q1356: 95 | R1356: https://eby.gov.py/cota-82-82-msnm-resumen-ejecutivo-n-6077-10-09-2026/ | S1356: V5_CURRENT_BASELINES | U1356: 2026-09-11T01:00:00-03:00 | V1356: Brazo Ana Cua spillway.
A1357: V5_0016 | B1357: 2026-09-10 | C1357: 2026-09-10 | D1357: day | E1357: AYOLAS_RIVER_LEVEL | F1357: AYOLAS | I1357: 1.8 | J1357: m | K1357: 1.8 | L1357: m | M1357: EBY | N1357: OFFICIAL_PRIMARY | O1357: OFFICIAL_MEASURED | P1357: 1 | Q1357: 95 | R1357: https://eby.gov.py/cota-82-82-msnm-resumen-ejecutivo-n-6077-10-09-2026/ | S1357: V5_CURRENT_BASELINES | U1357: 2026-09-11T01:00:00-03:00
A1358: V5_0017 | B1358: 2026-09-10 | C1358: 2026-09-10 | D1358: 02:00 | E1358: ITUZAINGO_RIVER_LEVEL | F1358: ITUZAINGO | I1358: 1.6 | J1358: m | K1358: 1.6 | L1358: m | M1358: EBY | N1358: OFFICIAL_PRIMARY | O1358: OFFICIAL_MEASURED | P1358: 1 | Q1358: 95 | R1358: https://eby.gov.py/cota-82-82-msnm-resumen-ejecutivo-n-6077-10-09-2026/ | S1358: V5_CURRENT_BASELINES | U1358: 2026-09-11T01:00:00-03:00
A1359: V5_0018 | B1359: 2025-01-01 | C1359: 2025-12-31 | D1359: year | E1359: PY_SIN_ENERGY_CONSUMPTION | F1359: PY_SIN | I1359: 29418538 | J1359: MWh | K1359: 29418538 | L1359: MWh | M1359: ANDE | N1359: OFFICIAL_PRIMARY | O1359: OFFICIAL_AGGREGATE | P1359: 1 | Q1359: 95 | R1359: https://www.ande.gov.py/finanzas/BAGP%202025%20ANDE.pdf | S1359: V5_CURRENT_BASELINES | U1359: 2026-09-11T01:00:00-03:00
A1360: V5_0019 | B1360: 2025-01-01 | C1360: 2025-12-31 | D1360: year | E1360: PY_SIN_MAX_DEMAND | F1360: PY_SIN | I1360: 5280 | J1360: MW | K1360: 5280 | L1360: MW | M1360: ANDE | N1360: OFFICIAL_PRIMARY | O1360: OFFICIAL_AGGREGATE | P1360: 1 | Q1360: 95 | R1360: https://www.ande.gov.py/finanzas/BAGP%202025%20ANDE.pdf | S1360: V5_CURRENT_BASELINES | U1360: 2026-09-11T01:00:00-03:00
A1361: V5_0020 | B1361: 2025-01-01 | C1361: 2025-12-31 | D1361: year | E1361: PY_SIN_LOAD_FACTOR | F1361: PY_SIN | I1361: 63.6 | J1361: percent | K1361: 63.6 | L1361: percent | M1361: ANDE | N1361: OFFICIAL_PRIMARY | O1361: OFFICIAL_AGGREGATE | P1361: 1 | Q1361: 95 | R1361: https://www.ande.gov.py/finanzas/BAGP%202025%20ANDE.pdf | S1361: V5_CURRENT_BASELINES | U1361: 2026-09-11T01:00:00-03:00
A1362: V5_0021 | B1362: 2025-01-01 | C1362: 2025-12-31 | D1362: year | E1362: ANDE_TOTAL_LOSS_RATE | F1362: PY_GRID | I1362: 24.4 | J1362: percent | K1362: 24.4 | L1362: percent | M1362: ANDE | N1362: OFFICIAL_PRIMARY | O1362: OFFICIAL_AGGREGATE | P1362: 1 | Q1362: 95 | R1362: https://www.ande.gov.py/finanzas/BAGP%202025%20ANDE.pdf | S1362: V5_CURRENT_BASELINES | U1362: 2026-09-11T01:00:00-03:00 | V1362: BAGP annual canonical figure. ANDE news rounds this to 24.5%.
A1363: V5_0022 | B1363: 2025-01-01 | C1363: 2025-12-31 | D1363: year | E1363: ANDE_DISTRIBUTION_LOSS_RATE | F1363: PY_GRID | I1363: 20.03 | J1363: percent | K1363: 20.03 | L1363: percent | M1363: ANDE | N1363: OFFICIAL_PRIMARY | O1363: OFFICIAL_RELEASE | P1363: 1 | Q1363: 95 | R1363: https://www.ande.gov.py/interna.php?id=15116 | S1363: V5_CURRENT_BASELINES | U1363: 2026-09-11T01:00:00-03:00
A1364: V5_0023 | B1364: 2024-12-01 | C1364: 2025-03-31 | D1364: season | E1364: DEP_METROPOLITAN_SUMMER | F1364: PY_GRID_METRO | I1364: 2.44 | J1364: hours | K1364: 2.44 | L1364: hours | M1364: ANDE | N1364: OFFICIAL_PRIMARY | O1364: OFFICIAL_RELEASE | P1364: 1 | Q1364: 95 | R1364: https://www.ande.gov.py/interna.php?id=13680 | S1364: V5_CURRENT_BASELINES | U1364: 2026-09-11T01:00:00-03:00
A1365: V5_0024 | B1365: 2024-12-01 | C1365: 2025-03-31 | D1365: season | E1365: FEP_METROPOLITAN_SUMMER | F1365: PY_GRID_METRO | I1365: 3.79 | J1365: interruptions_equivalent | K1365: 3.79 | L1365: interruptions_equivalent | M1365: ANDE | N1365: OFFICIAL_PRIMARY | O1365: OFFICIAL_RELEASE | P1365: 1 | Q1365: 95 | R1365: https://www.ande.gov.py/interna.php?id=13680 | S1365: V5_CURRENT_BASELINES | U1365: 2026-09-11T01:00:00-03:00
A1366: V5_0025 | B1366: 2025-01-01 | C1366: 2025-12-31 | D1366: year | E1366: TARIFA_SOCIAL_SUBSIDY_TOTAL | F1366: PY_HOUSEHOLDS | I1366: 50185 | J1366: million_PYG | K1366: 50185 | L1366: million_PYG | M1366: ANDE | N1366: OFFICIAL_PRIMARY | O1366: OFFICIAL_AGGREGATE | P1366: 1 | Q1366: 95 | R1366: https://www.ande.gov.py/finanzas/BAGP%202025%20ANDE.pdf | S1366: V5_CURRENT_BASELINES | U1366: 2026-09-11T01:00:00-03:00
A1367: V5_0026 | B1367: 2025-01-01 | C1367: 2025-12-31 | D1367: year_avg | E1367: TARIFA_SOCIAL_SUBSIDY_MONTHLY_AVG | F1367: PY_HOUSEHOLDS | I1367: 4182 | J1367: million_PYG/month | K1367: 4182 | L1367: million_PYG/month | M1367: ANDE | N1367: OFFICIAL_PRIMARY | O1367: OFFICIAL_AGGREGATE | P1367: 1 | Q1367: 95 | R1367: https://www.ande.gov.py/finanzas/BAGP%202025%20ANDE.pdf | S1367: V5_CURRENT_BASELINES | U1367: 2026-09-11T01:00:00-03:00 | V1367: Published average in BAGP.
A1368: V5_0027 | B1368: 2024-01-01 | C1368: 2025-12-31 | D1368: 2y | E1368: ILLEGAL_CRYPTO_POWER_INTERVENED | F1368: PY_GRID | I1368: 91.8 | J1368: MW | K1368: 91.8 | L1368: MW | M1368: ANDE | N1368: OFFICIAL_PRIMARY | O1368: OFFICIAL_RELEASE | P1368: 1 | Q1368: 95 | R1368: https://www.ande.gov.py/interna.php?id=15116 | S1368: V5_CURRENT_BASELINES | U1368: 2026-09-11T01:00:00-03:00 | V1368: 37 illegal crypto farms intervened in 2024-2025.
A1369: V5_0028 | B1369: 2024-01-01 | C1369: 2025-12-31 | D1369: 2y_context | E1369: ILLEGAL_CRYPTO_AVOIDED_LOSS_MONTHLY | F1369: PY_GRID | I1369: 18600 | J1369: million_PYG/month | K1369: 18600 | L1369: million_PYG/month | M1369: ANDE | N1369: OFFICIAL_PRIMARY | O1369: OFFICIAL_RELEASE | P1369: 1 | Q1369: 95 | R1369: https://www.ande.gov.py/interna.php?id=15116 | S1369: V5_CURRENT_BASELINES | U1369: 2026-09-11T01:00:00-03:00 | V1369: ANDE says monthly economic harm avoided exceeds this amount.
A1370: V5_0029 | B1370: 2026-06-01 | C1370: 2026-06-30 | D1370: month_or_YTD | E1370: IMAEP_YOY | F1370: PY_ECONOMY | I1370: 5.6 | J1370: percent | K1370: 5.6 | L1370: percent | M1370: BCP | N1370: OFFICIAL_PRIMARY | O1370: OFFICIAL_PRELIMINARY | P1370: 1 | Q1370: 95 | R1370: https://www.bcp.gov.py/documents/20117/2588253/Informe%2BIMAEP-Sectores-Junio_2026.pdf/1b25c6bf-e43c-1c91-9a58-037d4cee0653 | S1370: V5_CURRENT_BASELINES | U1370: 2026-09-11T01:00:00-03:00 | V1370: IMAEP total interannual growth
A1371: V5_0030 | B1371: 2026-01-01 | C1371: 2026-06-30 | D1371: month_or_YTD | E1371: IMAEP_YTD | F1371: PY_ECONOMY | I1371: 5.6 | J1371: percent | K1371: 5.6 | L1371: percent | M1371: BCP | N1371: OFFICIAL_PRIMARY | O1371: OFFICIAL_PRELIMINARY | P1371: 1 | Q1371: 95 | R1371: https://www.bcp.gov.py/documents/20117/2588253/Informe%2BIMAEP-Sectores-Junio_2026.pdf/1b25c6bf-e43c-1c91-9a58-037d4cee0653 | S1371: V5_CURRENT_BASELINES | U1371: 2026-09-11T01:00:00-03:00 | V1371: IMAEP accumulated Jan-Jun 2026
A1372: V5_0031 | B1372: 2026-06-01 | C1372: 2026-06-30 | D1372: month_or_YTD | E1372: IMAEP_PRIMARY_YOY | F1372: PY_ECONOMY | I1372: 9.4 | J1372: percent | K1372: 9.4 | L1372: percent | M1372: BCP | N1372: OFFICIAL_PRIMARY | O1372: OFFICIAL_PRELIMINARY | P1372: 1 | Q1372: 95 | R1372: https://www.bcp.gov.py/documents/20117/2588253/Informe%2BIMAEP-Sectores-Junio_2026.pdf/1b25c6bf-e43c-1c91-9a58-037d4cee0653 | S1372: V5_CURRENT_BASELINES | U1372: 2026-09-11T01:00:00-03:00 | V1372: Primary sector interannual
A1373: V5_0032 | B1373: 2026-01-01 | C1373: 2026-06-30 | D1373: month_or_YTD | E1373: IMAEP_PRIMARY_YTD | F1373: PY_ECONOMY | I1373: 9.8 | J1373: percent | K1373: 9.8 | L1373: percent | M1373: BCP | N1373: OFFICIAL_PRIMARY | O1373: OFFICIAL_PRELIMINARY | P1373: 1 | Q1373: 95 | R1373: https://www.bcp.gov.py/documents/20117/2588253/Informe%2BIMAEP-Sectores-Junio_2026.pdf/1b25c6bf-e43c-1c91-9a58-037d4cee0653 | S1373: V5_CURRENT_BASELINES | U1373: 2026-09-11T01:00:00-03:00 | V1373: Primary sector accumulated
A1374: V5_0033 | B1374: 2026-06-01 | C1374: 2026-06-30 | D1374: month_or_YTD | E1374: IMAEP_SECONDARY_YOY | F1374: PY_ECONOMY | I1374: 5.6 | J1374: percent | K1374: 5.6 | L1374: percent | M1374: BCP | N1374: OFFICIAL_PRIMARY | O1374: OFFICIAL_PRELIMINARY | P1374: 1 | Q1374: 95 | R1374: https://www.bcp.gov.py/documents/20117/2588253/Informe%2BIMAEP-Sectores-Junio_2026.pdf/1b25c6bf-e43c-1c91-9a58-037d4cee0653 | S1374: V5_CURRENT_BASELINES | U1374: 2026-09-11T01:00:00-03:00 | V1374: Secondary sector interannual
A1375: V5_0034 | B1375: 2026-01-01 | C1375: 2026-06-30 | D1375: month_or_YTD | E1375: IMAEP_SECONDARY_YTD | F1375: PY_ECONOMY | I1375: 4.7 | J1375: percent | K1375: 4.7 | L1375: percent | M1375: BCP | N1375: OFFICIAL_PRIMARY | O1375: OFFICIAL_PRELIMINARY | P1375: 1 | Q1375: 95 | R1375: https://www.bcp.gov.py/documents/20117/2588253/Informe%2BIMAEP-Sectores-Junio_2026.pdf/1b25c6bf-e43c-1c91-9a58-037d4cee0653 | S1375: V5_CURRENT_BASELINES | U1375: 2026-09-11T01:00:00-03:00 | V1375: Secondary sector accumulated
A1376: V5_0035 | B1376: 2026-06-01 | C1376: 2026-06-30 | D1376: month_or_YTD | E1376: IMAEP_MANUFACTURING_YOY | F1376: PY_ECONOMY | I1376: 2.8 | J1376: percent | K1376: 2.8 | L1376: percent | M1376: BCP | N1376: OFFICIAL_PRIMARY | O1376: OFFICIAL_PRELIMINARY | P1376: 1 | Q1376: 95 | R1376: https://www.bcp.gov.py/documents/20117/2588253/Informe%2BIMAEP-Sectores-Junio_2026.pdf/1b25c6bf-e43c-1c91-9a58-037d4cee0653 | S1376: V5_CURRENT_BASELINES | U1376: 2026-09-11T01:00:00-03:00 | V1376: Manufacturing interannual
A1377: V5_0036 | B1377: 2026-01-01 | C1377: 2026-06-30 | D1377: month_or_YTD | E1377: IMAEP_MANUFACTURING_YTD | F1377: PY_ECONOMY | I1377: 3.1 | J1377: percent | K1377: 3.1 | L1377: percent | M1377: BCP | N1377: OFFICIAL_PRIMARY | O1377: OFFICIAL_PRELIMINARY | P1377: 1 | Q1377: 95 | R1377: https://www.bcp.gov.py/documents/20117/2588253/Informe%2BIMAEP-Sectores-Junio_2026.pdf/1b25c6bf-e43c-1c91-9a58-037d4cee0653 | S1377: V5_CURRENT_BASELINES | U1377: 2026-09-11T01:00:00-03:00 | V1377: Manufacturing accumulated
A1378: V5_0037 | B1378: 2026-06-01 | C1378: 2026-06-30 | D1378: month_or_YTD | E1378: IMAEP_SERVICES_YOY | F1378: PY_ECONOMY | I1378: 4.9 | J1378: percent | K1378: 4.9 | L1378: percent | M1378: BCP | N1378: OFFICIAL_PRIMARY | O1378: OFFICIAL_PRELIMINARY | P1378: 1 | Q1378: 95 | R1378: https://www.bcp.gov.py/documents/20117/2588253/Informe%2BIMAEP-Sectores-Junio_2026.pdf/1b25c6bf-e43c-1c91-9a58-037d4cee0653 | S1378: V5_CURRENT_BASELINES | U1378: 2026-09-11T01:00:00-03:00 | V1378: Services interannual
... A1407: V5_0066 | B1407: 2025-01-01 | C1407: 2028-12-31 | D1407: plan | E1407: DISTRIBUTION_LOSS_TARGET_2028 | F1407: PY_GRID | I1407: 15 | J1407: percent | K1407: 15 | L1407: percent | M1407: ANDE | N1407: OFFICIAL_PRIMARY | O1407: OFFICIAL_PLAN | P1407: 1 | Q1407: 95 | R1407: https://www.ande.gov.py/interna.php?id=15116 | S1407: V5_CURRENT_BASELINES | U1407: 2026-09-11T01:00:00-03:00 | V1407: ANDE target for total distribution losses by end-2028.

Sheet Prices
A1: price_id | B1: period_start | C1: period_end | D1: grain | E1: price_code | F1: asset_code | G1: market_counterparty | H1: value | I1: unit | J1: currency | K1: source_code | L1: authority_class | M1: quality_class | N1: source_url | O1: revision_priority | P1: notes
A2: P00001 | B2: 1990-01-01 | C2: 1990-12-31 | D2: year | E2: ANDE_TARIFF_RESIDENTIAL | F2: PY_SIN | G2: PY | H2: 56.1 | I2: Gs/kWh | J2: PYG | K2: ANDE | L2: OFFICIAL_PRIMARY | M2: OFFICIAL_AGGREGATE | N2: https://www.ande.gov.py/documentos_contables/157/compilacion_estadistica_1990-2010.pdf | O2: 75 | P2: Tarifa media anual sin impuestos segun compilacion.
A3: P00002 | B3: 1991-01-01 | C3: 1991-12-31 | D3: year | E3: ANDE_TARIFF_RESIDENTIAL | F3: PY_SIN | G3: PY | H3: 66.2 | I3: Gs/kWh | J3: PYG | K3: ANDE | L3: OFFICIAL_PRIMARY | M3: OFFICIAL_AGGREGATE | N3: https://www.ande.gov.py/documentos_contables/157/compilacion_estadistica_1990-2010.pdf | O3: 75 | P3: Tarifa media anual sin impuestos segun compilacion.
A4: P00003 | B4: 1992-01-01 | C4: 1992-12-31 | D4: year | E4: ANDE_TARIFF_RESIDENTIAL | F4: PY_SIN | G4: PY | H4: 66.3 | I4: Gs/kWh | J4: PYG | K4: ANDE | L4: OFFICIAL_PRIMARY | M4: OFFICIAL_AGGREGATE | N4: https://www.ande.gov.py/documentos_contables/157/compilacion_estadistica_1990-2010.pdf | O4: 75 | P4: Tarifa media anual sin impuestos segun compilacion.
A5: P00004 | B5: 1993-01-01 | C5: 1993-12-31 | D5: year | E5: ANDE_TARIFF_RESIDENTIAL | F5: PY_SIN | G5: PY | H5: 70.6 | I5: Gs/kWh | J5: PYG | K5: ANDE | L5: OFFICIAL_PRIMARY | M5: OFFICIAL_AGGREGATE | N5: https://www.ande.gov.py/documentos_contables/157/compilacion_estadistica_1990-2010.pdf | O5: 75 | P5: Tarifa media anual sin impuestos segun compilacion.
A6: P00005 | B6: 1994-01-01 | C6: 1994-12-31 | D6: year | E6: ANDE_TARIFF_RESIDENTIAL | F6: PY_SIN | G6: PY | H6: 85.5 | I6: Gs/kWh | J6: PYG | K6: ANDE | L6: OFFICIAL_PRIMARY | M6: OFFICIAL_AGGREGATE | N6: https://www.ande.gov.py/documentos_contables/157/compilacion_estadistica_1990-2010.pdf | O6: 75 | P6: Tarifa media anual sin impuestos segun compilacion.
A7: P00006 | B7: 1995-01-01 | C7: 1995-12-31 | D7: year | E7: ANDE_TARIFF_RESIDENTIAL | F7: PY_SIN | G7: PY | H7: 95.5 | I7: Gs/kWh | J7: PYG | K7: ANDE | L7: OFFICIAL_PRIMARY | M7: OFFICIAL_AGGREGATE | N7: https://www.ande.gov.py/documentos_contables/157/compilacion_estadistica_1990-2010.pdf | O7: 75 | P7: Tarifa media anual sin impuestos segun compilacion.
A8: P00007 | B8: 1996-01-01 | C8: 1996-12-31 | D8: year | E8: ANDE_TARIFF_RESIDENTIAL | F8: PY_SIN | G8: PY | H8: 118 | I8: Gs/kWh | J8: PYG | K8: ANDE | L8: OFFICIAL_PRIMARY | M8: OFFICIAL_AGGREGATE | N8: https://www.ande.gov.py/documentos_contables/157/compilacion_estadistica_1990-2010.pdf | O8: 75 | P8: Tarifa media anual sin impuestos segun compilacion.
A9: P00008 | B9: 1997-01-01 | C9: 1997-12-31 | D9: year | E9: ANDE_TARIFF_RESIDENTIAL | F9: PY_SIN | G9: PY | H9: 135.1 | I9: Gs/kWh | J9: PYG | K9: ANDE | L9: OFFICIAL_PRIMARY | M9: OFFICIAL_AGGREGATE | N9: https://www.ande.gov.py/documentos_contables/157/compilacion_estadistica_1990-2010.pdf | O9: 75 | P9: Tarifa media anual sin impuestos segun compilacion.
A10: P00009 | B10: 1998-01-01 | C10: 1998-12-31 | D10: year | E10: ANDE_TARIFF_RESIDENTIAL | F10: PY_SIN | G10: PY | H10: 159.9 | I10: Gs/kWh | J10: PYG | K10: ANDE | L10: OFFICIAL_PRIMARY | M10: OFFICIAL_AGGREGATE | N10: https://www.ande.gov.py/documentos_contables/157/compilacion_estadistica_1990-2010.pdf | O10: 75 | P10: Tarifa media anual sin impuestos segun compilacion.
A11: P00010 | B11: 1999-01-01 | C11: 1999-12-31 | D11: year | E11: ANDE_TARIFF_RESIDENTIAL | F11: PY_SIN | G11: PY | H11: 161.7 | I11: Gs/kWh | J11: PYG | K11: ANDE | L11: OFFICIAL_PRIMARY | M11: OFFICIAL_AGGREGATE | N11: https://www.ande.gov.py/documentos_contables/157/compilacion_estadistica_1990-2010.pdf | O11: 75 | P11: Tarifa media anual sin impuestos segun compilacion.
A12: P00011 | B12: 2000-01-01 | C12: 2000-12-31 | D12: year | E12: ANDE_TARIFF_RESIDENTIAL | F12: PY_SIN | G12: PY | H12: 171.4 | I12: Gs/kWh | J12: PYG | K12: ANDE | L12: OFFICIAL_PRIMARY | M12: OFFICIAL_AGGREGATE | N12: https://www.ande.gov.py/documentos_contables/157/compilacion_estadistica_1990-2010.pdf | O12: 75 | P12: Tarifa media anual sin impuestos segun compilacion.
A13: P00012 | B13: 2001-01-01 | C13: 2001-12-31 | D13: year | E13: ANDE_TARIFF_RESIDENTIAL | F13: PY_SIN | G13: PY | H13: 232 | I13: Gs/kWh | J13: PYG | K13: ANDE | L13: OFFICIAL_PRIMARY | M13: OFFICIAL_AGGREGATE | N13: https://www.ande.gov.py/documentos_contables/157/compilacion_estadistica_1990-2010.pdf | O13: 75 | P13: Tarifa media anual sin impuestos segun compilacion.
... A369: P00368 | B369: 2024-01-01 | C369: 2024-12-31 | D369: year | E369: ANDE_TARIFF_GENERAL_AVG | F369: PY_SIN | G369: PY | H369: 374.6 | I369: Gs/kWh | J369: PYG | K369: ANDE | L369: OFFICIAL_PRIMARY | M369: OFFICIAL_AGGREGATE | N369: https://www.ande.gov.py/finanzas/ANDE%20-%20Resumen%20Estad%C3%ADstico%202020%20-%202024.pdf | O369: 95 | P369: Tarifa media anual segun Resumen Estadistico 2020-2024. Fuente mas reciente para este periodo; preservar revisiones previas para auditoria.

Sheet Retail_Tariff_History
A1: Año | B1: Residencial media (Gs/kWh) | C1: Nacional media (Gs/kWh) | D1: Exportación ANDE media (Gs/kWh) | E1: Var. residencial YoY | F1: Residencial / Exportación | G1: Calidad | H1: Fuente principal
A2: 1990 | B2: 56.1 | C2: 52.2 | D2: 44.5 | F2: =IFERROR(B2/D2,"") | G2: OFICIAL | H2: https://www.ande.gov.py/documentos_contables/157/compilacion_estadistica_1990-2010.pdf
A3: 1991 | B3: 66.2 | C3: 62.2 | D3: 44.6 | E3: =IFERROR(B3/B2-1,"") | F3: =IFERROR(B3/D3,"") | G3: OFICIAL | H3: https://www.ande.gov.py/documentos_contables/157/compilacion_estadistica_1990-2010.pdf
A4: 1992 | B4: 66.3 | C4: 61.7 | D4: 50.2 | E4: =IFERROR(B4/B3-1,"") | F4: =IFERROR(B4/D4,"") | G4: OFICIAL | H4: https://www.ande.gov.py/documentos_contables/157/compilacion_estadistica_1990-2010.pdf
A5: 1993 | B5: 70.6 | C5: 66.4 | D5: 65.9 | E5: =IFERROR(B5/B4-1,"") | F5: =IFERROR(B5/D5,"") | G5: OFICIAL | H5: https://www.ande.gov.py/documentos_contables/157/compilacion_estadistica_1990-2010.pdf
A6: 1994 | B6: 85.5 | C6: 80.3 | D6: 66.2 | E6: =IFERROR(B6/B5-1,"") | F6: =IFERROR(B6/D6,"") | G6: OFICIAL | H6: https://www.ande.gov.py/documentos_contables/157/compilacion_estadistica_1990-2010.pdf
A7: 1995 | B7: 95.5 | C7: 89.2 | D7: 78.7 | E7: =IFERROR(B7/B6-1,"") | F7: =IFERROR(B7/D7,"") | G7: OFICIAL | H7: https://www.ande.gov.py/documentos_contables/157/compilacion_estadistica_1990-2010.pdf
A8: 1996 | B8: 118 | C8: 110 | D8: 75.4 | E8: =IFERROR(B8/B7-1,"") | F8: =IFERROR(B8/D8,"") | G8: OFICIAL | H8: https://www.ande.gov.py/documentos_contables/157/compilacion_estadistica_1990-2010.pdf
A9: 1997 | B9: 135.1 | C9: 124.6 | D9: 55 | E9: =IFERROR(B9/B8-1,"") | F9: =IFERROR(B9/D9,"") | G9: OFICIAL | H9: https://www.ande.gov.py/documentos_contables/157/compilacion_estadistica_1990-2010.pdf
A10: 1998 | B10: 159.9 | C10: 148.6 | D10: 48.7 | E10: =IFERROR(B10/B9-1,"") | F10: =IFERROR(B10/D10,"") | G10: OFICIAL | H10: https://www.ande.gov.py/documentos_contables/157/compilacion_estadistica_1990-2010.pdf
A11: 1999 | B11: 161.7 | C11: 146.8 | D11: 40.2 | E11: =IFERROR(B11/B10-1,"") | F11: =IFERROR(B11/D11,"") | G11: OFICIAL | H11: https://www.ande.gov.py/documentos_contables/157/compilacion_estadistica_1990-2010.pdf
A12: 2000 | B12: 171.4 | C12: 159.1 | D12: 53.7 | E12: =IFERROR(B12/B11-1,"") | F12: =IFERROR(B12/D12,"") | G12: OFICIAL | H12: https://www.ande.gov.py/documentos_contables/157/compilacion_estadistica_1990-2010.pdf
A13: 2001 | B13: 232 | C13: 211.2 | D13: 60.9 | E13: =IFERROR(B13/B12-1,"") | F13: =IFERROR(B13/D13,"") | G13: OFICIAL | H13: https://www.ande.gov.py/documentos_contables/157/compilacion_estadistica_1990-2010.pdf
A14: 2002 | B14: 299.7 | C14: 275.4 | D14: 51.3 | E14: =IFERROR(B14/B13-1,"") | F14: =IFERROR(B14/D14,"") | G14: OFICIAL | H14: https://www.ande.gov.py/documentos_contables/157/compilacion_estadistica_1990-2010.pdf
... A36: 2024 | B36: 415.5 | C36: 371.9 | D36: 899.3 | E36: =IFERROR(B36/B35-1,"") | F36: =IFERROR(B36/D36,"") | G36: OFICIAL | H36: https://www.ande.gov.py/finanzas/ANDE%20-%20Resumen%20Estad%C3%ADstico%202020%20-%202024.pdf

Sheet Retail_Tariff_Current
A1: ANDE — Tarifas residenciales vigentes de referencia
A2: Vigencia de referencia | B2: 27-11-2024 → vigente en portal ANDE consultado 2026
A4: Categoría | B4: Nombre | C4: Desde kWh/mes | D4: Hasta kWh/mes | E4: Precio nominal | F4: Unidad | G4: Tipo | H4: Fuente
A5: 142 | B5: Residencial normal BT | C5: 0 | D5: 50 | E5: 311.55 | F5: Gs/kWh | G5: Tarifa residencial normal | H5: https://www.ande.gov.py/docs/tarifas/Pliego%20de%20Tarifas%20NRO%2021%20Version%20Actualizada%2027-11-2024.pdf
A6: 142 | B6: Residencial normal BT | C6: 51 | D6: 150 | E6: 349.89 | F6: Gs/kWh | G6: Tarifa residencial normal | H6: https://www.ande.gov.py/docs/tarifas/Pliego%20de%20Tarifas%20NRO%2021%20Version%20Actualizada%2027-11-2024.pdf
A7: 142 | B7: Residencial normal BT | C7: 151 | D7: 300 | E7: 365.45 | F7: Gs/kWh | G7: Tarifa residencial normal | H7: https://www.ande.gov.py/docs/tarifas/Pliego%20de%20Tarifas%20NRO%2021%20Version%20Actualizada%2027-11-2024.pdf
A8: 142 | B8: Residencial normal BT | C8: 301 | D8: 500 | E8: 403.82 | F8: Gs/kWh | G8: Tarifa residencial normal | H8: https://www.ande.gov.py/docs/tarifas/Pliego%20de%20Tarifas%20NRO%2021%20Version%20Actualizada%2027-11-2024.pdf
A9: 142 | B9: Residencial normal BT | C9: 501 | D9: 1000 | E9: 420.27 | F9: Gs/kWh | G9: Tarifa residencial normal | H9: https://www.ande.gov.py/docs/tarifas/Pliego%20de%20Tarifas%20NRO%2021%20Version%20Actualizada%2027-11-2024.pdf
A10: 142 | B10: Residencial normal BT | C10: 1001 | E10: 435.51 | F10: Gs/kWh | G10: Tarifa residencial normal | H10: https://www.ande.gov.py/docs/tarifas/Pliego%20de%20Tarifas%20NRO%2021%20Version%20Actualizada%2027-11-2024.pdf
A12: Tarifa social — descuentos sobre tarifa residencial normal
A13: Categoría | B13: Nombre | C13: Desde kWh/mes | D13: Hasta kWh/mes | E13: Descuento | F13: Fracción pagada | G13: Nota | H13: Fuente
A14: 141 | B14: Tarifa social BT | C14: 0 | D14: 100 | E14: 0.75 | F14: =1-E14 | G14: La tarifa social aplica el descuento legal sobre la tarifa residencial normal correspondiente. | H14: Ley 3480/2008 / Pliego 21
A15: 141 | B15: Tarifa social BT | C15: 101 | D15: 200 | E15: 0.5 | F15: =1-E15 | G15: La tarifa social aplica el descuento legal sobre la tarifa residencial normal correspondiente. | H15: Ley 3480/2008 / Pliego 21
A16: 141 | B16: Tarifa social BT | C16: 201 | D16: 300 | E16: 0.25 | F16: =1-E16 | G16: La tarifa social aplica el descuento legal sobre la tarifa residencial normal correspondiente. | H16: Ley 3480/2008 / Pliego 21

Sheet Retail_Tariff_Summary
A1: EnergiaPY.live — Precio de la electricidad al usuario paraguayo
A2: Indicador | B2: Valor | C2: Unidad | D2: Tipo | E2: Interpretación | F2: Fuente / supuesto
A3: Tarifa media residencial 2024 | B3: ='Retail_Tariff_History'!B36 | C3: Gs/kWh | D3: OFICIAL | E3: Precio medio efectivo anual del segmento residencial. | F3: ANDE Resumen Estadístico 2020-2024
A4: Promedio residencial 1990-2024 | B4: =AVERAGE('Retail_Tariff_History'!B2:B36) | C4: Gs/kWh | D4: DERIVADO | E4: Promedio aritmético nominal; no ajustado por inflación. | F4: Serie oficial ANDE
A5: Promedio residencial 2003-2024 | B5: =AVERAGE('Retail_Tariff_History'!B15:B36) | C5: Gs/kWh | D5: DERIVADO | E5: Promedio nominal del periodo moderno. | F5: Serie oficial ANDE
A6: Promedio residencial 2020-2024 | B6: =AVERAGE('Retail_Tariff_History'!B32:B36) | C6: Gs/kWh | D6: DERIVADO | E6: Referencia reciente de 5 años. | F6: Serie oficial ANDE
A7: Tarifa residencial vigente mínima | B7: ='Retail_Tariff_Current'!E5 | C7: Gs/kWh | D7: OFICIAL CONTRACTUAL | E7: Faja 0-50 kWh/mes. | F7: Pliego 21
A8: Tarifa residencial vigente máxima | B8: ='Retail_Tariff_Current'!E10 | C8: Gs/kWh | D8: OFICIAL CONTRACTUAL | E8: Faja mayor a 1.000 kWh/mes. | F8: Pliego 21
A9: Tarifa media nacional 2024 | B9: ='Retail_Tariff_History'!C36 | C9: Gs/kWh | D9: OFICIAL | E9: Promedio de ventas dentro del mercado nacional. | F9: ANDE Resumen Estadístico 2020-2024
A10: Tarifa media exportación ANDE 2024 | B10: ='Retail_Tariff_History'!D36 | C10: Gs/kWh | D10: OFICIAL | E10: Promedio de exportación ANDE; no equivale a cesión binacional. | F10: ANDE Resumen Estadístico 2020-2024
A11: Relación residencial / exportación 2024 | B11: =B3/B10 | C11: % | D11: DERIVADO | E11: Compara tarifa residencial media con tarifa media de exportación ANDE del mismo año. | F11: EnergiaPY sobre ANDE
A12: Proxy tarifa media nacional 2025 | B12: =B9*(1+$F$14)/(1+$F$15) | C12: Gs/kWh | D12: DERIVADO PROVISIONAL | E12: Estimación usando crecimiento del importe facturado y de la energía facturada 2025. No sustituye una tarifa media oficial 2025. | F12: BAGP 2025
E13: Supuestos proxy 2025
E14: Crecimiento importe facturado 2025 | F14: 0.1334
E15: Crecimiento energía facturada 2025 | F15: 0.1595
A17: Normalización macro V4
A18: Tarifa residencial media 2024 en USD/MWh | B18: ='Retail_Tariff_History'!B36*1000/'Macro_Annual'!D37 | C18: USD/MWh | D18: CALCULADO | E18: Usa FX promedio anual 2024. | F18: https://data.worldbank.org/indicator/PA.NUS.FCRF?locations=PY
A19: Tarifa residencial media 2024 en Gs de 2025 | B19: ='Retail_Tariff_History'!B36*'Macro_Annual'!B38/'Macro_Annual'!B37 | C19: Gs 2025/kWh | D19: CALCULADO | E19: Deflactada/reexpresada con IPC anual. | F19: https://data.worldbank.org/indicator/PA.NUS.FCRF?locations=PY
A20: Tarifa residencial vigente mínima a FX 10-09-2026 | B20: ='Retail_Tariff_Current'!E5*1000/5933.25 | C20: USD/MWh | D20: CALCULADO SNAPSHOT | E20: Conversión con BCP 10-09-2026; no es promedio anual. | F20: https://www.bcp.gov.py/webapps/web/cotizacion/monedas
A21: Tarifa residencial vigente máxima a FX 10-09-2026 | B21: ='Retail_Tariff_Current'!E10*1000/5933.25 | C21: USD/MWh | D21: CALCULADO SNAPSHOT | E21: Conversión con BCP 10-09-2026; no es promedio anual. | F21: https://www.bcp.gov.py/webapps/web/cotizacion/monedas

Sheet Macro_Annual
A1: EnergiaPY.live — Macro anual para normalización económica
A2: Año | B2: IPC (2010=100) | C2: Inflación anual | D2: USD/PYG promedio | E2: Fuente IPC | F2: Fuente FX | G2: Autoridad | H2: Calidad | I2: Pendiente reconciliar BCP | J2: URL IPC | K2: URL FX | L2: Notas
A3: 1990 | B3: 13.412 | C3: 0.37259956 | D3: 1229.8083 | E3: WDI/IMF | F3: WDI/IMF | G3: OFICIAL INTERNACIONAL | H3: BACKFILL PROVISIONAL | I3: SÍ | J3: https://data.worldbank.org/indicator/FP.CPI.TOTL?locations=PY | K3: https://data.worldbank.org/indicator/PA.NUS.FCRF?locations=PY | L3: BCP es la fuente primaria objetivo; reconciliar contra archivo bruto BCP en producción.
A4: 1991 | B4: 16.6663 | C4: 0.24225352 | D4: 1325.1833 | E4: WDI/IMF | F4: WDI/IMF | G4: OFICIAL INTERNACIONAL | H4: BACKFILL PROVISIONAL | I4: SÍ | J4: https://data.worldbank.org/indicator/FP.CPI.TOTL?locations=PY | K4: https://data.worldbank.org/indicator/PA.NUS.FCRF?locations=PY | L4: BCP es la fuente primaria objetivo; reconciliar contra archivo bruto BCP en producción.
A5: 1992 | B5: 19.1868 | C5: 0.15192744 | D5: 1500.2583 | E5: WDI/IMF | F5: WDI/IMF | G5: OFICIAL INTERNACIONAL | H5: BACKFILL PROVISIONAL | I5: SÍ | J5: https://data.worldbank.org/indicator/FP.CPI.TOTL?locations=PY | K5: https://data.worldbank.org/indicator/PA.NUS.FCRF?locations=PY | L5: BCP es la fuente primaria objetivo; reconciliar contra archivo bruto BCP en producción.
A6: 1993 | B6: 22.6898 | C6: 0.18208661 | D6: 1744.3458 | E6: WDI/IMF | F6: WDI/IMF | G6: OFICIAL INTERNACIONAL | H6: BACKFILL PROVISIONAL | I6: SÍ | J6: https://data.worldbank.org/indicator/FP.CPI.TOTL?locations=PY | K6: https://data.worldbank.org/indicator/PA.NUS.FCRF?locations=PY | L6: BCP es la fuente primaria objetivo; reconciliar contra archivo bruto BCP en producción.
A7: 1994 | B7: 27.3657 | C7: 0.20566195 | D7: 1904.7608 | E7: WDI/IMF | F7: WDI/IMF | G7: OFICIAL INTERNACIONAL | H7: BACKFILL PROVISIONAL | I7: SÍ | J7: https://data.worldbank.org/indicator/FP.CPI.TOTL?locations=PY | K7: https://data.worldbank.org/indicator/PA.NUS.FCRF?locations=PY | L7: BCP es la fuente primaria objetivo; reconciliar contra archivo bruto BCP en producción.
A8: 1995 | B8: 31.0292 | C8: 0.13425414 | D8: 1963.0192 | E8: WDI/IMF | F8: WDI/IMF | G8: OFICIAL INTERNACIONAL | H8: BACKFILL PROVISIONAL | I8: SÍ | J8: https://data.worldbank.org/indicator/FP.CPI.TOTL?locations=PY | K8: https://data.worldbank.org/indicator/PA.NUS.FCRF?locations=PY | L8: BCP es la fuente primaria objetivo; reconciliar contra archivo bruto BCP en producción.
A9: 1996 | B9: 34.0693 | C9: 0.097996834 | D9: 2056.8117 | E9: WDI/IMF | F9: WDI/IMF | G9: OFICIAL INTERNACIONAL | H9: BACKFILL PROVISIONAL | I9: SÍ | J9: https://data.worldbank.org/indicator/FP.CPI.TOTL?locations=PY | K9: https://data.worldbank.org/indicator/PA.NUS.FCRF?locations=PY | L9: BCP es la fuente primaria objetivo; reconciliar contra archivo bruto BCP en producción.
A10: 1997 | B10: 36.4372 | C10: 0.069495661 | D10: 2177.8625 | E10: WDI/IMF | F10: WDI/IMF | G10: OFICIAL INTERNACIONAL | H10: BACKFILL PROVISIONAL | I10: SÍ | J10: https://data.worldbank.org/indicator/FP.CPI.TOTL?locations=PY | K10: https://data.worldbank.org/indicator/PA.NUS.FCRF?locations=PY | L10: BCP es la fuente primaria objetivo; reconciliar contra archivo bruto BCP en producción.
A11: 1998 | B11: 40.647 | C11: 0.11553268 | D11: 2726.49 | E11: WDI/IMF | F11: WDI/IMF | G11: OFICIAL INTERNACIONAL | H11: BACKFILL PROVISIONAL | I11: SÍ | J11: https://data.worldbank.org/indicator/FP.CPI.TOTL?locations=PY | K11: https://data.worldbank.org/indicator/PA.NUS.FCRF?locations=PY | L11: BCP es la fuente primaria objetivo; reconciliar contra archivo bruto BCP en producción.
A12: 1999 | B12: 43.3912 | C12: 0.067522659 | D12: 3119.0733 | E12: WDI/IMF | F12: WDI/IMF | G12: OFICIAL INTERNACIONAL | H12: BACKFILL PROVISIONAL | I12: SÍ | J12: https://data.worldbank.org/indicator/FP.CPI.TOTL?locations=PY | K12: https://data.worldbank.org/indicator/PA.NUS.FCRF?locations=PY | L12: BCP es la fuente primaria objetivo; reconciliar contra archivo bruto BCP en producción.
A13: 2000 | B13: 47.2893 | C13: 0.089821598 | D13: 3486.3533 | E13: WDI/IMF | F13: WDI/IMF | G13: OFICIAL INTERNACIONAL | H13: BACKFILL PROVISIONAL | I13: SÍ | J13: https://data.worldbank.org/indicator/FP.CPI.TOTL?locations=PY | K13: https://data.worldbank.org/indicator/PA.NUS.FCRF?locations=PY | L13: BCP es la fuente primaria objetivo; reconciliar contra archivo bruto BCP en producción.
A14: 2001 | B14: 50.7261 | C14: 0.072680603 | D14: 4105.925 | E14: WDI/IMF | F14: WDI/IMF | G14: OFICIAL INTERNACIONAL | H14: BACKFILL PROVISIONAL | I14: SÍ | J14: https://data.worldbank.org/indicator/FP.CPI.TOTL?locations=PY | K14: https://data.worldbank.org/indicator/PA.NUS.FCRF?locations=PY | L14: BCP es la fuente primaria objetivo; reconciliar contra archivo bruto BCP en producción.
... A38: 2025 | B38: 190.28869 | C38: 0.040380642 | D38: 7545.45 | E38: WDI/IMF | F38: WDI/IMF | G38: OFICIAL INTERNACIONAL | H38: BACKFILL PROVISIONAL | I38: SÍ | J38: https://data.worldbank.org/indicator/FP.CPI.TOTL?locations=PY | K38: https://data.worldbank.org/indicator/PA.NUS.FCRF?locations=PY | L38: BCP es la fuente primaria objetivo; reconciliar contra archivo bruto BCP en producción.

Sheet Macro_Current
A1: EnergiaPY.live — Macro BCP actual / expectativas 2026
A2: ID | B2: Fecha | C2: Serie | D2: Valor | E2: Unidad | F2: Fuente | G2: Calidad | H2: URL | I2: Notas
A3: M2026-001 | B3: 2026-08-31 | C3: CPI_MONTHLY_INFLATION | D3: 0 | E3: percent | F3: BCP | G3: OFFICIAL_MEASURED | H3: https://www.bcp.gov.py/web/institucional/w/informe-de-inflaci%C3%B3n-agosto-2026 | I3: Inflacion mensual IPC agosto 2026.
A4: M2026-002 | B4: 2026-08-31 | C4: CPI_YTD_INFLATION | D4: 1.8 | E4: percent | F4: BCP | G4: OFFICIAL_MEASURED | H4: https://www.bcp.gov.py/web/institucional/w/informe-de-inflaci%C3%B3n-agosto-2026 | I4: Inflacion acumulada enero-agosto 2026.
A5: M2026-003 | B5: 2026-08-31 | C5: CPI_YOY_INFLATION | D5: 1.5 | E5: percent | F5: BCP | G5: OFFICIAL_MEASURED | H5: https://www.bcp.gov.py/web/institucional/w/informe-de-inflaci%C3%B3n-agosto-2026 | I5: Inflacion interanual agosto 2026.
A6: M2026-004 | B6: 2026-09-10 | C6: FX_USD_PYG_REFERENCE | D6: 5933.25 | E6: PYG/USD | F6: BCP | G6: OFFICIAL_MEASURED | H6: https://www.bcp.gov.py/webapps/web/cotizacion/monedas | I6: Cotizacion referencial USD/PYG del 10-09-2026.
A7: M2026-005 | B7: 2026-09-10 | C7: FX_BRL_PYG_REFERENCE | D7: 1165.78 | E7: PYG/BRL | F7: BCP | G7: OFFICIAL_MEASURED | H7: https://www.bcp.gov.py/webapps/web/cotizacion/monedas | I7: Cotizacion referencial BRL/PYG del 10-09-2026.
A8: M2026-006 | B8: 2026-09-10 | C8: FX_ARS_PYG_REFERENCE | D8: 3.92 | E8: PYG/ARS | F8: BCP | G8: OFFICIAL_MEASURED | H8: https://www.bcp.gov.py/webapps/web/cotizacion/monedas | I8: Cotizacion referencial ARS/PYG del 10-09-2026.
A9: M2026-007 | B9: 2026-08-07 | C9: EVE_INFLATION_2026 | D9: 3.3 | E9: percent | F9: BCP | G9: OFFICIAL_SURVEY_EXPECTATION | H9: https://www.bcp.gov.py/es/web/institucional/w/encuesta-de-expectativas-de-variables-econ%C3%B3micas-agosto-2026/-/categories/158845 | I9: Mediana EVE agosto 2026 para cierre 2026.
A10: M2026-008 | B10: 2026-08-07 | C10: EVE_INFLATION_2027 | D10: 3.5 | E10: percent | F10: BCP | G10: OFFICIAL_SURVEY_EXPECTATION | H10: https://www.bcp.gov.py/es/web/institucional/w/encuesta-de-expectativas-de-variables-econ%C3%B3micas-agosto-2026/-/categories/158845 | I10: Mediana EVE agosto 2026 para cierre 2027.
A11: M2026-009 | B11: 2026-08-07 | C11: EVE_FX_SEP_2026 | D11: 6015 | E11: PYG/USD | F11: BCP | G11: OFFICIAL_SURVEY_EXPECTATION | H11: https://www.bcp.gov.py/es/web/institucional/w/encuesta-de-expectativas-de-variables-econ%C3%B3micas-agosto-2026/-/categories/158845 | I11: Mediana EVE para septiembre 2026.
A12: M2026-010 | B12: 2026-08-07 | C12: EVE_FX_EOY_2026 | D12: 6150 | E12: PYG/USD | F12: BCP | G12: OFFICIAL_SURVEY_EXPECTATION | H12: https://www.bcp.gov.py/es/web/institucional/w/encuesta-de-expectativas-de-variables-econ%C3%B3micas-agosto-2026/-/categories/158845 | I12: Mediana EVE para cierre 2026.
A13: M2026-011 | B13: 2026-08-07 | C13: EVE_FX_EOY_2027 | D13: 6400 | E13: PYG/USD | F13: BCP | G13: OFFICIAL_SURVEY_EXPECTATION | H13: https://www.bcp.gov.py/es/web/institucional/w/encuesta-de-expectativas-de-variables-econ%C3%B3micas-agosto-2026/-/categories/158845 | I13: Mediana EVE para cierre 2027.
A14: M2026-012 | B14: 2026-08-07 | C14: EVE_GDP_GROWTH_2026 | D14: 4.3 | E14: percent | F14: BCP | G14: OFFICIAL_SURVEY_EXPECTATION | H14: https://www.bcp.gov.py/es/web/institucional/w/encuesta-de-expectativas-de-variables-econ%C3%B3micas-agosto-2026/-/categories/158845 | I14: Mediana EVE crecimiento PIB 2026.
... A16: M2026-014 | B16: 2026-08-07 | C16: EVE_TPM_EOY_2026 | D16: 5.5 | E16: percent | F16: BCP | G16: OFFICIAL_SURVEY_EXPECTATION | H16: https://www.bcp.gov.py/es/web/institucional/w/encuesta-de-expectativas-de-variables-econ%C3%B3micas-agosto-2026/-/categories/158845 | I16: Mediana EVE TPM cierre 2026.

Sheet Tariff_Normalized
A1: EnergiaPY.live — Tarifas ANDE comparables en términos reales y USD
A2: Año | B2: Código tarifa | C2: Tarifa nominal (Gs/kWh) | D2: IPC del año | E2: USD/PYG promedio | F2: Tarifa real (Gs 2025/kWh) | G2: Equivalente (USD/MWh) | H2: Calidad tarifa | I2: Calidad macro | J2: Fuente tarifa | K2: Fuente IPC | L2: Fuente FX
A3: 1990 | B3: ANDE_TARIFF_COMMERCIAL | C3: 72.9 | D3: ='Macro_Annual'!B3 | E3: ='Macro_Annual'!D3 | F3: =IFERROR(C3*'Macro_Annual'!$B$38/D3,"") | G3: =IFERROR(C3*1000/E3,"") | H3: OFFICIAL_AGGREGATE | I3: BACKFILL PROVISIONAL | J3: https://www.ande.gov.py/documentos_contables/157/compilacion_estadistica_1990-2010.pdf | K3: https://data.worldbank.org/indicator/FP.CPI.TOTL?locations=PY | L3: https://data.worldbank.org/indicator/PA.NUS.FCRF?locations=PY
A4: 1990 | B4: ANDE_TARIFF_EXPORT_AVG | C4: 44.5 | D4: ='Macro_Annual'!B3 | E4: ='Macro_Annual'!D3 | F4: =IFERROR(C4*'Macro_Annual'!$B$38/D4,"") | G4: =IFERROR(C4*1000/E4,"") | H4: OFFICIAL_AGGREGATE | I4: BACKFILL PROVISIONAL | J4: https://www.ande.gov.py/documentos_contables/157/compilacion_estadistica_1990-2010.pdf | K4: https://data.worldbank.org/indicator/FP.CPI.TOTL?locations=PY | L4: https://data.worldbank.org/indicator/PA.NUS.FCRF?locations=PY
A5: 1990 | B5: ANDE_TARIFF_GENERAL | C5: 48.9 | D5: ='Macro_Annual'!B3 | E5: ='Macro_Annual'!D3 | F5: =IFERROR(C5*'Macro_Annual'!$B$38/D5,"") | G5: =IFERROR(C5*1000/E5,"") | H5: OFFICIAL_AGGREGATE | I5: BACKFILL PROVISIONAL | J5: https://www.ande.gov.py/documentos_contables/157/compilacion_estadistica_1990-2010.pdf | K5: https://data.worldbank.org/indicator/FP.CPI.TOTL?locations=PY | L5: https://data.worldbank.org/indicator/PA.NUS.FCRF?locations=PY
A6: 1990 | B6: ANDE_TARIFF_GENERAL_AVG | C6: 51.7 | D6: ='Macro_Annual'!B3 | E6: ='Macro_Annual'!D3 | F6: =IFERROR(C6*'Macro_Annual'!$B$38/D6,"") | G6: =IFERROR(C6*1000/E6,"") | H6: OFFICIAL_AGGREGATE | I6: BACKFILL PROVISIONAL | J6: https://www.ande.gov.py/documentos_contables/157/compilacion_estadistica_1990-2010.pdf | K6: https://data.worldbank.org/indicator/FP.CPI.TOTL?locations=PY | L6: https://data.worldbank.org/indicator/PA.NUS.FCRF?locations=PY
A7: 1990 | B7: ANDE_TARIFF_GOV | C7: 28.1 | D7: ='Macro_Annual'!B3 | E7: ='Macro_Annual'!D3 | F7: =IFERROR(C7*'Macro_Annual'!$B$38/D7,"") | G7: =IFERROR(C7*1000/E7,"") | H7: OFFICIAL_AGGREGATE | I7: BACKFILL PROVISIONAL | J7: https://www.ande.gov.py/documentos_contables/157/compilacion_estadistica_1990-2010.pdf | K7: https://data.worldbank.org/indicator/FP.CPI.TOTL?locations=PY | L7: https://data.worldbank.org/indicator/PA.NUS.FCRF?locations=PY
A8: 1990 | B8: ANDE_TARIFF_INDUSTRIAL | C8: 40.1 | D8: ='Macro_Annual'!B3 | E8: ='Macro_Annual'!D3 | F8: =IFERROR(C8*'Macro_Annual'!$B$38/D8,"") | G8: =IFERROR(C8*1000/E8,"") | H8: OFFICIAL_AGGREGATE | I8: BACKFILL PROVISIONAL | J8: https://www.ande.gov.py/documentos_contables/157/compilacion_estadistica_1990-2010.pdf | K8: https://data.worldbank.org/indicator/FP.CPI.TOTL?locations=PY | L8: https://data.worldbank.org/indicator/PA.NUS.FCRF?locations=PY
A9: 1990 | B9: ANDE_TARIFF_NATIONAL_AVG | C9: 52.2 | D9: ='Macro_Annual'!B3 | E9: ='Macro_Annual'!D3 | F9: =IFERROR(C9*'Macro_Annual'!$B$38/D9,"") | G9: =IFERROR(C9*1000/E9,"") | H9: OFFICIAL_AGGREGATE | I9: BACKFILL PROVISIONAL | J9: https://www.ande.gov.py/documentos_contables/157/compilacion_estadistica_1990-2010.pdf | K9: https://data.worldbank.org/indicator/FP.CPI.TOTL?locations=PY | L9: https://data.worldbank.org/indicator/PA.NUS.FCRF?locations=PY
A10: 1990 | B10: ANDE_TARIFF_PUBLIC_LIGHT | C10: 61.8 | D10: ='Macro_Annual'!B3 | E10: ='Macro_Annual'!D3 | F10: =IFERROR(C10*'Macro_Annual'!$B$38/D10,"") | G10: =IFERROR(C10*1000/E10,"") | H10: OFFICIAL_AGGREGATE | I10: BACKFILL PROVISIONAL | J10: https://www.ande.gov.py/documentos_contables/157/compilacion_estadistica_1990-2010.pdf | K10: https://data.worldbank.org/indicator/FP.CPI.TOTL?locations=PY | L10: https://data.worldbank.org/indicator/PA.NUS.FCRF?locations=PY
A11: 1990 | B11: ANDE_TARIFF_RESIDENTIAL | C11: 56.1 | D11: ='Macro_Annual'!B3 | E11: ='Macro_Annual'!D3 | F11: =IFERROR(C11*'Macro_Annual'!$B$38/D11,"") | G11: =IFERROR(C11*1000/E11,"") | H11: OFFICIAL_AGGREGATE | I11: BACKFILL PROVISIONAL | J11: https://www.ande.gov.py/documentos_contables/157/compilacion_estadistica_1990-2010.pdf | K11: https://data.worldbank.org/indicator/FP.CPI.TOTL?locations=PY | L11: https://data.worldbank.org/indicator/PA.NUS.FCRF?locations=PY
A12: 1991 | B12: ANDE_TARIFF_COMMERCIAL | C12: 85.4 | D12: ='Macro_Annual'!B4 | E12: ='Macro_Annual'!D4 | F12: =IFERROR(C12*'Macro_Annual'!$B$38/D12,"") | G12: =IFERROR(C12*1000/E12,"") | H12: OFFICIAL_AGGREGATE | I12: BACKFILL PROVISIONAL | J12: https://www.ande.gov.py/documentos_contables/157/compilacion_estadistica_1990-2010.pdf | K12: https://data.worldbank.org/indicator/FP.CPI.TOTL?locations=PY | L12: https://data.worldbank.org/indicator/PA.NUS.FCRF?locations=PY
A13: 1991 | B13: ANDE_TARIFF_EXPORT_AVG | C13: 44.6 | D13: ='Macro_Annual'!B4 | E13: ='Macro_Annual'!D4 | F13: =IFERROR(C13*'Macro_Annual'!$B$38/D13,"") | G13: =IFERROR(C13*1000/E13,"") | H13: OFFICIAL_AGGREGATE | I13: BACKFILL PROVISIONAL | J13: https://www.ande.gov.py/documentos_contables/157/compilacion_estadistica_1990-2010.pdf | K13: https://data.worldbank.org/indicator/FP.CPI.TOTL?locations=PY | L13: https://data.worldbank.org/indicator/PA.NUS.FCRF?locations=PY
A14: 1991 | B14: ANDE_TARIFF_GENERAL | C14: 56.1 | D14: ='Macro_Annual'!B4 | E14: ='Macro_Annual'!D4 | F14: =IFERROR(C14*'Macro_Annual'!$B$38/D14,"") | G14: =IFERROR(C14*1000/E14,"") | H14: OFFICIAL_AGGREGATE | I14: BACKFILL PROVISIONAL | J14: https://www.ande.gov.py/documentos_contables/157/compilacion_estadistica_1990-2010.pdf | K14: https://data.worldbank.org/indicator/FP.CPI.TOTL?locations=PY | L14: https://data.worldbank.org/indicator/PA.NUS.FCRF?locations=PY
A15: 1991 | B15: ANDE_TARIFF_GENERAL_AVG | C15: 61.5 | D15: ='Macro_Annual'!B4 | E15: ='Macro_Annual'!D4 | F15: =IFERROR(C15*'Macro_Annual'!$B$38/D15,"") | G15: =IFERROR(C15*1000/E15,"") | H15: OFFICIAL_AGGREGATE | I15: BACKFILL PROVISIONAL | J15: https://www.ande.gov.py/documentos_contables/157/compilacion_estadistica_1990-2010.pdf | K15: https://data.worldbank.org/indicator/FP.CPI.TOTL?locations=PY | L15: https://data.worldbank.org/indicator/PA.NUS.FCRF?locations=PY
A16: 1991 | B16: ANDE_TARIFF_GOV | C16: 28.9 | D16: ='Macro_Annual'!B4 | E16: ='Macro_Annual'!D4 | F16: =IFERROR(C16*'Macro_Annual'!$B$38/D16,"") | G16: =IFERROR(C16*1000/E16,"") | H16: OFFICIAL_AGGREGATE | I16: BACKFILL PROVISIONAL | J16: https://www.ande.gov.py/documentos_contables/157/compilacion_estadistica_1990-2010.pdf | K16: https://data.worldbank.org/indicator/FP.CPI.TOTL?locations=PY | L16: https://data.worldbank.org/indicator/PA.NUS.FCRF?locations=PY
A17: 1991 | B17: ANDE_TARIFF_INDUSTRIAL | C17: 49.2 | D17: ='Macro_Annual'!B4 | E17: ='Macro_Annual'!D4 | F17: =IFERROR(C17*'Macro_Annual'!$B$38/D17,"") | G17: =IFERROR(C17*1000/E17,"") | H17: OFFICIAL_AGGREGATE | I17: BACKFILL PROVISIONAL | J17: https://www.ande.gov.py/documentos_contables/157/compilacion_estadistica_1990-2010.pdf | K17: https://data.worldbank.org/indicator/FP.CPI.TOTL?locations=PY | L17: https://data.worldbank.org/indicator/PA.NUS.FCRF?locations=PY
A18: 1991 | B18: ANDE_TARIFF_NATIONAL_AVG | C18: 62.2 | D18: ='Macro_Annual'!B4 | E18: ='Macro_Annual'!D4 | F18: =IFERROR(C18*'Macro_Annual'!$B$38/D18,"") | G18: =IFERROR(C18*1000/E18,"") | H18: OFFICIAL_AGGREGATE | I18: BACKFILL PROVISIONAL | J18: https://www.ande.gov.py/documentos_contables/157/compilacion_estadistica_1990-2010.pdf | K18: https://data.worldbank.org/indicator/FP.CPI.TOTL?locations=PY | L18: https://data.worldbank.org/indicator/PA.NUS.FCRF?locations=PY
A19: 1991 | B19: ANDE_TARIFF_PUBLIC_LIGHT | C19: 75.3 | D19: ='Macro_Annual'!B4 | E19: ='Macro_Annual'!D4 | F19: =IFERROR(C19*'Macro_Annual'!$B$38/D19,"") | G19: =IFERROR(C19*1000/E19,"") | H19: OFFICIAL_AGGREGATE | I19: BACKFILL PROVISIONAL | J19: https://www.ande.gov.py/documentos_contables/157/compilacion_estadistica_1990-2010.pdf | K19: https://data.worldbank.org/indicator/FP.CPI.TOTL?locations=PY | L19: https://data.worldbank.org/indicator/PA.NUS.FCRF?locations=PY
A20: 1991 | B20: ANDE_TARIFF_RESIDENTIAL | C20: 66.2 | D20: ='Macro_Annual'!B4 | E20: ='Macro_Annual'!D4 | F20: =IFERROR(C20*'Macro_Annual'!$B$38/D20,"") | G20: =IFERROR(C20*1000/E20,"") | H20: OFFICIAL_AGGREGATE | I20: BACKFILL PROVISIONAL | J20: https://www.ande.gov.py/documentos_contables/157/compilacion_estadistica_1990-2010.pdf | K20: https://data.worldbank.org/indicator/FP.CPI.TOTL?locations=PY | L20: https://data.worldbank.org/indicator/PA.NUS.FCRF?locations=PY
A21: 1992 | B21: ANDE_TARIFF_COMMERCIAL | C21: 85.1 | D21: ='Macro_Annual'!B5 | E21: ='Macro_Annual'!D5 | F21: =IFERROR(C21*'Macro_Annual'!$B$38/D21,"") | G21: =IFERROR(C21*1000/E21,"") | H21: OFFICIAL_AGGREGATE | I21: BACKFILL PROVISIONAL | J21: https://www.ande.gov.py/documentos_contables/157/compilacion_estadistica_1990-2010.pdf | K21: https://data.worldbank.org/indicator/FP.CPI.TOTL?locations=PY | L21: https://data.worldbank.org/indicator/PA.NUS.FCRF?locations=PY
A22: 1992 | B22: ANDE_TARIFF_EXPORT_AVG | C22: 50.2 | D22: ='Macro_Annual'!B5 | E22: ='Macro_Annual'!D5 | F22: =IFERROR(C22*'Macro_Annual'!$B$38/D22,"") | G22: =IFERROR(C22*1000/E22,"") | H22: OFFICIAL_AGGREGATE | I22: BACKFILL PROVISIONAL | J22: https://www.ande.gov.py/documentos_contables/157/compilacion_estadistica_1990-2010.pdf | K22: https://data.worldbank.org/indicator/FP.CPI.TOTL?locations=PY | L22: https://data.worldbank.org/indicator/PA.NUS.FCRF?locations=PY
A23: 1992 | B23: ANDE_TARIFF_GENERAL | C23: 57.3 | D23: ='Macro_Annual'!B5 | E23: ='Macro_Annual'!D5 | F23: =IFERROR(C23*'Macro_Annual'!$B$38/D23,"") | G23: =IFERROR(C23*1000/E23,"") | H23: OFFICIAL_AGGREGATE | I23: BACKFILL PROVISIONAL | J23: https://www.ande.gov.py/documentos_contables/157/compilacion_estadistica_1990-2010.pdf | K23: https://data.worldbank.org/indicator/FP.CPI.TOTL?locations=PY | L23: https://data.worldbank.org/indicator/PA.NUS.FCRF?locations=PY
A24: 1992 | B24: ANDE_TARIFF_GENERAL_AVG | C24: 61.4 | D24: ='Macro_Annual'!B5 | E24: ='Macro_Annual'!D5 | F24: =IFERROR(C24*'Macro_Annual'!$B$38/D24,"") | G24: =IFERROR(C24*1000/E24,"") | H24: OFFICIAL_AGGREGATE | I24: BACKFILL PROVISIONAL | J24: https://www.ande.gov.py/documentos_contables/157/compilacion_estadistica_1990-2010.pdf | K24: https://data.worldbank.org/indicator/FP.CPI.TOTL?locations=PY | L24: https://data.worldbank.org/indicator/PA.NUS.FCRF?locations=PY
A25: 1992 | B25: ANDE_TARIFF_GOV | C25: 25.9 | D25: ='Macro_Annual'!B5 | E25: ='Macro_Annual'!D5 | F25: =IFERROR(C25*'Macro_Annual'!$B$38/D25,"") | G25: =IFERROR(C25*1000/E25,"") | H25: OFFICIAL_AGGREGATE | I25: BACKFILL PROVISIONAL | J25: https://www.ande.gov.py/documentos_contables/157/compilacion_estadistica_1990-2010.pdf | K25: https://data.worldbank.org/indicator/FP.CPI.TOTL?locations=PY | L25: https://data.worldbank.org/indicator/PA.NUS.FCRF?locations=PY
A26: 1992 | B26: ANDE_TARIFF_INDUSTRIAL | C26: 46.9 | D26: ='Macro_Annual'!B5 | E26: ='Macro_Annual'!D5 | F26: =IFERROR(C26*'Macro_Annual'!$B$38/D26,"") | G26: =IFERROR(C26*1000/E26,"") | H26: OFFICIAL_AGGREGATE | I26: BACKFILL PROVISIONAL | J26: https://www.ande.gov.py/documentos_contables/157/compilacion_estadistica_1990-2010.pdf | K26: https://data.worldbank.org/indicator/FP.CPI.TOTL?locations=PY | L26: https://data.worldbank.org/indicator/PA.NUS.FCRF?locations=PY
A27: 1992 | B27: ANDE_TARIFF_NATIONAL_AVG | C27: 61.7 | D27: ='Macro_Annual'!B5 | E27: ='Macro_Annual'!D5 | F27: =IFERROR(C27*'Macro_Annual'!$B$38/D27,"") | G27: =IFERROR(C27*1000/E27,"") | H27: OFFICIAL_AGGREGATE | I27: BACKFILL PROVISIONAL | J27: https://www.ande.gov.py/documentos_contables/157/compilacion_estadistica_1990-2010.pdf | K27: https://data.worldbank.org/indicator/FP.CPI.TOTL?locations=PY | L27: https://data.worldbank.org/indicator/PA.NUS.FCRF?locations=PY
A28: 1992 | B28: ANDE_TARIFF_PUBLIC_LIGHT | C28: 76.3 | D28: ='Macro_Annual'!B5 | E28: ='Macro_Annual'!D5 | F28: =IFERROR(C28*'Macro_Annual'!$B$38/D28,"") | G28: =IFERROR(C28*1000/E28,"") | H28: OFFICIAL_AGGREGATE | I28: BACKFILL PROVISIONAL | J28: https://www.ande.gov.py/documentos_contables/157/compilacion_estadistica_1990-2010.pdf | K28: https://data.worldbank.org/indicator/FP.CPI.TOTL?locations=PY | L28: https://data.worldbank.org/indicator/PA.NUS.FCRF?locations=PY
A29: 1992 | B29: ANDE_TARIFF_RESIDENTIAL | C29: 66.3 | D29: ='Macro_Annual'!B5 | E29: ='Macro_Annual'!D5 | F29: =IFERROR(C29*'Macro_Annual'!$B$38/D29,"") | G29: =IFERROR(C29*1000/E29,"") | H29: OFFICIAL_AGGREGATE | I29: BACKFILL PROVISIONAL | J29: https://www.ande.gov.py/documentos_contables/157/compilacion_estadistica_1990-2010.pdf | K29: https://data.worldbank.org/indicator/FP.CPI.TOTL?locations=PY | L29: https://data.worldbank.org/indicator/PA.NUS.FCRF?locations=PY
A30: 1993 | B30: ANDE_TARIFF_COMMERCIAL | C30: 85.4 | D30: ='Macro_Annual'!B6 | E30: ='Macro_Annual'!D6 | F30: =IFERROR(C30*'Macro_Annual'!$B$38/D30,"") | G30: =IFERROR(C30*1000/E30,"") | H30: OFFICIAL_AGGREGATE | I30: BACKFILL PROVISIONAL | J30: https://www.ande.gov.py/documentos_contables/157/compilacion_estadistica_1990-2010.pdf | K30: https://data.worldbank.org/indicator/FP.CPI.TOTL?locations=PY | L30: https://data.worldbank.org/indicator/PA.NUS.FCRF?locations=PY
A31: 1993 | B31: ANDE_TARIFF_EXPORT_AVG | C31: 65.9 | D31: ='Macro_Annual'!B6 | E31: ='Macro_Annual'!D6 | F31: =IFERROR(C31*'Macro_Annual'!$B$38/D31,"") | G31: =IFERROR(C31*1000/E31,"") | H31: OFFICIAL_AGGREGATE | I31: BACKFILL PROVISIONAL | J31: https://www.ande.gov.py/documentos_contables/157/compilacion_estadistica_1990-2010.pdf | K31: https://data.worldbank.org/indicator/FP.CPI.TOTL?locations=PY | L31: https://data.worldbank.org/indicator/PA.NUS.FCRF?locations=PY
A32: 1993 | B32: ANDE_TARIFF_GENERAL | C32: 62.4 | D32: ='Macro_Annual'!B6 | E32: ='Macro_Annual'!D6 | F32: =IFERROR(C32*'Macro_Annual'!$B$38/D32,"") | G32: =IFERROR(C32*1000/E32,"") | H32: OFFICIAL_AGGREGATE | I32: BACKFILL PROVISIONAL | J32: https://www.ande.gov.py/documentos_contables/157/compilacion_estadistica_1990-2010.pdf | K32: https://data.worldbank.org/indicator/FP.CPI.TOTL?locations=PY | L32: https://data.worldbank.org/indicator/PA.NUS.FCRF?locations=PY
A33: 1993 | B33: ANDE_TARIFF_GENERAL_AVG | C33: 66.4 | D33: ='Macro_Annual'!B6 | E33: ='Macro_Annual'!D6 | F33: =IFERROR(C33*'Macro_Annual'!$B$38/D33,"") | G33: =IFERROR(C33*1000/E33,"") | H33: OFFICIAL_AGGREGATE | I33: BACKFILL PROVISIONAL | J33: https://www.ande.gov.py/documentos_contables/157/compilacion_estadistica_1990-2010.pdf | K33: https://data.worldbank.org/indicator/FP.CPI.TOTL?locations=PY | L33: https://data.worldbank.org/indicator/PA.NUS.FCRF?locations=PY
A34: 1993 | B34: ANDE_TARIFF_GOV | C34: 32.1 | D34: ='Macro_Annual'!B6 | E34: ='Macro_Annual'!D6 | F34: =IFERROR(C34*'Macro_Annual'!$B$38/D34,"") | G34: =IFERROR(C34*1000/E34,"") | H34: OFFICIAL_AGGREGATE | I34: BACKFILL PROVISIONAL | J34: https://www.ande.gov.py/documentos_contables/157/compilacion_estadistica_1990-2010.pdf | K34: https://data.worldbank.org/indicator/FP.CPI.TOTL?locations=PY | L34: https://data.worldbank.org/indicator/PA.NUS.FCRF?locations=PY
A35: 1993 | B35: ANDE_TARIFF_INDUSTRIAL | C35: 52.2 | D35: ='Macro_Annual'!B6 | E35: ='Macro_Annual'!D6 | F35: =IFERROR(C35*'Macro_Annual'!$B$38/D35,"") | G35: =IFERROR(C35*1000/E35,"") | H35: OFFICIAL_AGGREGATE | I35: BACKFILL PROVISIONAL | J35: https://www.ande.gov.py/documentos_contables/157/compilacion_estadistica_1990-2010.pdf | K35: https://data.worldbank.org/indicator/FP.CPI.TOTL?locations=PY | L35: https://data.worldbank.org/indicator/PA.NUS.FCRF?locations=PY
A36: 1993 | B36: ANDE_TARIFF_NATIONAL_AVG | C36: 66.4 | D36: ='Macro_Annual'!B6 | E36: ='Macro_Annual'!D6 | F36: =IFERROR(C36*'Macro_Annual'!$B$38/D36,"") | G36: =IFERROR(C36*1000/E36,"") | H36: OFFICIAL_AGGREGATE | I36: BACKFILL PROVISIONAL | J36: https://www.ande.gov.py/documentos_contables/157/compilacion_estadistica_1990-2010.pdf | K36: https://data.worldbank.org/indicator/FP.CPI.TOTL?locations=PY | L36: https://data.worldbank.org/indicator/PA.NUS.FCRF?locations=PY
A37: 1993 | B37: ANDE_TARIFF_PUBLIC_LIGHT | C37: 84.5 | D37: ='Macro_Annual'!B6 | E37: ='Macro_Annual'!D6 | F37: =IFERROR(C37*'Macro_Annual'!$B$38/D37,"") | G37: =IFERROR(C37*1000/E37,"") | H37: OFFICIAL_AGGREGATE | I37: BACKFILL PROVISIONAL | J37: https://www.ande.gov.py/documentos_contables/157/compilacion_estadistica_1990-2010.pdf | K37: https://data.worldbank.org/indicator/FP.CPI.TOTL?locations=PY | L37: https://data.worldbank.org/indicator/PA.NUS.FCRF?locations=PY
A38: 1993 | B38: ANDE_TARIFF_RESIDENTIAL | C38: 70.6 | D38: ='Macro_Annual'!B6 | E38: ='Macro_Annual'!D6 | F38: =IFERROR(C38*'Macro_Annual'!$B$38/D38,"") | G38: =IFERROR(C38*1000/E38,"") | H38: OFFICIAL_AGGREGATE | I38: BACKFILL PROVISIONAL | J38: https://www.ande.gov.py/documentos_contables/157/compilacion_estadistica_1990-2010.pdf | K38: https://data.worldbank.org/indicator/FP.CPI.TOTL?locations=PY | L38: https://data.worldbank.org/indicator/PA.NUS.FCRF?locations=PY
A39: 1994 | B39: ANDE_TARIFF_COMMERCIAL | C39: 94.7 | D39: ='Macro_Annual'!B7 | E39: ='Macro_Annual'!D7 | F39: =IFERROR(C39*'Macro_Annual'!$B$38/D39,"") | G39: =IFERROR(C39*1000/E39,"") | H39: OFFICIAL_AGGREGATE | I39: BACKFILL PROVISIONAL | J39: https://www.ande.gov.py/documentos_contables/157/compilacion_estadistica_1990-2010.pdf | K39: https://data.worldbank.org/indicator/FP.CPI.TOTL?locations=PY | L39: https://data.worldbank.org/indicator/PA.NUS.FCRF?locations=PY
A40: 1994 | B40: ANDE_TARIFF_EXPORT_AVG | C40: 66.2 | D40: ='Macro_Annual'!B7 | E40: ='Macro_Annual'!D7 | F40: =IFERROR(C40*'Macro_Annual'!$B$38/D40,"") | G40: =IFERROR(C40*1000/E40,"") | H40: OFFICIAL_AGGREGATE | I40: BACKFILL PROVISIONAL | J40: https://www.ande.gov.py/documentos_contables/157/compilacion_estadistica_1990-2010.pdf | K40: https://data.worldbank.org/indicator/FP.CPI.TOTL?locations=PY | L40: https://data.worldbank.org/indicator/PA.NUS.FCRF?locations=PY
A41: 1994 | B41: ANDE_TARIFF_GENERAL | C41: 75.4 | D41: ='Macro_Annual'!B7 | E41: ='Macro_Annual'!D7 | F41: =IFERROR(C41*'Macro_Annual'!$B$38/D41,"") | G41: =IFERROR(C41*1000/E41,"") | H41: OFFICIAL_AGGREGATE | I41: BACKFILL PROVISIONAL | J41: https://www.ande.gov.py/documentos_contables/157/compilacion_estadistica_1990-2010.pdf | K41: https://data.worldbank.org/indicator/FP.CPI.TOTL?locations=PY | L41: https://data.worldbank.org/indicator/PA.NUS.FCRF?locations=PY
A42: 1994 | B42: ANDE_TARIFF_GENERAL_AVG | C42: 79.8 | D42: ='Macro_Annual'!B7 | E42: ='Macro_Annual'!D7 | F42: =IFERROR(C42*'Macro_Annual'!$B$38/D42,"") | G42: =IFERROR(C42*1000/E42,"") | H42: OFFICIAL_AGGREGATE | I42: BACKFILL PROVISIONAL | J42: https://www.ande.gov.py/documentos_contables/157/compilacion_estadistica_1990-2010.pdf | K42: https://data.worldbank.org/indicator/FP.CPI.TOTL?locations=PY | L42: https://data.worldbank.org/indicator/PA.NUS.FCRF?locations=PY
A43: 1994 | B43: ANDE_TARIFF_GOV | C43: 52 | D43: ='Macro_Annual'!B7 | E43: ='Macro_Annual'!D7 | F43: =IFERROR(C43*'Macro_Annual'!$B$38/D43,"") | G43: =IFERROR(C43*1000/E43,"") | H43: OFFICIAL_AGGREGATE | I43: BACKFILL PROVISIONAL | J43: https://www.ande.gov.py/documentos_contables/157/compilacion_estadistica_1990-2010.pdf | K43: https://data.worldbank.org/indicator/FP.CPI.TOTL?locations=PY | L43: https://data.worldbank.org/indicator/PA.NUS.FCRF?locations=PY
A44: 1994 | B44: ANDE_TARIFF_INDUSTRIAL | C44: 63.9 | D44: ='Macro_Annual'!B7 | E44: ='Macro_Annual'!D7 | F44: =IFERROR(C44*'Macro_Annual'!$B$38/D44,"") | G44: =IFERROR(C44*1000/E44,"") | H44: OFFICIAL_AGGREGATE | I44: BACKFILL PROVISIONAL | J44: https://www.ande.gov.py/documentos_contables/157/compilacion_estadistica_1990-2010.pdf | K44: https://data.worldbank.org/indicator/FP.CPI.TOTL?locations=PY | L44: https://data.worldbank.org/indicator/PA.NUS.FCRF?locations=PY
A45: 1994 | B45: ANDE_TARIFF_NATIONAL_AVG | C45: 80.3 | D45: ='Macro_Annual'!B7 | E45: ='Macro_Annual'!D7 | F45: =IFERROR(C45*'Macro_Annual'!$B$38/D45,"") | G45: =IFERROR(C45*1000/E45,"") | H45: OFFICIAL_AGGREGATE | I45: BACKFILL PROVISIONAL | J45: https://www.ande.gov.py/documentos_contables/157/compilacion_estadistica_1990-2010.pdf | K45: https://data.worldbank.org/indicator/FP.CPI.TOTL?locations=PY | L45: https://data.worldbank.org/indicator/PA.NUS.FCRF?locations=PY
A46: 1994 | B46: ANDE_TARIFF_PUBLIC_LIGHT | C46: 116.4 | D46: ='Macro_Annual'!B7 | E46: ='Macro_Annual'!D7 | F46: =IFERROR(C46*'Macro_Annual'!$B$38/D46,"") | G46: =IFERROR(C46*1000/E46,"") | H46: OFFICIAL_AGGREGATE | I46: BACKFILL PROVISIONAL | J46: https://www.ande.gov.py/documentos_contables/157/compilacion_estadistica_1990-2010.pdf | K46: https://data.worldbank.org/indicator/FP.CPI.TOTL?locations=PY | L46: https://data.worldbank.org/indicator/PA.NUS.FCRF?locations=PY
A47: 1994 | B47: ANDE_TARIFF_RESIDENTIAL | C47: 85.5 | D47: ='Macro_Annual'!B7 | E47: ='Macro_Annual'!D7 | F47: =IFERROR(C47*'Macro_Annual'!$B$38/D47,"") | G47: =IFERROR(C47*1000/E47,"") | H47: OFFICIAL_AGGREGATE | I47: BACKFILL PROVISIONAL | J47: https://www.ande.gov.py/documentos_contables/157/compilacion_estadistica_1990-2010.pdf | K47: https://data.worldbank.org/indicator/FP.CPI.TOTL?locations=PY | L47: https://data.worldbank.org/indicator/PA.NUS.FCRF?locations=PY
A48: 1995 | B48: ANDE_TARIFF_COMMERCIAL | C48: 103.5 | D48: ='Macro_Annual'!B8 | E48: ='Macro_Annual'!D8 | F48: =IFERROR(C48*'Macro_Annual'!$B$38/D48,"") | G48: =IFERROR(C48*1000/E48,"") | H48: OFFICIAL_AGGREGATE | I48: BACKFILL PROVISIONAL | J48: https://www.ande.gov.py/documentos_contables/157/compilacion_estadistica_1990-2010.pdf | K48: https://data.worldbank.org/indicator/FP.CPI.TOTL?locations=PY | L48: https://data.worldbank.org/indicator/PA.NUS.FCRF?locations=PY
A49: 1995 | B49: ANDE_TARIFF_EXPORT_AVG | C49: 78.7 | D49: ='Macro_Annual'!B8 | E49: ='Macro_Annual'!D8 | F49: =IFERROR(C49*'Macro_Annual'!$B$38/D49,"") | G49: =IFERROR(C49*1000/E49,"") | H49: OFFICIAL_AGGREGATE | I49: BACKFILL PROVISIONAL | J49: https://www.ande.gov.py/documentos_contables/157/compilacion_estadistica_1990-2010.pdf | K49: https://data.worldbank.org/indicator/FP.CPI.TOTL?locations=PY | L49: https://data.worldbank.org/indicator/PA.NUS.FCRF?locations=PY
A50: 1995 | B50: ANDE_TARIFF_GENERAL | C50: 82.3 | D50: ='Macro_Annual'!B8 | E50: ='Macro_Annual'!D8 | F50: =IFERROR(C50*'Macro_Annual'!$B$38/D50,"") | G50: =IFERROR(C50*1000/E50,"") | H50: OFFICIAL_AGGREGATE | I50: BACKFILL PROVISIONAL | J50: https://www.ande.gov.py/documentos_contables/157/compilacion_estadistica_1990-2010.pdf | K50: https://data.worldbank.org/indicator/FP.CPI.TOTL?locations=PY | L50: https://data.worldbank.org/indicator/PA.NUS.FCRF?locations=PY
A51: 1995 | B51: ANDE_TARIFF_GENERAL_AVG | C51: 88.7 | D51: ='Macro_Annual'!B8 | E51: ='Macro_Annual'!D8 | F51: =IFERROR(C51*'Macro_Annual'!$B$38/D51,"") | G51: =IFERROR(C51*1000/E51,"") | H51: OFFICIAL_AGGREGATE | I51: BACKFILL PROVISIONAL | J51: https://www.ande.gov.py/documentos_contables/157/compilacion_estadistica_1990-2010.pdf | K51: https://data.worldbank.org/indicator/FP.CPI.TOTL?locations=PY | L51: https://data.worldbank.org/indicator/PA.NUS.FCRF?locations=PY
A52: 1995 | B52: ANDE_TARIFF_GOV | C52: 62.6 | D52: ='Macro_Annual'!B8 | E52: ='Macro_Annual'!D8 | F52: =IFERROR(C52*'Macro_Annual'!$B$38/D52,"") | G52: =IFERROR(C52*1000/E52,"") | H52: OFFICIAL_AGGREGATE | I52: BACKFILL PROVISIONAL | J52: https://www.ande.gov.py/documentos_contables/157/compilacion_estadistica_1990-2010.pdf | K52: https://data.worldbank.org/indicator/FP.CPI.TOTL?locations=PY | L52: https://data.worldbank.org/indicator/PA.NUS.FCRF?locations=PY
A53: 1995 | B53: ANDE_TARIFF_INDUSTRIAL | C53: 69.4 | D53: ='Macro_Annual'!B8 | E53: ='Macro_Annual'!D8 | F53: =IFERROR(C53*'Macro_Annual'!$B$38/D53,"") | G53: =IFERROR(C53*1000/E53,"") | H53: OFFICIAL_AGGREGATE | I53: BACKFILL PROVISIONAL | J53: https://www.ande.gov.py/documentos_contables/157/compilacion_estadistica_1990-2010.pdf | K53: https://data.worldbank.org/indicator/FP.CPI.TOTL?locations=PY | L53: https://data.worldbank.org/indicator/PA.NUS.FCRF?locations=PY
A54: 1995 | B54: ANDE_TARIFF_NATIONAL_AVG | C54: 89.2 | D54: ='Macro_Annual'!B8 | E54: ='Macro_Annual'!D8 | F54: =IFERROR(C54*'Macro_Annual'!$B$38/D54,"") | G54: =IFERROR(C54*1000/E54,"") | H54: OFFICIAL_AGGREGATE | I54: BACKFILL PROVISIONAL | J54: https://www.ande.gov.py/documentos_contables/157/compilacion_estadistica_1990-2010.pdf | K54: https://data.worldbank.org/indicator/FP.CPI.TOTL?locations=PY | L54: https://data.worldbank.org/indicator/PA.NUS.FCRF?locations=PY
A55: 1995 | B55: ANDE_TARIFF_PUBLIC_LIGHT | C55: 136.5 | D55: ='Macro_Annual'!B8 | E55: ='Macro_Annual'!D8 | F55: =IFERROR(C55*'Macro_Annual'!$B$38/D55,"") | G55: =IFERROR(C55*1000/E55,"") | H55: OFFICIAL_AGGREGATE | I55: BACKFILL PROVISIONAL | J55: https://www.ande.gov.py/documentos_contables/157/compilacion_estadistica_1990-2010.pdf | K55: https://data.worldbank.org/indicator/FP.CPI.TOTL?locations=PY | L55: https://data.worldbank.org/indicator/PA.NUS.FCRF?locations=PY
A56: 1995 | B56: ANDE_TARIFF_RESIDENTIAL | C56: 95.5 | D56: ='Macro_Annual'!B8 | E56: ='Macro_Annual'!D8 | F56: =IFERROR(C56*'Macro_Annual'!$B$38/D56,"") | G56: =IFERROR(C56*1000/E56,"") | H56: OFFICIAL_AGGREGATE | I56: BACKFILL PROVISIONAL | J56: https://www.ande.gov.py/documentos_contables/157/compilacion_estadistica_1990-2010.pdf | K56: https://data.worldbank.org/indicator/FP.CPI.TOTL?locations=PY | L56: https://data.worldbank.org/indicator/PA.NUS.FCRF?locations=PY
A57: 1996 | B57: ANDE_TARIFF_COMMERCIAL | C57: 123.9 | D57: ='Macro_Annual'!B9 | E57: ='Macro_Annual'!D9 | F57: =IFERROR(C57*'Macro_Annual'!$B$38/D57,"") | G57: =IFERROR(C57*1000/E57,"") | H57: OFFICIAL_AGGREGATE | I57: BACKFILL PROVISIONAL | J57: https://www.ande.gov.py/documentos_contables/157/compilacion_estadistica_1990-2010.pdf | K57: https://data.worldbank.org/indicator/FP.CPI.TOTL?locations=PY | L57: https://data.worldbank.org/indicator/PA.NUS.FCRF?locations=PY
A58: 1996 | B58: ANDE_TARIFF_EXPORT_AVG | C58: 75.4 | D58: ='Macro_Annual'!B9 | E58: ='Macro_Annual'!D9 | F58: =IFERROR(C58*'Macro_Annual'!$B$38/D58,"") | G58: =IFERROR(C58*1000/E58,"") | H58: OFFICIAL_AGGREGATE | I58: BACKFILL PROVISIONAL | J58: https://www.ande.gov.py/documentos_contables/157/compilacion_estadistica_1990-2010.pdf | K58: https://data.worldbank.org/indicator/FP.CPI.TOTL?locations=PY | L58: https://data.worldbank.org/indicator/PA.NUS.FCRF?locations=PY
A59: 1996 | B59: ANDE_TARIFF_GENERAL | C59: 90.1 | D59: ='Macro_Annual'!B9 | E59: ='Macro_Annual'!D9 | F59: =IFERROR(C59*'Macro_Annual'!$B$38/D59,"") | G59: =IFERROR(C59*1000/E59,"") | H59: OFFICIAL_AGGREGATE | I59: BACKFILL PROVISIONAL | J59: https://www.ande.gov.py/documentos_contables/157/compilacion_estadistica_1990-2010.pdf | K59: https://data.worldbank.org/indicator/FP.CPI.TOTL?locations=PY | L59: https://data.worldbank.org/indicator/PA.NUS.FCRF?locations=PY
A60: 1996 | B60: ANDE_TARIFF_GENERAL_AVG | C60: 108.6 | D60: ='Macro_Annual'!B9 | E60: ='Macro_Annual'!D9 | F60: =IFERROR(C60*'Macro_Annual'!$B$38/D60,"") | G60: =IFERROR(C60*1000/E60,"") | H60: OFFICIAL_AGGREGATE | I60: BACKFILL PROVISIONAL | J60: https://www.ande.gov.py/documentos_contables/157/compilacion_estadistica_1990-2010.pdf | K60: https://data.worldbank.org/indicator/FP.CPI.TOTL?locations=PY | L60: https://data.worldbank.org/indicator/PA.NUS.FCRF?locations=PY
A61: 1996 | B61: ANDE_TARIFF_GOV | C61: 103.9 | D61: ='Macro_Annual'!B9 | E61: ='Macro_Annual'!D9 | F61: =IFERROR(C61*'Macro_Annual'!$B$38/D61,"") | G61: =IFERROR(C61*1000/E61,"") | H61: OFFICIAL_AGGREGATE | I61: BACKFILL PROVISIONAL | J61: https://www.ande.gov.py/documentos_contables/157/compilacion_estadistica_1990-2010.pdf | K61: https://data.worldbank.org/indicator/FP.CPI.TOTL?locations=PY | L61: https://data.worldbank.org/indicator/PA.NUS.FCRF?locations=PY
A62: 1996 | B62: ANDE_TARIFF_INDUSTRIAL | C62: 85.8 | D62: ='Macro_Annual'!B9 | E62: ='Macro_Annual'!D9 | F62: =IFERROR(C62*'Macro_Annual'!$B$38/D62,"") | G62: =IFERROR(C62*1000/E62,"") | H62: OFFICIAL_AGGREGATE | I62: BACKFILL PROVISIONAL | J62: https://www.ande.gov.py/documentos_contables/157/compilacion_estadistica_1990-2010.pdf | K62: https://data.worldbank.org/indicator/FP.CPI.TOTL?locations=PY | L62: https://data.worldbank.org/indicator/PA.NUS.FCRF?locations=PY
A63: 1996 | B63: ANDE_TARIFF_NATIONAL_AVG | C63: 110 | D63: ='Macro_Annual'!B9 | E63: ='Macro_Annual'!D9 | F63: =IFERROR(C63*'Macro_Annual'!$B$38/D63,"") | G63: =IFERROR(C63*1000/E63,"") | H63: OFFICIAL_AGGREGATE | I63: BACKFILL PROVISIONAL | J63: https://www.ande.gov.py/documentos_contables/157/compilacion_estadistica_1990-2010.pdf | K63: https://data.worldbank.org/indicator/FP.CPI.TOTL?locations=PY | L63: https://data.worldbank.org/indicator/PA.NUS.FCRF?locations=PY
A64: 1996 | B64: ANDE_TARIFF_PUBLIC_LIGHT | C64: 171.4 | D64: ='Macro_Annual'!B9 | E64: ='Macro_Annual'!D9 | F64: =IFERROR(C64*'Macro_Annual'!$B$38/D64,"") | G64: =IFERROR(C64*1000/E64,"") | H64: OFFICIAL_AGGREGATE | I64: BACKFILL PROVISIONAL | J64: https://www.ande.gov.py/documentos_contables/157/compilacion_estadistica_1990-2010.pdf | K64: https://data.worldbank.org/indicator/FP.CPI.TOTL?locations=PY | L64: https://data.worldbank.org/indicator/PA.NUS.FCRF?locations=PY
A65: 1996 | B65: ANDE_TARIFF_RESIDENTIAL | C65: 118 | D65: ='Macro_Annual'!B9 | E65: ='Macro_Annual'!D9 | F65: =IFERROR(C65*'Macro_Annual'!$B$38/D65,"") | G65: =IFERROR(C65*1000/E65,"") | H65: OFFICIAL_AGGREGATE | I65: BACKFILL PROVISIONAL | J65: https://www.ande.gov.py/documentos_contables/157/compilacion_estadistica_1990-2010.pdf | K65: https://data.worldbank.org/indicator/FP.CPI.TOTL?locations=PY | L65: https://data.worldbank.org/indicator/PA.NUS.FCRF?locations=PY
A66: 1997 | B66: ANDE_TARIFF_COMMERCIAL | C66: 139.3 | D66: ='Macro_Annual'!B10 | E66: ='Macro_Annual'!D10 | F66: =IFERROR(C66*'Macro_Annual'!$B$38/D66,"") | G66: =IFERROR(C66*1000/E66,"") | H66: OFFICIAL_AGGREGATE | I66: BACKFILL PROVISIONAL | J66: https://www.ande.gov.py/documentos_contables/157/compilacion_estadistica_1990-2010.pdf | K66: https://data.worldbank.org/indicator/FP.CPI.TOTL?locations=PY | L66: https://data.worldbank.org/indicator/PA.NUS.FCRF?locations=PY
A67: 1997 | B67: ANDE_TARIFF_EXPORT_AVG | C67: 55 | D67: ='Macro_Annual'!B10 | E67: ='Macro_Annual'!D10 | F67: =IFERROR(C67*'Macro_Annual'!$B$38/D67,"") | G67: =IFERROR(C67*1000/E67,"") | H67: OFFICIAL_AGGREGATE | I67: BACKFILL PROVISIONAL | J67: https://www.ande.gov.py/documentos_contables/157/compilacion_estadistica_1990-2010.pdf | K67: https://data.worldbank.org/indicator/FP.CPI.TOTL?locations=PY | L67: https://data.worldbank.org/indicator/PA.NUS.FCRF?locations=PY
A68: 1997 | B68: ANDE_TARIFF_GENERAL | C68: 103.9 | D68: ='Macro_Annual'!B10 | E68: ='Macro_Annual'!D10 | F68: =IFERROR(C68*'Macro_Annual'!$B$38/D68,"") | G68: =IFERROR(C68*1000/E68,"") | H68: OFFICIAL_AGGREGATE | I68: BACKFILL PROVISIONAL | J68: https://www.ande.gov.py/documentos_contables/157/compilacion_estadistica_1990-2010.pdf | K68: https://data.worldbank.org/indicator/FP.CPI.TOTL?locations=PY | L68: https://data.worldbank.org/indicator/PA.NUS.FCRF?locations=PY
A69: 1997 | B69: ANDE_TARIFF_GENERAL_AVG | C69: 122.7 | D69: ='Macro_Annual'!B10 | E69: ='Macro_Annual'!D10 | F69: =IFERROR(C69*'Macro_Annual'!$B$38/D69,"") | G69: =IFERROR(C69*1000/E69,"") | H69: OFFICIAL_AGGREGATE | I69: BACKFILL PROVISIONAL | J69: https://www.ande.gov.py/documentos_contables/157/compilacion_estadistica_1990-2010.pdf | K69: https://data.worldbank.org/indicator/FP.CPI.TOTL?locations=PY | L69: https://data.worldbank.org/indicator/PA.NUS.FCRF?locations=PY
A70: 1997 | B70: ANDE_TARIFF_GOV | C70: 95.4 | D70: ='Macro_Annual'!B10 | E70: ='Macro_Annual'!D10 | F70: =IFERROR(C70*'Macro_Annual'!$B$38/D70,"") | G70: =IFERROR(C70*1000/E70,"") | H70: OFFICIAL_AGGREGATE | I70: BACKFILL PROVISIONAL | J70: https://www.ande.gov.py/documentos_contables/157/compilacion_estadistica_1990-2010.pdf | K70: https://data.worldbank.org/indicator/FP.CPI.TOTL?locations=PY | L70: https://data.worldbank.org/indicator/PA.NUS.FCRF?locations=PY
A71: 1997 | B71: ANDE_TARIFF_INDUSTRIAL | C71: 95.8 | D71: ='Macro_Annual'!B10 | E71: ='Macro_Annual'!D10 | F71: =IFERROR(C71*'Macro_Annual'!$B$38/D71,"") | G71: =IFERROR(C71*1000/E71,"") | H71: OFFICIAL_AGGREGATE | I71: BACKFILL PROVISIONAL | J71: https://www.ande.gov.py/documentos_contables/157/compilacion_estadistica_1990-2010.pdf | K71: https://data.worldbank.org/indicator/FP.CPI.TOTL?locations=PY | L71: https://data.worldbank.org/indicator/PA.NUS.FCRF?locations=PY
A72: 1997 | B72: ANDE_TARIFF_NATIONAL_AVG | C72: 124.6 | D72: ='Macro_Annual'!B10 | E72: ='Macro_Annual'!D10 | F72: =IFERROR(C72*'Macro_Annual'!$B$38/D72,"") | G72: =IFERROR(C72*1000/E72,"") | H72: OFFICIAL_AGGREGATE | I72: BACKFILL PROVISIONAL | J72: https://www.ande.gov.py/documentos_contables/157/compilacion_estadistica_1990-2010.pdf | K72: https://data.worldbank.org/indicator/FP.CPI.TOTL?locations=PY | L72: https://data.worldbank.org/indicator/PA.NUS.FCRF?locations=PY
A73: 1997 | B73: ANDE_TARIFF_PUBLIC_LIGHT | C73: 177.8 | D73: ='Macro_Annual'!B10 | E73: ='Macro_Annual'!D10 | F73: =IFERROR(C73*'Macro_Annual'!$B$38/D73,"") | G73: =IFERROR(C73*1000/E73,"") | H73: OFFICIAL_AGGREGATE | I73: BACKFILL PROVISIONAL | J73: https://www.ande.gov.py/documentos_contables/157/compilacion_estadistica_1990-2010.pdf | K73: https://data.worldbank.org/indicator/FP.CPI.TOTL?locations=PY | L73: https://data.worldbank.org/indicator/PA.NUS.FCRF?locations=PY
A74: 1997 | B74: ANDE_TARIFF_RESIDENTIAL | C74: 135.1 | D74: ='Macro_Annual'!B10 | E74: ='Macro_Annual'!D10 | F74: =IFERROR(C74*'Macro_Annual'!$B$38/D74,"") | G74: =IFERROR(C74*1000/E74,"") | H74: OFFICIAL_AGGREGATE | I74: BACKFILL PROVISIONAL | J74: https://www.ande.gov.py/documentos_contables/157/compilacion_estadistica_1990-2010.pdf | K74: https://data.worldbank.org/indicator/FP.CPI.TOTL?locations=PY | L74: https://data.worldbank.org/indicator/PA.NUS.FCRF?locations=PY
A75: 1998 | B75: ANDE_TARIFF_COMMERCIAL | C75: 163.2 | D75: ='Macro_Annual'!B11 | E75: ='Macro_Annual'!D11 | F75: =IFERROR(C75*'Macro_Annual'!$B$38/D75,"") | G75: =IFERROR(C75*1000/E75,"") | H75: OFFICIAL_AGGREGATE | I75: BACKFILL PROVISIONAL | J75: https://www.ande.gov.py/documentos_contables/157/compilacion_estadistica_1990-2010.pdf | K75: https://data.worldbank.org/indicator/FP.CPI.TOTL?locations=PY | L75: https://data.worldbank.org/indicator/PA.NUS.FCRF?locations=PY
A76: 1998 | B76: ANDE_TARIFF_EXPORT_AVG | C76: 48.7 | D76: ='Macro_Annual'!B11 | E76: ='Macro_Annual'!D11 | F76: =IFERROR(C76*'Macro_Annual'!$B$38/D76,"") | G76: =IFERROR(C76*1000/E76,"") | H76: OFFICIAL_AGGREGATE | I76: BACKFILL PROVISIONAL | J76: https://www.ande.gov.py/documentos_contables/157/compilacion_estadistica_1990-2010.pdf | K76: https://data.worldbank.org/indicator/FP.CPI.TOTL?locations=PY | L76: https://data.worldbank.org/indicator/PA.NUS.FCRF?locations=PY
A77: 1998 | B77: ANDE_TARIFF_GENERAL | C77: 149.1 | D77: ='Macro_Annual'!B11 | E77: ='Macro_Annual'!D11 | F77: =IFERROR(C77*'Macro_Annual'!$B$38/D77,"") | G77: =IFERROR(C77*1000/E77,"") | H77: OFFICIAL_AGGREGATE | I77: BACKFILL PROVISIONAL | J77: https://www.ande.gov.py/documentos_contables/157/compilacion_estadistica_1990-2010.pdf | K77: https://data.worldbank.org/indicator/FP.CPI.TOTL?locations=PY | L77: https://data.worldbank.org/indicator/PA.NUS.FCRF?locations=PY
A78: 1998 | B78: ANDE_TARIFF_GENERAL_AVG | C78: 146.1 | D78: ='Macro_Annual'!B11 | E78: ='Macro_Annual'!D11 | F78: =IFERROR(C78*'Macro_Annual'!$B$38/D78,"") | G78: =IFERROR(C78*1000/E78,"") | H78: OFFICIAL_AGGREGATE | I78: BACKFILL PROVISIONAL | J78: https://www.ande.gov.py/documentos_contables/157/compilacion_estadistica_1990-2010.pdf | K78: https://data.worldbank.org/indicator/FP.CPI.TOTL?locations=PY | L78: https://data.worldbank.org/indicator/PA.NUS.FCRF?locations=PY
A79: 1998 | B79: ANDE_TARIFF_GOV | C79: 120.1 | D79: ='Macro_Annual'!B11 | E79: ='Macro_Annual'!D11 | F79: =IFERROR(C79*'Macro_Annual'!$B$38/D79,"") | G79: =IFERROR(C79*1000/E79,"") | H79: OFFICIAL_AGGREGATE | I79: BACKFILL PROVISIONAL | J79: https://www.ande.gov.py/documentos_contables/157/compilacion_estadistica_1990-2010.pdf | K79: https://data.worldbank.org/indicator/FP.CPI.TOTL?locations=PY | L79: https://data.worldbank.org/indicator/PA.NUS.FCRF?locations=PY
A80: 1998 | B80: ANDE_TARIFF_INDUSTRIAL | C80: 109.6 | D80: ='Macro_Annual'!B11 | E80: ='Macro_Annual'!D11 | F80: =IFERROR(C80*'Macro_Annual'!$B$38/D80,"") | G80: =IFERROR(C80*1000/E80,"") | H80: OFFICIAL_AGGREGATE | I80: BACKFILL PROVISIONAL | J80: https://www.ande.gov.py/documentos_contables/157/compilacion_estadistica_1990-2010.pdf | K80: https://data.worldbank.org/indicator/FP.CPI.TOTL?locations=PY | L80: https://data.worldbank.org/indicator/PA.NUS.FCRF?locations=PY
A81: 1998 | B81: ANDE_TARIFF_NATIONAL_AVG | C81: 148.6 | D81: ='Macro_Annual'!B11 | E81: ='Macro_Annual'!D11 | F81: =IFERROR(C81*'Macro_Annual'!$B$38/D81,"") | G81: =IFERROR(C81*1000/E81,"") | H81: OFFICIAL_AGGREGATE | I81: BACKFILL PROVISIONAL | J81: https://www.ande.gov.py/documentos_contables/157/compilacion_estadistica_1990-2010.pdf | K81: https://data.worldbank.org/indicator/FP.CPI.TOTL?locations=PY | L81: https://data.worldbank.org/indicator/PA.NUS.FCRF?locations=PY
A82: 1998 | B82: ANDE_TARIFF_PUBLIC_LIGHT | C82: 185.2 | D82: ='Macro_Annual'!B11 | E82: ='Macro_Annual'!D11 | F82: =IFERROR(C82*'Macro_Annual'!$B$38/D82,"") | G82: =IFERROR(C82*1000/E82,"") | H82: OFFICIAL_AGGREGATE | I82: BACKFILL PROVISIONAL | J82: https://www.ande.gov.py/documentos_contables/157/compilacion_estadistica_1990-2010.pdf | K82: https://data.worldbank.org/indicator/FP.CPI.TOTL?locations=PY | L82: https://data.worldbank.org/indicator/PA.NUS.FCRF?locations=PY
A83: 1998 | B83: ANDE_TARIFF_RESIDENTIAL | C83: 159.9 | D83: ='Macro_Annual'!B11 | E83: ='Macro_Annual'!D11 | F83: =IFERROR(C83*'Macro_Annual'!$B$38/D83,"") | G83: =IFERROR(C83*1000/E83,"") | H83: OFFICIAL_AGGREGATE | I83: BACKFILL PROVISIONAL | J83: https://www.ande.gov.py/documentos_contables/157/compilacion_estadistica_1990-2010.pdf | K83: https://data.worldbank.org/indicator/FP.CPI.TOTL?locations=PY | L83: https://data.worldbank.org/indicator/PA.NUS.FCRF?locations=PY
A84: 1999 | B84: ANDE_TARIFF_COMMERCIAL | C84: 163.4 | D84: ='Macro_Annual'!B12 | E84: ='Macro_Annual'!D12 | F84: =IFERROR(C84*'Macro_Annual'!$B$38/D84,"") | G84: =IFERROR(C84*1000/E84,"") | H84: OFFICIAL_AGGREGATE | I84: BACKFILL PROVISIONAL | J84: https://www.ande.gov.py/documentos_contables/157/compilacion_estadistica_1990-2010.pdf | K84: https://data.worldbank.org/indicator/FP.CPI.TOTL?locations=PY | L84: https://data.worldbank.org/indicator/PA.NUS.FCRF?locations=PY
A85: 1999 | B85: ANDE_TARIFF_EXPORT_AVG | C85: 40.2 | D85: ='Macro_Annual'!B12 | E85: ='Macro_Annual'!D12 | F85: =IFERROR(C85*'Macro_Annual'!$B$38/D85,"") | G85: =IFERROR(C85*1000/E85,"") | H85: OFFICIAL_AGGREGATE | I85: BACKFILL PROVISIONAL | J85: https://www.ande.gov.py/documentos_contables/157/compilacion_estadistica_1990-2010.pdf | K85: https://data.worldbank.org/indicator/FP.CPI.TOTL?locations=PY | L85: https://data.worldbank.org/indicator/PA.NUS.FCRF?locations=PY
A86: 1999 | B86: ANDE_TARIFF_GENERAL | C86: 154.9 | D86: ='Macro_Annual'!B12 | E86: ='Macro_Annual'!D12 | F86: =IFERROR(C86*'Macro_Annual'!$B$38/D86,"") | G86: =IFERROR(C86*1000/E86,"") | H86: OFFICIAL_AGGREGATE | I86: BACKFILL PROVISIONAL | J86: https://www.ande.gov.py/documentos_contables/157/compilacion_estadistica_1990-2010.pdf | K86: https://data.worldbank.org/indicator/FP.CPI.TOTL?locations=PY | L86: https://data.worldbank.org/indicator/PA.NUS.FCRF?locations=PY
A87: 1999 | B87: ANDE_TARIFF_GENERAL_AVG | C87: 136.1 | D87: ='Macro_Annual'!B12 | E87: ='Macro_Annual'!D12 | F87: =IFERROR(C87*'Macro_Annual'!$B$38/D87,"") | G87: =IFERROR(C87*1000/E87,"") | H87: OFFICIAL_AGGREGATE | I87: BACKFILL PROVISIONAL | J87: https://www.ande.gov.py/documentos_contables/157/compilacion_estadistica_1990-2010.pdf | K87: https://data.worldbank.org/indicator/FP.CPI.TOTL?locations=PY | L87: https://data.worldbank.org/indicator/PA.NUS.FCRF?locations=PY
A88: 1999 | B88: ANDE_TARIFF_GOV | C88: 129 | D88: ='Macro_Annual'!B12 | E88: ='Macro_Annual'!D12 | F88: =IFERROR(C88*'Macro_Annual'!$B$38/D88,"") | G88: =IFERROR(C88*1000/E88,"") | H88: OFFICIAL_AGGREGATE | I88: BACKFILL PROVISIONAL | J88: https://www.ande.gov.py/documentos_contables/157/compilacion_estadistica_1990-2010.pdf | K88: https://data.worldbank.org/indicator/FP.CPI.TOTL?locations=PY | L88: https://data.worldbank.org/indicator/PA.NUS.FCRF?locations=PY
A89: 1999 | B89: ANDE_TARIFF_INDUSTRIAL | C89: 99.9 | D89: ='Macro_Annual'!B12 | E89: ='Macro_Annual'!D12 | F89: =IFERROR(C89*'Macro_Annual'!$B$38/D89,"") | G89: =IFERROR(C89*1000/E89,"") | H89: OFFICIAL_AGGREGATE | I89: BACKFILL PROVISIONAL | J89: https://www.ande.gov.py/documentos_contables/157/compilacion_estadistica_1990-2010.pdf | K89: https://data.worldbank.org/indicator/FP.CPI.TOTL?locations=PY | L89: https://data.worldbank.org/indicator/PA.NUS.FCRF?locations=PY
A90: 1999 | B90: ANDE_TARIFF_NATIONAL_AVG | C90: 146.8 | D90: ='Macro_Annual'!B12 | E90: ='Macro_Annual'!D12 | F90: =IFERROR(C90*'Macro_Annual'!$B$38/D90,"") | G90: =IFERROR(C90*1000/E90,"") | H90: OFFICIAL_AGGREGATE | I90: BACKFILL PROVISIONAL | J90: https://www.ande.gov.py/documentos_contables/157/compilacion_estadistica_1990-2010.pdf | K90: https://data.worldbank.org/indicator/FP.CPI.TOTL?locations=PY | L90: https://data.worldbank.org/indicator/PA.NUS.FCRF?locations=PY
A91: 1999 | B91: ANDE_TARIFF_PUBLIC_LIGHT | C91: 171.2 | D91: ='Macro_Annual'!B12 | E91: ='Macro_Annual'!D12 | F91: =IFERROR(C91*'Macro_Annual'!$B$38/D91,"") | G91: =IFERROR(C91*1000/E91,"") | H91: OFFICIAL_AGGREGATE | I91: BACKFILL PROVISIONAL | J91: https://www.ande.gov.py/documentos_contables/157/compilacion_estadistica_1990-2010.pdf | K91: https://data.worldbank.org/indicator/FP.CPI.TOTL?locations=PY | L91: https://data.worldbank.org/indicator/PA.NUS.FCRF?locations=PY
A92: 1999 | B92: ANDE_TARIFF_RESIDENTIAL | C92: 161.7 | D92: ='Macro_Annual'!B12 | E92: ='Macro_Annual'!D12 | F92: =IFERROR(C92*'Macro_Annual'!$B$38/D92,"") | G92: =IFERROR(C92*1000/E92,"") | H92: OFFICIAL_AGGREGATE | I92: BACKFILL PROVISIONAL | J92: https://www.ande.gov.py/documentos_contables/157/compilacion_estadistica_1990-2010.pdf | K92: https://data.worldbank.org/indicator/FP.CPI.TOTL?locations=PY | L92: https://data.worldbank.org/indicator/PA.NUS.FCRF?locations=PY
A93: 2000 | B93: ANDE_TARIFF_COMMERCIAL | C93: 175.9 | D93: ='Macro_Annual'!B13 | E93: ='Macro_Annual'!D13 | F93: =IFERROR(C93*'Macro_Annual'!$B$38/D93,"") | G93: =IFERROR(C93*1000/E93,"") | H93: OFFICIAL_AGGREGATE | I93: BACKFILL PROVISIONAL | J93: https://www.ande.gov.py/documentos_contables/157/compilacion_estadistica_1990-2010.pdf | K93: https://data.worldbank.org/indicator/FP.CPI.TOTL?locations=PY | L93: https://data.worldbank.org/indicator/PA.NUS.FCRF?locations=PY
A94: 2000 | B94: ANDE_TARIFF_EXPORT_AVG | C94: 53.7 | D94: ='Macro_Annual'!B13 | E94: ='Macro_Annual'!D13 | F94: =IFERROR(C94*'Macro_Annual'!$B$38/D94,"") | G94: =IFERROR(C94*1000/E94,"") | H94: OFFICIAL_AGGREGATE | I94: BACKFILL PROVISIONAL | J94: https://www.ande.gov.py/documentos_contables/157/compilacion_estadistica_1990-2010.pdf | K94: https://data.worldbank.org/indicator/FP.CPI.TOTL?locations=PY | L94: https://data.worldbank.org/indicator/PA.NUS.FCRF?locations=PY
A95: 2000 | B95: ANDE_TARIFF_GENERAL | C95: 155.1 | D95: ='Macro_Annual'!B13 | E95: ='Macro_Annual'!D13 | F95: =IFERROR(C95*'Macro_Annual'!$B$38/D95,"") | G95: =IFERROR(C95*1000/E95,"") | H95: OFFICIAL_AGGREGATE | I95: BACKFILL PROVISIONAL | J95: https://www.ande.gov.py/documentos_contables/157/compilacion_estadistica_1990-2010.pdf | K95: https://data.worldbank.org/indicator/FP.CPI.TOTL?locations=PY | L95: https://data.worldbank.org/indicator/PA.NUS.FCRF?locations=PY
A96: 2000 | B96: ANDE_TARIFF_GENERAL_AVG | C96: 146.4 | D96: ='Macro_Annual'!B13 | E96: ='Macro_Annual'!D13 | F96: =IFERROR(C96*'Macro_Annual'!$B$38/D96,"") | G96: =IFERROR(C96*1000/E96,"") | H96: OFFICIAL_AGGREGATE | I96: BACKFILL PROVISIONAL | J96: https://www.ande.gov.py/documentos_contables/157/compilacion_estadistica_1990-2010.pdf | K96: https://data.worldbank.org/indicator/FP.CPI.TOTL?locations=PY | L96: https://data.worldbank.org/indicator/PA.NUS.FCRF?locations=PY
A97: 2000 | B97: ANDE_TARIFF_GOV | C97: 129.8 | D97: ='Macro_Annual'!B13 | E97: ='Macro_Annual'!D13 | F97: =IFERROR(C97*'Macro_Annual'!$B$38/D97,"") | G97: =IFERROR(C97*1000/E97,"") | H97: OFFICIAL_AGGREGATE | I97: BACKFILL PROVISIONAL | J97: https://www.ande.gov.py/documentos_contables/157/compilacion_estadistica_1990-2010.pdf | K97: https://data.worldbank.org/indicator/FP.CPI.TOTL?locations=PY | L97: https://data.worldbank.org/indicator/PA.NUS.FCRF?locations=PY
A98: 2000 | B98: ANDE_TARIFF_INDUSTRIAL | C98: 111.6 | D98: ='Macro_Annual'!B13 | E98: ='Macro_Annual'!D13 | F98: =IFERROR(C98*'Macro_Annual'!$B$38/D98,"") | G98: =IFERROR(C98*1000/E98,"") | H98: OFFICIAL_AGGREGATE | I98: BACKFILL PROVISIONAL | J98: https://www.ande.gov.py/documentos_contables/157/compilacion_estadistica_1990-2010.pdf | K98: https://data.worldbank.org/indicator/FP.CPI.TOTL?locations=PY | L98: https://data.worldbank.org/indicator/PA.NUS.FCRF?locations=PY
A99: 2000 | B99: ANDE_TARIFF_NATIONAL_AVG | C99: 159.1 | D99: ='Macro_Annual'!B13 | E99: ='Macro_Annual'!D13 | F99: =IFERROR(C99*'Macro_Annual'!$B$38/D99,"") | G99: =IFERROR(C99*1000/E99,"") | H99: OFFICIAL_AGGREGATE | I99: BACKFILL PROVISIONAL | J99: https://www.ande.gov.py/documentos_contables/157/compilacion_estadistica_1990-2010.pdf | K99: https://data.worldbank.org/indicator/FP.CPI.TOTL?locations=PY | L99: https://data.worldbank.org/indicator/PA.NUS.FCRF?locations=PY
A100: 2000 | B100: ANDE_TARIFF_PUBLIC_LIGHT | C100: 235.6 | D100: ='Macro_Annual'!B13 | E100: ='Macro_Annual'!D13 | F100: =IFERROR(C100*'Macro_Annual'!$B$38/D100,"") | G100: =IFERROR(C100*1000/E100,"") | H100: OFFICIAL_AGGREGATE | I100: BACKFILL PROVISIONAL | J100: https://www.ande.gov.py/documentos_contables/157/compilacion_estadistica_1990-2010.pdf | K100: https://data.worldbank.org/indicator/FP.CPI.TOTL?locations=PY | L100: https://data.worldbank.org/indicator/PA.NUS.FCRF?locations=PY
...

Sheet Macro_Notes
A1: EnergiaPY.live — Lineage y uso de macrodatos
A2: Tema | B2: Regla | C2: Fuente primaria objetivo | D2: Backfill actual | E2: Uso en EnergiaPY
A3: IPC | B3: BCP controla la serie final. WDI/IMF se usa como backfill provisional hasta reconciliar el XLSX empalmado BCP. | C3: https://www.bcp.gov.py/es/web/institucional/indice-precios-al-consumidor-ipc | D3: https://data.worldbank.org/indicator/FP.CPI.TOTL?locations=PY | E3: Tarifas en guaraníes reales, poder de compra y comparaciones históricas.
A4: USD/PYG | B4: Usar promedio anual para históricos; cotización puntual solo para calculadoras actuales. | C4: https://www.bcp.gov.py/webapps/web/cotizacion/monedas-historica | D4: https://data.worldbank.org/indicator/PA.NUS.FCRF?locations=PY | E4: Convertir Gs/kWh a USD/MWh sin usar el dólar actual para años pasados.
A5: 2026 actual | B5: No inferir promedio anual 2026 desde una cotización puntual. Guardar observaciones BCP con fecha. | C5: https://www.bcp.gov.py/webapps/web/cotizacion/monedas | D5: N/A | E5: Calculadora ciudadanía y contexto actual.
A6: Expectativas | B6: EVE es expectativa de agentes, no dato realizado. | C6: https://www.bcp.gov.py/es/web/institucional/w/encuesta-de-expectativas-de-variables-econ%C3%B3micas-agosto-2026/-/categories/158845 | D6: N/A | E6: Escenarios, no históricos realizados.
A7: Revisión | B7: Cuando el collector BCP ingiera el bruto oficial, comparar diferencias y elevar BCP a canonical sin borrar el backfill. | C7: https://www.bcp.gov.py/es/web/institucional/indice-precios-al-consumidor-ipc | https://www.bcp.gov.py/webapps/web/cotizacion/monedas-historica | D7: https://data.worldbank.org/indicator/FP.CPI.TOTL?locations=PY | https://data.worldbank.org/indicator/PA.NUS.FCRF?locations=PY | E7: Auditoría y reproducibilidad.

Sheet Economic_Terms
A1: term_id | B1: term_code | C1: asset_code | D1: effective_from | E1: effective_to | F1: concept | G1: value | H1: unit | I1: currency | J1: source_code | K1: authority_class | L1: source_url | M1: notes
A2: T0001 | B2: YACYRETA_RIGHT_SHARE | C2: YACYRETA | D2: 1973-12-13 | F2: Derecho de cada Parte sobre energia generada | G2: 50 | H2: percent | J2: BACN | K2: OFFICIAL_LEGAL | L2: https://www.bacn.gov.py/leyes-paraguayas/8397/ley-n-6135-aprueba-el-acuerdo-por-notas-reversales-n-r-n-2-17-para-el-ordenamiento-econ-mico-y-financiero-de-la-entidad-binacional-yacyret-entre-la-rep-blica-del-paraguay-y-la-rep-blica-argentina | M2: Tratado/ordenamiento binacional; energia no utilizada puede cederse con compensacion.
A3: T0002 | B3: YACYRETA_CESSION_BASE_PRE2017 | C3: YACYRETA | E3: 2016-12-31 | F3: Compensacion unitaria por energia cedida | G3: 2998 | H3: USD/GWh | I3: USD | J3: BACN | K3: OFFICIAL_LEGAL | L3: https://www.bacn.gov.py/leyes-paraguayas/8397/ley-n-6135-aprueba-el-acuerdo-por-notas-reversales-n-r-n-2-17-para-el-ordenamiento-econ-mico-y-financiero-de-la-entidad-binacional-yacyret-entre-la-rep-blica-del-paraguay-y-la-rep-blica-argentina | M3: Valor base marzo 1974; se mantiene constante mediante formula de actualizacion.
A4: T0003 | B4: YACYRETA_CESSION_BASE_2017 | C4: YACYRETA | D4: 2017-01-01 | F4: Compensacion unitaria por energia cedida | G4: 3598 | H4: USD/GWh | I4: USD | J4: BACN | K4: OFFICIAL_LEGAL | L4: https://www.bacn.gov.py/leyes-paraguayas/8397/ley-n-6135-aprueba-el-acuerdo-por-notas-reversales-n-r-n-2-17-para-el-ordenamiento-econ-mico-y-financiero-de-la-entidad-binacional-yacyret-entre-la-rep-blica-del-paraguay-y-la-rep-blica-argentina | M4: Valor base marzo 1974, sujeto a actualizacion contractual.
A5: T0004 | B5: YACYRETA_MIN_ANNUAL_COMP | C5: YACYRETA | F5: Compensacion minima anual | G5: 9000000 | H5: USD/year | I5: USD | J5: BACN | K5: OFFICIAL_LEGAL | L5: https://www.bacn.gov.py/leyes-paraguayas/8397/ley-n-6135-aprueba-el-acuerdo-por-notas-reversales-n-r-n-2-17-para-el-ordenamiento-econ-mico-y-financiero-de-la-entidad-binacional-yacyret-entre-la-rep-blica-del-paraguay-y-la-rep-blica-argentina | M5: Referencia del regimen contractual; verificar aplicabilidad por periodo antes de uso analitico.
A6: T0005 | B6: ACARAY_COPEL_CONTRACT | C6: ACARAY | D6: 1969-12-03 | E6: 2014-12-31 | F6: Contrato de interconexion y abastecimiento ANDE-COPEL | J6: ANDE | K6: OFFICIAL_PRIMARY | L6: https://www.ande.gov.py/interna.php?id=8362 | M6: Venta, compra, entrega y recepcion de energia; linea 138 kV Acaray-Foz.
A7: T0006 | B7: ACARAY_BRAZIL_ACL_TENDER | C7: ACARAY | D7: 2024-05-31 | F7: Concurso para venta de 100 MW medios al ACL Brasil | G7: 100 | H7: MWavg | J7: ANDE | K7: OFFICIAL_PRIMARY | L7: https://www.ande.gov.py/interna.php?id=12352 | M7: Plazo 1-6 años; entrega en SMD vinculada a frontera Itaipu. Ofertas no equivalen a contrato.

Sheet Economic_Transactions
A1: transaction_id | B1: period_start | C1: period_end | D1: grain | E1: transaction_code | F1: asset_code | G1: payer | H1: payee | I1: value | J1: currency | K1: source_code | L1: authority_class | M1: quality_class | N1: source_url | O1: notes
A2: X00001 | B2: 1989-01-01 | C2: 1989-12-31 | D2: year | E2: ITAIPU_ROYALTIES_CASH | F2: ITAIPU | G2: ITAIPU | H2: PY_TREASURY | I2: 36734560 | J2: USD | K2: ITAIPU | L2: OFFICIAL_PRIMARY | M2: OFFICIAL_ACCOUNTING | N2: https://www.itaipu.gov.py/wp-content/uploads/2026/04/03-Planillas-de-Royalties-31_03_26.pdf | O2: Regimen de caja; planilla anual oficial.
A3: X00002 | B3: 1990-01-01 | C3: 1990-12-31 | D3: year | E3: ITAIPU_ROYALTIES_CASH | F3: ITAIPU | G3: ITAIPU | H3: PY_TREASURY | I3: 80245850 | J3: USD | K3: ITAIPU | L3: OFFICIAL_PRIMARY | M3: OFFICIAL_ACCOUNTING | N3: https://www.itaipu.gov.py/wp-content/uploads/2026/04/03-Planillas-de-Royalties-31_03_26.pdf | O3: Regimen de caja; planilla anual oficial.
A4: X00003 | B4: 1991-01-01 | C4: 1991-12-31 | D4: year | E4: ITAIPU_ROYALTIES_CASH | F4: ITAIPU | G4: ITAIPU | H4: PY_TREASURY | I4: 77925100 | J4: USD | K4: ITAIPU | L4: OFFICIAL_PRIMARY | M4: OFFICIAL_ACCOUNTING | N4: https://www.itaipu.gov.py/wp-content/uploads/2026/04/03-Planillas-de-Royalties-31_03_26.pdf | O4: Regimen de caja; planilla anual oficial.
A5: X00004 | B5: 1992-01-01 | C5: 1992-12-31 | D5: year | E5: ITAIPU_ROYALTIES_CASH | F5: ITAIPU | G5: ITAIPU | H5: PY_TREASURY | I5: 123886090 | J5: USD | K5: ITAIPU | L5: OFFICIAL_PRIMARY | M5: OFFICIAL_ACCOUNTING | N5: https://www.itaipu.gov.py/wp-content/uploads/2026/04/03-Planillas-de-Royalties-31_03_26.pdf | O5: Regimen de caja; planilla anual oficial.
A6: X00005 | B6: 1993-01-01 | C6: 1993-12-31 | D6: year | E6: ITAIPU_ROYALTIES_CASH | F6: ITAIPU | G6: ITAIPU | H6: PY_TREASURY | I6: 123787990 | J6: USD | K6: ITAIPU | L6: OFFICIAL_PRIMARY | M6: OFFICIAL_ACCOUNTING | N6: https://www.itaipu.gov.py/wp-content/uploads/2026/04/03-Planillas-de-Royalties-31_03_26.pdf | O6: Regimen de caja; planilla anual oficial.
A7: X00006 | B7: 1994-01-01 | C7: 1994-12-31 | D7: year | E7: ITAIPU_ROYALTIES_CASH | F7: ITAIPU | G7: ITAIPU | H7: PY_TREASURY | I7: 160303310 | J7: USD | K7: ITAIPU | L7: OFFICIAL_PRIMARY | M7: OFFICIAL_ACCOUNTING | N7: https://www.itaipu.gov.py/wp-content/uploads/2026/04/03-Planillas-de-Royalties-31_03_26.pdf | O7: Regimen de caja; planilla anual oficial.
A8: X00007 | B8: 1995-01-01 | C8: 1995-12-31 | D8: year | E8: ITAIPU_ROYALTIES_CASH | F8: ITAIPU | G8: ITAIPU | H8: PY_TREASURY | I8: 123154740 | J8: USD | K8: ITAIPU | L8: OFFICIAL_PRIMARY | M8: OFFICIAL_ACCOUNTING | N8: https://www.itaipu.gov.py/wp-content/uploads/2026/04/03-Planillas-de-Royalties-31_03_26.pdf | O8: Regimen de caja; planilla anual oficial.
A9: X00008 | B9: 1996-01-01 | C9: 1996-12-31 | D9: year | E9: ITAIPU_ROYALTIES_CASH | F9: ITAIPU | G9: ITAIPU | H9: PY_TREASURY | I9: 104214460 | J9: USD | K9: ITAIPU | L9: OFFICIAL_PRIMARY | M9: OFFICIAL_ACCOUNTING | N9: https://www.itaipu.gov.py/wp-content/uploads/2026/04/03-Planillas-de-Royalties-31_03_26.pdf | O9: Regimen de caja; planilla anual oficial.
A10: X00009 | B10: 1997-01-01 | C10: 1997-12-31 | D10: year | E10: ITAIPU_ROYALTIES_CASH | F10: ITAIPU | G10: ITAIPU | H10: PY_TREASURY | I10: 163965270 | J10: USD | K10: ITAIPU | L10: OFFICIAL_PRIMARY | M10: OFFICIAL_ACCOUNTING | N10: https://www.itaipu.gov.py/wp-content/uploads/2026/04/03-Planillas-de-Royalties-31_03_26.pdf | O10: Regimen de caja; planilla anual oficial.
A11: X00010 | B11: 1998-01-01 | C11: 1998-12-31 | D11: year | E11: ITAIPU_ROYALTIES_CASH | F11: ITAIPU | G11: ITAIPU | H11: PY_TREASURY | I11: 294175640 | J11: USD | K11: ITAIPU | L11: OFFICIAL_PRIMARY | M11: OFFICIAL_ACCOUNTING | N11: https://www.itaipu.gov.py/wp-content/uploads/2026/04/03-Planillas-de-Royalties-31_03_26.pdf | O11: Regimen de caja; planilla anual oficial.
A12: X00011 | B12: 1999-01-01 | C12: 1999-12-31 | D12: year | E12: ITAIPU_ROYALTIES_CASH | F12: ITAIPU | G12: ITAIPU | H12: PY_TREASURY | I12: 155382560 | J12: USD | K12: ITAIPU | L12: OFFICIAL_PRIMARY | M12: OFFICIAL_ACCOUNTING | N12: https://www.itaipu.gov.py/wp-content/uploads/2026/04/03-Planillas-de-Royalties-31_03_26.pdf | O12: Regimen de caja; planilla anual oficial.
A13: X00012 | B13: 2000-01-01 | C13: 2000-12-31 | D13: year | E13: ITAIPU_ROYALTIES_CASH | F13: ITAIPU | G13: ITAIPU | H13: PY_TREASURY | I13: 147100460 | J13: USD | K13: ITAIPU | L13: OFFICIAL_PRIMARY | M13: OFFICIAL_ACCOUNTING | N13: https://www.itaipu.gov.py/wp-content/uploads/2026/04/03-Planillas-de-Royalties-31_03_26.pdf | O13: Regimen de caja; planilla anual oficial.
... A77: X00076 | B77: 2024-06-17 | C77: 2024-06-17 | D77: event | E77: YACYRETA_GENERATION_RECEIVABLE | F77: YACYRETA | G77: AR | H77: EBY | I77: 92000000 | J77: USD | K77: EBY | L77: OFFICIAL_NEWS | M77: OFFICIAL_ACCOUNTING | N77: https://eby.gov.py/paraguay-recibe-historica-transferencia-record-de-usd-100-000-000-por-cesion-de-energia-de-yacyreta/ | O77: Monto pendiente por generacion reportado por EBY.

Sheet Infrastructure
A1: year | B1: metric_code | C1: value | D1: unit | E1: scope | F1: source_code | G1: authority_class | H1: source_url | I1: notes
A2: 2003 | B2: TX_LINE_500KV | C2: 16 | D2: km | E2: transmission | F2: ANDE | G2: OFFICIAL_PRIMARY | H2: https://www.ande.gov.py/finanzas/2.%20COMPILACION%20ESTADISTICA%202003-2023/ANDE%20-%20Compilacion%20Estadistica%202003-2023.pdf
A3: 2003 | B3: TX_LINE_220KV | C3: 3367 | D3: km | E3: transmission | F3: ANDE | G3: OFFICIAL_PRIMARY | H3: https://www.ande.gov.py/finanzas/2.%20COMPILACION%20ESTADISTICA%202003-2023/ANDE%20-%20Compilacion%20Estadistica%202003-2023.pdf
A4: 2003 | B4: TX_LINE_66KV | C4: 1087 | D4: km | E4: transmission | F4: ANDE | G4: OFFICIAL_PRIMARY | H4: https://www.ande.gov.py/finanzas/2.%20COMPILACION%20ESTADISTICA%202003-2023/ANDE%20-%20Compilacion%20Estadistica%202003-2023.pdf
A5: 2003 | B5: TX_TRANSFORMATION_CAPACITY | C5: 1896 | D5: MVA | E5: transmission | F5: ANDE | G5: OFFICIAL_PRIMARY | H5: https://www.ande.gov.py/finanzas/2.%20COMPILACION%20ESTADISTICA%202003-2023/ANDE%20-%20Compilacion%20Estadistica%202003-2023.pdf
A6: 2003 | B6: DIST_MEDIUM_VOLTAGE_NETWORK | C6: 28642 | D6: km | E6: distribution | F6: ANDE | G6: OFFICIAL_PRIMARY | H6: https://www.ande.gov.py/finanzas/2.%20COMPILACION%20ESTADISTICA%202003-2023/ANDE%20-%20Compilacion%20Estadistica%202003-2023.pdf
A7: 2003 | B7: DIST_TRANSFORMERS_QTY | C7: 34081 | D7: count | E7: distribution | F7: ANDE | G7: OFFICIAL_PRIMARY | H7: https://www.ande.gov.py/finanzas/2.%20COMPILACION%20ESTADISTICA%202003-2023/ANDE%20-%20Compilacion%20Estadistica%202003-2023.pdf
A8: 2003 | B8: DIST_TRANSFORMERS_CAPACITY | C8: 2223 | D8: MVA | E8: distribution | F8: ANDE | G8: OFFICIAL_PRIMARY | H8: https://www.ande.gov.py/finanzas/2.%20COMPILACION%20ESTADISTICA%202003-2023/ANDE%20-%20Compilacion%20Estadistica%202003-2023.pdf
A9: 2004 | B9: TX_LINE_500KV | C9: 16 | D9: km | E9: transmission | F9: ANDE | G9: OFFICIAL_PRIMARY | H9: https://www.ande.gov.py/finanzas/2.%20COMPILACION%20ESTADISTICA%202003-2023/ANDE%20-%20Compilacion%20Estadistica%202003-2023.pdf
A10: 2004 | B10: TX_LINE_220KV | C10: 3367 | D10: km | E10: transmission | F10: ANDE | G10: OFFICIAL_PRIMARY | H10: https://www.ande.gov.py/finanzas/2.%20COMPILACION%20ESTADISTICA%202003-2023/ANDE%20-%20Compilacion%20Estadistica%202003-2023.pdf
A11: 2004 | B11: TX_LINE_66KV | C11: 1140 | D11: km | E11: transmission | F11: ANDE | G11: OFFICIAL_PRIMARY | H11: https://www.ande.gov.py/finanzas/2.%20COMPILACION%20ESTADISTICA%202003-2023/ANDE%20-%20Compilacion%20Estadistica%202003-2023.pdf
A12: 2004 | B12: TX_TRANSFORMATION_CAPACITY | C12: 2008 | D12: MVA | E12: transmission | F12: ANDE | G12: OFFICIAL_PRIMARY | H12: https://www.ande.gov.py/finanzas/2.%20COMPILACION%20ESTADISTICA%202003-2023/ANDE%20-%20Compilacion%20Estadistica%202003-2023.pdf
A13: 2004 | B13: DIST_MEDIUM_VOLTAGE_NETWORK | C13: 29013 | D13: km | E13: distribution | F13: ANDE | G13: OFFICIAL_PRIMARY | H13: https://www.ande.gov.py/finanzas/2.%20COMPILACION%20ESTADISTICA%202003-2023/ANDE%20-%20Compilacion%20Estadistica%202003-2023.pdf
... A82: 2014 | B82: TX_TRANSFORMATION_CAPACITY | C82: 4276 | D82: MVA | E82: transmission | F82: ANDE | G82: OFFICIAL_PRIMARY | H82: https://www.ande.gov.py/finanzas/2.%20COMPILACION%20ESTADISTICA%202003-2023/ANDE%20-%20Compilacion%20Estadistica%202003-2023.pdf
A83: 2014 | B83: DIST_MEDIUM_VOLTAGE_NETWORK | C83: 65141 | D83: km | E83: distribution | F83: ANDE | G83: OFFICIAL_PRIMARY | H83: https://www.ande.gov.py/finanzas/2.%20COMPILACION%20ESTADISTICA%202003-2023/ANDE%20-%20Compilacion%20Estadistica%202003-2023.pdf | I83: Ruptura metodologica desde 2014 por inclusion de obras de autoconstruccion/uso exclusivo.
A84: 2014 | B84: DIST_TRANSFORMERS_QTY | C84: 71312 | D84: count | E84: distribution | F84: ANDE | G84: OFFICIAL_PRIMARY | H84: https://www.ande.gov.py/finanzas/2.%20COMPILACION%20ESTADISTICA%202003-2023/ANDE%20-%20Compilacion%20Estadistica%202003-2023.pdf | I84: Ruptura metodologica desde 2014 por inclusion de obras de autoconstruccion/uso exclusivo.
A85: 2014 | B85: DIST_TRANSFORMERS_CAPACITY | C85: 5300 | D85: MVA | E85: distribution | F85: ANDE | G85: OFFICIAL_PRIMARY | H85: https://www.ande.gov.py/finanzas/2.%20COMPILACION%20ESTADISTICA%202003-2023/ANDE%20-%20Compilacion%20Estadistica%202003-2023.pdf | I85: Ruptura metodologica desde 2014 por inclusion de obras de autoconstruccion/uso exclusivo.
A86: 2015 | B86: TX_LINE_500KV | C86: 364 | D86: km | E86: transmission | F86: ANDE | G86: OFFICIAL_PRIMARY | H86: https://www.ande.gov.py/finanzas/2.%20COMPILACION%20ESTADISTICA%202003-2023/ANDE%20-%20Compilacion%20Estadistica%202003-2023.pdf
A87: 2015 | B87: TX_LINE_220KV | C87: 4172 | D87: km | E87: transmission | F87: ANDE | G87: OFFICIAL_PRIMARY | H87: https://www.ande.gov.py/finanzas/2.%20COMPILACION%20ESTADISTICA%202003-2023/ANDE%20-%20Compilacion%20Estadistica%202003-2023.pdf
A88: 2015 | B88: TX_LINE_66KV | C88: 1305 | D88: km | E88: transmission | F88: ANDE | G88: OFFICIAL_PRIMARY | H88: https://www.ande.gov.py/finanzas/2.%20COMPILACION%20ESTADISTICA%202003-2023/ANDE%20-%20Compilacion%20Estadistica%202003-2023.pdf
A89: 2015 | B89: TX_TRANSFORMATION_CAPACITY | C89: 4656 | D89: MVA | E89: transmission | F89: ANDE | G89: OFFICIAL_PRIMARY | H89: https://www.ande.gov.py/finanzas/2.%20COMPILACION%20ESTADISTICA%202003-2023/ANDE%20-%20Compilacion%20Estadistica%202003-2023.pdf
A90: 2015 | B90: DIST_MEDIUM_VOLTAGE_NETWORK | C90: 65696 | D90: km | E90: distribution | F90: ANDE | G90: OFFICIAL_PRIMARY | H90: https://www.ande.gov.py/finanzas/2.%20COMPILACION%20ESTADISTICA%202003-2023/ANDE%20-%20Compilacion%20Estadistica%202003-2023.pdf | I90: Ruptura metodologica desde 2014 por inclusion de obras de autoconstruccion/uso exclusivo.
A91: 2015 | B91: DIST_TRANSFORMERS_QTY | C91: 74480 | D91: count | E91: distribution | F91: ANDE | G91: OFFICIAL_PRIMARY | H91: https://www.ande.gov.py/finanzas/2.%20COMPILACION%20ESTADISTICA%202003-2023/ANDE%20-%20Compilacion%20Estadistica%202003-2023.pdf | I91: Ruptura metodologica desde 2014 por inclusion de obras de autoconstruccion/uso exclusivo.
A92: 2015 | B92: DIST_TRANSFORMERS_CAPACITY | C92: 5573 | D92: MVA | E92: distribution | F92: ANDE | G92: OFFICIAL_PRIMARY | H92: https://www.ande.gov.py/finanzas/2.%20COMPILACION%20ESTADISTICA%202003-2023/ANDE%20-%20Compilacion%20Estadistica%202003-2023.pdf | I92: Ruptura metodologica desde 2014 por inclusion de obras de autoconstruccion/uso exclusivo.
A93: 2016 | B93: TX_LINE_500KV | C93: 364 | D93: km | E93: transmission | F93: ANDE | G93: OFFICIAL_PRIMARY | H93: https://www.ande.gov.py/finanzas/2.%20COMPILACION%20ESTADISTICA%202003-2023/ANDE%20-%20Compilacion%20Estadistica%202003-2023.pdf
A94: 2016 | B94: TX_LINE_220KV | C94: 4529 | D94: km | E94: transmission | F94: ANDE | G94: OFFICIAL_PRIMARY | H94: https://www.ande.gov.py/finanzas/2.%20COMPILACION%20ESTADISTICA%202003-2023/ANDE%20-%20Compilacion%20Estadistica%202003-2023.pdf
A95: 2016 | B95: TX_LINE_66KV | C95: 1261 | D95: km | E95: transmission | F95: ANDE | G95: OFFICIAL_PRIMARY | H95: https://www.ande.gov.py/finanzas/2.%20COMPILACION%20ESTADISTICA%202003-2023/ANDE%20-%20Compilacion%20Estadistica%202003-2023.pdf
A96: 2016 | B96: TX_TRANSFORMATION_CAPACITY | C96: 4900 | D96: MVA | E96: transmission | F96: ANDE | G96: OFFICIAL_PRIMARY | H96: https://www.ande.gov.py/finanzas/2.%20COMPILACION%20ESTADISTICA%202003-2023/ANDE%20-%20Compilacion%20Estadistica%202003-2023.pdf
A97: 2016 | B97: DIST_MEDIUM_VOLTAGE_NETWORK | C97: 66339 | D97: km | E97: distribution | F97: ANDE | G97: OFFICIAL_PRIMARY | H97: https://www.ande.gov.py/finanzas/2.%20COMPILACION%20ESTADISTICA%202003-2023/ANDE%20-%20Compilacion%20Estadistica%202003-2023.pdf | I97: Ruptura metodologica desde 2014 por inclusion de obras de autoconstruccion/uso exclusivo.
A98: 2016 | B98: DIST_TRANSFORMERS_QTY | C98: 76972 | D98: count | E98: distribution | F98: ANDE | G98: OFFICIAL_PRIMARY | H98: https://www.ande.gov.py/finanzas/2.%20COMPILACION%20ESTADISTICA%202003-2023/ANDE%20-%20Compilacion%20Estadistica%202003-2023.pdf | I98: Ruptura metodologica desde 2014 por inclusion de obras de autoconstruccion/uso exclusivo.
A99: 2016 | B99: DIST_TRANSFORMERS_CAPACITY | C99: 5791 | D99: MVA | E99: distribution | F99: ANDE | G99: OFFICIAL_PRIMARY | H99: https://www.ande.gov.py/finanzas/2.%20COMPILACION%20ESTADISTICA%202003-2023/ANDE%20-%20Compilacion%20Estadistica%202003-2023.pdf | I99: Ruptura metodologica desde 2014 por inclusion de obras de autoconstruccion/uso exclusivo.
A100: 2017 | B100: TX_LINE_500KV | C100: 364 | D100: km | E100: transmission | F100: ANDE | G100: OFFICIAL_PRIMARY | H100: https://www.ande.gov.py/finanzas/2.%20COMPILACION%20ESTADISTICA%202003-2023/ANDE%20-%20Compilacion%20Estadistica%202003-2023.pdf
A101: 2017 | B101: TX_LINE_220KV | C101: 4564 | D101: km | E101: transmission | F101: ANDE | G101: OFFICIAL_PRIMARY | H101: https://www.ande.gov.py/finanzas/2.%20COMPILACION%20ESTADISTICA%202003-2023/ANDE%20-%20Compilacion%20Estadistica%202003-2023.pdf
A102: 2017 | B102: TX_LINE_66KV | C102: 1291 | D102: km | E102: transmission | F102: ANDE | G102: OFFICIAL_PRIMARY | H102: https://www.ande.gov.py/finanzas/2.%20COMPILACION%20ESTADISTICA%202003-2023/ANDE%20-%20Compilacion%20Estadistica%202003-2023.pdf
A103: 2017 | B103: TX_TRANSFORMATION_CAPACITY | C103: 5680 | D103: MVA | E103: transmission | F103: ANDE | G103: OFFICIAL_PRIMARY | H103: https://www.ande.gov.py/finanzas/2.%20COMPILACION%20ESTADISTICA%202003-2023/ANDE%20-%20Compilacion%20Estadistica%202003-2023.pdf
A104: 2017 | B104: DIST_MEDIUM_VOLTAGE_NETWORK | C104: 67354 | D104: km | E104: distribution | F104: ANDE | G104: OFFICIAL_PRIMARY | H104: https://www.ande.gov.py/finanzas/2.%20COMPILACION%20ESTADISTICA%202003-2023/ANDE%20-%20Compilacion%20Estadistica%202003-2023.pdf | I104: Ruptura metodologica desde 2014 por inclusion de obras de autoconstruccion/uso exclusivo.
A105: 2017 | B105: DIST_TRANSFORMERS_QTY | C105: 79920 | D105: count | E105: distribution | F105: ANDE | G105: OFFICIAL_PRIMARY | H105: https://www.ande.gov.py/finanzas/2.%20COMPILACION%20ESTADISTICA%202003-2023/ANDE%20-%20Compilacion%20Estadistica%202003-2023.pdf | I105: Ruptura metodologica desde 2014 por inclusion de obras de autoconstruccion/uso exclusivo.
A106: 2017 | B106: DIST_TRANSFORMERS_CAPACITY | C106: 6000 | D106: MVA | E106: distribution | F106: ANDE | G106: OFFICIAL_PRIMARY | H106: https://www.ande.gov.py/finanzas/2.%20COMPILACION%20ESTADISTICA%202003-2023/ANDE%20-%20Compilacion%20Estadistica%202003-2023.pdf | I106: Ruptura metodologica desde 2014 por inclusion de obras de autoconstruccion/uso exclusivo.
A107: 2018 | B107: TX_LINE_500KV | C107: 711 | D107: km | E107: transmission | F107: ANDE | G107: OFFICIAL_PRIMARY | H107: https://www.ande.gov.py/finanzas/2.%20COMPILACION%20ESTADISTICA%202003-2023/ANDE%20-%20Compilacion%20Estadistica%202003-2023.pdf
A108: 2018 | B108: TX_LINE_220KV | C108: 4575 | D108: km | E108: transmission | F108: ANDE | G108: OFFICIAL_PRIMARY | H108: https://www.ande.gov.py/finanzas/2.%20COMPILACION%20ESTADISTICA%202003-2023/ANDE%20-%20Compilacion%20Estadistica%202003-2023.pdf
A109: 2018 | B109: TX_LINE_66KV | C109: 1345 | D109: km | E109: transmission | F109: ANDE | G109: OFFICIAL_PRIMARY | H109: https://www.ande.gov.py/finanzas/2.%20COMPILACION%20ESTADISTICA%202003-2023/ANDE%20-%20Compilacion%20Estadistica%202003-2023.pdf
A110: 2018 | B110: TX_TRANSFORMATION_CAPACITY | C110: 6115 | D110: MVA | E110: transmission | F110: ANDE | G110: OFFICIAL_PRIMARY | H110: https://www.ande.gov.py/finanzas/2.%20COMPILACION%20ESTADISTICA%202003-2023/ANDE%20-%20Compilacion%20Estadistica%202003-2023.pdf
A111: 2018 | B111: DIST_MEDIUM_VOLTAGE_NETWORK | C111: 67815 | D111: km | E111: distribution | F111: ANDE | G111: OFFICIAL_PRIMARY | H111: https://www.ande.gov.py/finanzas/2.%20COMPILACION%20ESTADISTICA%202003-2023/ANDE%20-%20Compilacion%20Estadistica%202003-2023.pdf | I111: Ruptura metodologica desde 2014 por inclusion de obras de autoconstruccion/uso exclusivo.
A112: 2018 | B112: DIST_TRANSFORMERS_QTY | C112: 81942 | D112: count | E112: distribution | F112: ANDE | G112: OFFICIAL_PRIMARY | H112: https://www.ande.gov.py/finanzas/2.%20COMPILACION%20ESTADISTICA%202003-2023/ANDE%20-%20Compilacion%20Estadistica%202003-2023.pdf | I112: Ruptura metodologica desde 2014 por inclusion de obras de autoconstruccion/uso exclusivo.
